Workbook
Name _Hlk127452852: Gajendra!$L$8
Name _Hlk133227457: Yogesh!$I$86
Name _Hlk147505528: Yogesh!$L$61

Sheet Summary
B1: KARDEX LCS : LIVE OFFER FUNNEL,ACTUALS, DEVIATIONS - 2025 | S1: =((T1*94)/12)*1000 -> 23515667 | T1: 3002 | U1: =T1/12 -> 250.16667
B3: Offers Highlights | Q3: Forecast | S3: WEST | T3: SOUTH | U3: NORTH | V3: EAST
Q4: January | R4: =SUM(S4:V4) -> 45050692 | S4: =SUM(Yogesh!AE3+Ashraf!AE3+Rahul!AE3+Minesh!AE3) -> 15096544 | T4: =SUM(Gajendra!AF5+Pradeep!AF4+Sasi!AF4) -> 16046921 | U4: =SUM(Vinay!AF3+Nitin!AD4) -> 13078516 | V4: =Pankaj!AF3 -> 828711 | AA4: From Day 1 of each Month
B5: Zone | C5: No. of Offers | D5: Offers Value | E5: Orders Received | F5: Open Funnel | G5: Order Booking | H5: BU for Booking /2025 | I5: % | J5: Balance BU | Q5: February | R5: =SUM(S5:V5) -> 21122869 | S5: =SUM(Yogesh!AE4+Ashraf!AE4+Rahul!AE4+Minesh!AE4) -> 7548651 | T5: =SUM(Gajendra!AF6+Pradeep!AF5+Sasi!AF5) -> 6939439.8 | U5: =SUM(Vinay!AF4+Nitin!AD5) -> 6400898 | V5: =Pankaj!AF4 -> 233880 | W5: Q1 Forecast | X5: Q1 BU | Y5: Dev | AA5: Month | AB5: Forecast | AC5: Euro | AD5: Start of the Month | AE5: WEST | AF5: SOUTH | AG5: NORTH | AH5: EAST
B6: WEST | C6: =Yogesh!B4+Ashraf!B5+Minesh!B4+Rahul!B4 -> 529 | D6: =C28 -> 201107949 | E6: =D28 -> 132310920 | F6: =Yogesh!V5+Ashraf!V6+Rahul!V5+Minesh!V5 -> 47022033 | G6: =E28 -> 128881401 | H6: 121446000 | I6: =(H6-G6)/-H6 -> 0.061223927 | J6: =H6-G6 -> -7435401 | Q6: March | R6: =SUM(S6:V6) -> 24059432 | S6: =SUM(Yogesh!AE5+Ashraf!AE5+Rahul!AE5+Minesh!AE5) -> 10061774 | T6: =SUM(Gajendra!AF7+Pradeep!AF6+Sasi!AF6) -> 10184994 | U6: =SUM(Vinay!AF5+Nitin!AD6) -> 2708802 | V6: =Pankaj!AF5 -> 1103862 | W6: =SUM(R4:R6) -> 90232993 | X6: =S1*3 -> 70547000 | Y6: =SUM(W6-X6)/X6 -> 0.27904791 | AA6: FEB | AB6: =SUM(AE6:AH6) -> 39877565 | AC6: =(AB6/$S$97)/1000 -> 428.79102 | AD6: Febrauary | AE6: 9286760 | AF6: 12347508 | AG6: 17539857 | AH6: 703440
B7: SOUTH | C7: =Gajendra!B5+Pradeep!B4+Sasi!B4 -> 354 | D7: =C45 -> 1.7686402e+08 | E7: =D45 -> 95676327 | F7: =Gajendra!V6+Pradeep!V5+Sasi!V5 -> 63631579 | G7: =E45 -> 100601530 | H7: 107487000 | I7: =(H7-G7)/-H7 -> -0.06405863 | J7: =H7-G7 -> 6885470 | Q7: April | R7: =SUM(S7:V7) -> 61495167 | S7: =SUM(Yogesh!AE6+Ashraf!AE6+Rahul!AE6+Minesh!AE6) -> 38455613 | T7: =SUM(Gajendra!AF8+Pradeep!AF7+Sasi!AF7) -> 13886379 | U7: =SUM(Vinay!AF6+Nitin!AD7) -> 9153175 | V7: =Pankaj!AF6 -> 0 | AA7: MAR | AB7: =SUM(AE7:AH7) -> 24653350 | AC7: =(AB7/$S$97)/1000 -> 265.08979 | AD7: March | AE7: 8359399 | AF7: 15286310 | AG7: 1007641 | AH7: 0
B8: NORTH | C8: =Nitin!B4+Vinay!B4 -> 172 | D8: =C62 -> 101408542 | E8: =D62 -> 25743743 | F8: =Vinay!V5+Nitin!V5 -> 43216777 | G8: =E62 -> 31713749 | H8: 39086000 | I8: =(H8-G8)/-H8 -> -0.18861615 | J8: =H8-G8 -> 7372251 | Q8: May | R8: =SUM(S8:V8) -> 26287547 | S8: =SUM(Yogesh!AE7+Ashraf!AE7+Rahul!AE7+Minesh!AE7) -> 15750042 | T8: =SUM(Gajendra!AF9+Pradeep!AF8+Sasi!AF8) -> 4930834.8 | U8: =Vinay!AF7+Nitin!AF8 -> 4567340 | V8: =Pankaj!AF7 -> 1039330 | W8: Q2 Forecast | X8: Q2 BU | Y8: Dev | AA8: APR | AB8: =SUM(AE8:AH8) -> 53554063 | AC8: =(AB8/$S$97)/1000 -> 575.85014 | AD8: April | AE8: 35536379 | AF8: 16382704 | AG8: 1634980 | AH8: 0
B9: EAST | C9: =Pankaj!B4 -> 29 | D9: =C79 -> 12643664 | E9: =D79 -> 4782292.4 | F9: =Pankaj!V5 -> 7778194.6 | G9: =E79 -> 5968893 | H9: 11167000 | I9: =(H9-G9)/-H9 -> -0.46548822 | J9: =H9-G9 -> 5198107 | Q9: June | R9: =SUM(S9:V9) -> 25930489 | S9: =SUM(Yogesh!AE8+Ashraf!AE8+Rahul!AE8+Minesh!AE8) -> 16934646 | T9: =SUM(Gajendra!AF10+Pradeep!AF9+Sasi!AF9) -> 3121332 | U9: =SUM(Vinay!AF8+Nitin!AF9) -> 5874511 | V9: =Pankaj!AF8 -> 0 | W9: =SUM(R7:R9) -> 1.137132e+08 | X9: =S1*3 -> 70547000 | Y9: =SUM(W9-X9)/X9 -> 0.61187864 | AA9: MAY | AB9: =SUM(AE9:AH9) -> 45486916 | AC9: =(AB9/$S$97)/1000 -> 489.10662 | AD9: May | AE9: 27968195 | AF9: 9505075.8 | AG9: 6429763 | AH9: 1583882
B10: Total | C10: =SUM(C6:C9) -> 1084 | D10: =SUM(D6:D9) -> 4.9202418e+08 | E10: =SUM(E6:E9) -> 2.5851328e+08 | F10: =SUM(F6:F9) -> 1.6164858e+08 | G10: =SUM(G6:G9) -> 267165573 | H10: =SUM(H6:H9) -> 279186000 | I10: =(H10-G10)/-H10 -> -0.043055264 | J10: =H10-G10 -> 12020427 | Q10: July | R10: =SUM(S10:V10) -> 25780849 | S10: =SUM(Yogesh!AE9+Ashraf!AE9+Rahul!AE9+Minesh!AE9) -> 8768673 | T10: =SUM(Gajendra!AF11+Pradeep!AF10+Sasi!AF10) -> 14634990 | U10: =SUM(Vinay!AD12+Nitin!AD10) -> 1972332 | V10: =Pankaj!AF9 -> 404854 | AA10: JUN | AB10: =SUM(AE10:AH10) -> 37217079 | AC10: =(AB10/$S$97)/1000 -> 400.18365 | AD10: June | AE10: 24125701 | AF10: 11748673 | AG10: 1203007 | AH10: 139698
Q11: August | R11: =SUM(S11:V11) -> 38786728 | S11: =SUM(Yogesh!AE10+Ashraf!AE10+Rahul!AE10+Minesh!AE10) -> 13636734 | T11: =SUM(Gajendra!AF12+Pradeep!AF11+Sasi!AF11) -> 19450949 | U11: =SUM(Vinay!AF10+Nitin!AD11) -> 5538869 | V11: =Pankaj!AF10 -> 160176 | W11: Q3 Forecast | X11: Q3 BU | Y11: Dev | AA11: JULY | AB11: =SUM(AE11:AH11) -> 23876033 | AC11: =(AB11/$S$97)/1000 -> 256.73154 | AD11: July | AE11: 8954264 | AF11: 14251915 | AG11: 265000 | AH11: 404854
B12: NOTE : * Marked fields will be filled by Girija | Q12: September | R12: =SUM(S12:V12) -> 35015662 | S12: =SUM(Yogesh!AE11+Ashraf!AE11+Rahul!AE11+Minesh!AE11) -> 9602168 | T12: =SUM(Gajendra!AF13+Pradeep!AF12+Sasi!AF12) -> 16361962 | U12: =SUM(Vinay!AF10+Nitin!AD12) -> 8870957 | V12: =Pankaj!AF11 -> 180576 | W12: =SUM(R10:R12) -> 99583240 | X12: =S1*3 -> 70547000 | Y12: =SUM(W12-X12)/X12 -> 0.41158717 | AA12: AUG | AB12: =SUM(AE12:AH12) -> 48070994 | AC12: =(AB12/$S$97)/1000 -> 516.89241 | AD12: August | AE12: 20686301 | AF12: 25365441 | AG12: 1879554 | AH12: 139698
H13: 121446000 | K13: HIT RATE | L13: =D28/C28 -> 0.65790995 | Q13: October | R13: =SUM(S13:V13) -> 34898550 | S13: =SUM(Yogesh!AE12+Ashraf!AE12+Rahul!AE12+Minesh!AE12) -> 9102357 | T13: =SUM(Gajendra!AF14+Pradeep!AF13+Sasi!AF13) -> 16463774 | U13: =SUM(Vinay!AF11+Nitin!AD13) -> 8462431 | V13: =Pankaj!AF12 -> 869988 | AA13: Sept | AB13: =SUM(AE13:AH13) -> 0 | AC13: =(AB13/$S$97)/1000 -> 0 | AD13: September
B14: WEST | Q14: November | R14: =SUM(S14:V14) -> 45443423 | S14: =SUM(Yogesh!AE13+Ashraf!AE13+Rahul!AE13+Minesh!AE13) -> 18982678 | T14: =SUM(Gajendra!AF15+Pradeep!AF14+Sasi!AF14) -> 20007016 | U14: =SUM(Vinay!AF12+Nitin!AD14) -> 3245053 | V14: =Pankaj!AF13 -> 3208676 | W14: Q4 Forecast | X14: Q4 BU | Y14: Dev | AA14: Oct | AB14: =SUM(AE14:AH14) -> 0 | AC14: =(AB14/$S$97)/1000 -> 0 | AD14: October
B15: Month | C15: Offers/Value | D15: Order Received | E15: *Orders Booked | F15: Dev OR vs Booked | G15: *Orders In-Hand | H15: BU/Monthly | I15: Booked vs BU | J15: % Dev | K15: Offer BU Monthly | L15: % Dev | Q15: December | R15: =SUM(S15:V15) -> 71156885 | S15: =SUM(Yogesh!AE14+Ashraf!AE14+Rahul!AE14+Minesh!AE14) -> 34836169 | T15: =SUM(Gajendra!AF16+Pradeep!AF15+Sasi!AF15) -> 32235999 | U15: =SUM(Vinay!AF13+Nitin!AD15) -> 519444 | V15: =Pankaj!AF14 -> 3565273 | W15: =SUM(R13:R15) -> 1.5149886e+08 | X15: =S1*3 -> 70547000 | Y15: =SUM(W15-X15)/X15 -> 1.1474883 | AA15: Nov | AB15: =SUM(AE15:AH15) -> 0 | AC15: =(AB15/$S$97)/1000 -> 0 | AD15: November
B16: Januray | C16: =Yogesh!AC3+Ashraf!AC3+Rahul!AC3+Minesh!AC3 -> 42269479 | D16: =Yogesh!AD3+Ashraf!AD3+Rahul!AD3+Minesh!AD3 -> 13049548 | E16: 7811608 | F16: =D16-E16 -> 5237940 | H16: =$H$13/12 -> 10120500 | I16: =H16-E16 -> 2308892 | J16: =(E16-H16)/E16 -> -0.29557192 | K16: =H16*4 -> 40482000 | L16: =(K16-C16)/K16 -> -0.044154908 | AA16: Dec | AB16: =SUM(AE16:AH16) -> 0 | AC16: =(AB16/$S$97)/1000 -> 0 | AD16: December
B17: Febraury | C17: =Yogesh!AC4+Ashraf!AC4+Rahul!AC4+Minesh!AC4 -> 14144161 | D17: =Yogesh!AD4+Ashraf!AD4+Rahul!AD4+Minesh!AD4 -> 5515905 | E17: 6378607 | F17: =D17-E17 -> -862702 | G17: 4650252 | H17: =$H$13/12 -> 10120500 | I17: =H17-E17 -> 3741893 | J17: =(E17-H17)/E17 -> -0.58663169 | K17: =H17*4 -> 40482000 | L17: =(K17-C17)/K17 -> 0.65060617 | Q17: Product type | R17: Yogesh | S17: Ashraf | T17: Rahul | U17: Minesh | V17: WEST | X17: Product type | Y17: Total of All Zones
B18: March | C18: =Yogesh!AC5+Ashraf!AC5+Rahul!AC5+Minesh!AC5 -> 36601272 | D18: =Yogesh!AD5+Ashraf!AD5+Rahul!AD5+Minesh!AD5 -> 12619158 | E18: 12737918 | F18: =D18-E18 -> -118760 | G18: 6798827 | H18: =$H$13/12 -> 10120500 | I18: =H18-E18 -> -2617418 | J18: =(E18-H18)/E18 -> 0.2054824 | K18: =H18*4 -> 40482000 | L18: =(K18-C18)/K18 -> 0.09586305 | Q18: Contract | R18: =SUMIF(Yogesh!$J$7:$J$121,"Contract",Yogesh!$N$7:$N$122) -> 6066220 | S18: =SUMIF(Ashraf!$J$7:$J$123,"Contract",Ashraf!$N$7:$N$124) -> 5656160 | T18: =SUMIF(Rahul!$J$7:$J$121,"Contract",Rahul!$N$7:$N$122) -> 6519383 | U18: =SUMIF(Minesh!$J$7:$J$121,"Contract",Minesh!$N$7:$N$122) -> 6337225 | V18: =SUM(R18:U18) -> 24578988 | X18: Contract | Y18: =SUM(R18:X18) -> 49157976
B19: April | C19: =Yogesh!AC6+Ashraf!AC6+Rahul!AC6+Minesh!AC6 -> 9380360 | D19: =Yogesh!AD6+Ashraf!AD6+Rahul!AD6+Minesh!AD6 -> 35250947 | E19: 13101611 | F19: =D19-E19 -> 22149336 | G19: 28944762 | H19: =$H$13/12 -> 10120500 | I19: =H19-E19 -> -2981111 | J19: =(E19-H19)/E19 -> 0.22753774 | K19: =H19*4 -> 40482000 | L19: =(K19-C19)/K19 -> 0.76828319 | Q19: BD Spare | R19: =SUMIF(Yogesh!$J$8:$J$122,"BD Spare",Yogesh!$N$8:S34) -> 532632 | S19: =SUMIF(Ashraf!$J$8:$J$124,"BD Spare",Ashraf!$N$8:T35) -> 401990 | T19: =SUMIF(Rahul!$J$8:$J$122,"BD Spare",Rahul!$N$8:U34) -> 145900 | U19: =SUMIF(Minesh!$J$8:$J$122,"BD Spare",Minesh!$N$8:V34) -> 0 | V19: =SUM(R19:U19) -> 1080522 | X19: BD Spare | Y19: =SUM(R19:X19) -> 2161044
B20: May | C20: =Yogesh!AC7+Ashraf!AC7+Rahul!AC7+Minesh!AC7 -> 18380018 | D20: =Yogesh!AD7+Ashraf!AD7+Rahul!AD7+Minesh!AD7 -> 10887971 | E20: 28895197 | F20: =D20-E20 -> -18007226 | G20: 7234307 | H20: =$H$13/12 -> 10120500 | I20: =H20-E20 -> -18774697 | J20: =(E20-H20)/E20 -> 0.64975148 | K20: =H20*4 -> 40482000 | L20: =(K20-C20)/K20 -> 0.5459706 | Q20: SPP | R20: =SUMIF(Yogesh!$J$9:$J$123,"SPP",Yogesh!$N$9:$N$124) -> 5411008 | S20: =SUMIF(Ashraf!$J$9:$J$125,"SPP",Ashraf!$N$9:$N$126) -> 8788209 | T20: =SUMIF(Rahul!$J$9:$J$123,"SPP",Rahul!$N$9:$N$124) -> 4159739 | U20: =SUMIF(Minesh!$J$9:$J$123,"SPP",Minesh!$N$9:$N$124) -> 6573780 | V20: =SUM(R20:U20) -> 24932736 | X20: SPP | Y20: =SUM(R20:X20) -> 49865472
B21: June | C21: =Yogesh!AC8+Ashraf!AC8+Rahul!AC8+Minesh!AC8 -> 7996136 | D21: =Yogesh!AD8+Ashraf!AD8+Rahul!AD8+Minesh!AD8 -> 12237563 | E21: 9159288 | F21: =D21-E21 -> 3078275 | G21: 12189407 | H21: =$H$13/12 -> 10120500 | I21: =H21-E21 -> 961212 | J21: =(E21-H21)/E21 -> -0.10494397 | K21: =H21*4 -> 40482000 | L21: =(K21-C21)/K21 -> 0.80247676 | Q21: Relocation | R21: =SUMIF(Yogesh!$J$10:$J$124,"Relocation",Yogesh!$N$10:$N$125) -> 3348000 | S21: =SUMIF(Ashraf!$J$10:$J$126,"Relocation",Ashraf!$N$10:$N$127) -> 2065000 | T21: =SUMIF(Rahul!$J$10:$J$124,"Relocation",Rahul!$N$10:$N$125) -> 355000 | U21: =SUMIF(Minesh!$J$10:$J$124,"Relocation",Minesh!$N$10:$N$125) -> 1460000 | V21: =SUM(R21:U21) -> 7228000 | X21: Relocation | Y21: =SUM(R21:X21) -> 14456000
B22: July | C22: =Yogesh!AC9+Ashraf!AC9+Rahul!AC9+Minesh!AC9 -> 9993977 | D22: =Yogesh!AD9+Ashraf!AD9+Rahul!AD9+Minesh!AD9 -> 8059011 | E22: 11691476 | F22: =D22-E22 -> -3632465 | G22: 9044062 | H22: =$H$13/12 -> 10120500 | I22: =H22-E22 -> -1570976 | J22: =(E22-H22)/E22 -> 0.13436935 | K22: =H22*4 -> 40482000 | L22: =(K22-C22)/K22 -> 0.75312541 | Q22: Software | R22: =SUMIF(Yogesh!$J$11:$J$125,"Software",Yogesh!$N$11:$N$126) -> 1378000 | S22: =SUMIF(Ashraf!$J$11:$J$127,"Software",Ashraf!$N$11:$N$128) -> 0 | T22: =SUMIF(Rahul!$J$11:$J$125,"Software",Rahul!$N$11:$N$126) -> 0 | U22: =SUMIF(Minesh!$J$11:$J$125,"Software",Minesh!$N$11:$N$126) -> 0 | V22: =SUM(R22:U22) -> 1378000 | X22: Software | Y22: =SUM(R22:X22) -> 2756000
B23: August | C23: =Yogesh!AC10+Ashraf!AC10+Rahul!AC10+Minesh!AC10 -> 13796991 | D23: =Yogesh!AD10+Ashraf!AD10+Rahul!AD10+Minesh!AD10 -> 8512281 | E23: 9427885 | F23: =D23-E23 -> -915604 | G23: 10386133 | H23: =$H$13/12 -> 10120500 | I23: =H23-E23 -> 692615 | J23: =(E23-H23)/E23 -> -0.073464515 | K23: =H23*4 -> 40482000 | L23: =(K23-C23)/K23 -> 0.65918208 | Q23: BD Charges | R23: =SUMIF(Yogesh!$J$12:$J$126,"BD Charges",Yogesh!$N$12:$N$127) -> 22500 | S23: =SUMIF(Ashraf!$J$12:$J$128,"BD Charges",Ashraf!$N$12:$N$129) -> 0 | T23: =SUMIF(Rahul!$J$12:$J$126,"BD Charges",Rahul!$N$12:$N$127) -> 80000 | U23: =SUMIF(Minesh!$J$12:$J$126,"BD Charges",Minesh!$N$12:$N$127) -> 106000 | V23: =SUM(R23:U23) -> 208500 | X23: BD Charges | Y23: =SUM(R23:X23) -> 417000
B24: September | C24: =Yogesh!AC11+Ashraf!AC11+Rahul!AC11+Minesh!AC11 -> 13836161 | D24: =Yogesh!AD11+Ashraf!AD11+Rahul!AD11+Minesh!AD11 -> 5645535 | E24: 9911793 | F24: =D24-E24 -> -4266258 | G24: 6448434 | H24: =$H$13/12 -> 10120500 | I24: =H24-E24 -> 208707 | J24: =(E24-H24)/E24 -> -0.021056432 | K24: =H24*4 -> 40482000 | L24: =(K24-C24)/K24 -> 0.65821449 | Q24: Retrofit kit | R24: =SUMIF(Yogesh!$J$13:$J$127,"Retrofit kit",Yogesh!$N$13:$N$128) -> 25643885 | S24: =SUMIF(Ashraf!$J$13:$J$129,"Retrofit kit",Ashraf!$N$13:$N$130) -> 0 | T24: =SUMIF(Rahul!$J$13:$J$127,"Retrofit kit",Rahul!$N$13:$N$128) -> 2638700 | U24: =SUMIF(Minesh!$J$13:$J$127,"Minesh",Rahul!$N$13:$N$128) -> 0 | V24: =SUM(R24:U24) -> 28282585 | X24: Retrofit kit | Y24: =SUM(R24:X24) -> 56565170
B25: October | C25: =Yogesh!AC12+Ashraf!AC12+Rahul!AC12+Minesh!AC12 -> 11308134 | D25: =Yogesh!AD12+Ashraf!AD12+Rahul!AD12+Minesh!AD12 -> 8712367 | E25: 8097887 | F25: =D25-E25 -> 614480 | G25: 6480022 | H25: =$H$13/12 -> 10120500 | I25: =H25-E25 -> 2022613 | J25: =(E25-H25)/E25 -> -0.24977046 | K25: =H25*4 -> 40482000 | L25: =(K25-C25)/K25 -> 0.72066266 | Q25: Upgrade kit | R25: =SUMIF(Yogesh!$J$14:$J$128,"Upgrade kit",Yogesh!$N$14:$N$129) -> 112959 | S25: =SUMIF(Ashraf!$J$14:$J$130,"Upgrade kit",Ashraf!$N$14:$N$131) -> 1499595 | T25: =SUMIF(Rahul!$J$14:$J$128,"Upgrade kit",Rahul!$N$14:$N$129) -> 0 | U25: =SUMIF(Minesh!$J$14:$J$128,"Upgrade kit",Minesh!$N$14:$N$129) -> 0 | V25: =SUM(R25:U25) -> 1612554 | X25: Upgrade kit | Y25: =SUM(R25:X25) -> 3225108
B26: November | C26: =Yogesh!AC13+Ashraf!AC13+Rahul!AC13+Minesh!AC13 -> 14607524 | D26: =Yogesh!AD13+Ashraf!AD13+Rahul!AD13+Minesh!AD13 -> 6184871 | E26: 5314010 | F26: =D26-E26 -> 870861 | G26: 4773358 | H26: =$H$13/12 -> 10120500 | I26: =H26-E26 -> 4806490 | J26: =(E26-H26)/E26 -> -0.90449397 | K26: =H26*4 -> 40482000 | L26: =(K26-C26)/K26 -> 0.63916002 | Q26: Training | R26: =SUMIF(Yogesh!$J$15:$J$129,"Training",Yogesh!$N$15:$N$130) -> 0 | S26: =SUMIF(Ashraf!$J$15:$J$131,"Training",Ashraf!$N$15:$N$132) -> 0 | T26: =SUMIF(Rahul!$J$15:$J$129,"Training",Rahul!$N$15:$N$130) -> 0 | U26: =SUMIF(Minesh!$J$15:$J$129,"Training",Minesh!$N$15:$N$130) -> 0 | V26: =SUM(R26:U26) -> 0 | X26: Training | Y26: =SUM(R26:X26) -> 0
B27: December | C27: =Yogesh!AC14+Ashraf!AC14+Rahul!AC14+Minesh!AC14 -> 8793736 | D27: =Yogesh!AD14+Ashraf!AD14+Rahul!AD14+Minesh!AD14 -> 5635763 | E27: 6354121 | F27: =D27-E27 -> -718358 | G27: 7368251 | H27: =$H$13/12 -> 10120500 | I27: =H27-E27 -> 3766379 | J27: =(E27-H27)/E27 -> -0.59274587 | K27: =H27*4 -> 40482000 | L27: =(K27-C27)/K27 -> 0.78277417 | Q27: Midlife Upgrade | R27: =SUMIF(Yogesh!$J$16:$J$130,"Midlife Upgrade",Yogesh!$N$16:$N$131) -> 0 | S27: =SUMIF(Ashraf!$J$16:$J$132,"Midlife Upgrade",Ashraf!$N$16:$N$133) -> 1846770 | T27: =SUMIF(Rahul!$J$16:$J$130,"Midlife Upgrade",Rahul!$N$16:$N$131) -> 15947586 | U27: =SUMIF(Minesh!$J$16:$J$130,"Midlife Upgrade",Minesh!$N$16:$N$131) -> 694970 | V27: =SUM(R27:U27) -> 18489326 | X27: Midlife Upgrade | Y27: =SUM(R27:X27) -> 36978652
B28: Total | C28: =SUM(C16:C27) -> 201107949 | D28: =SUM(D16:D27) -> 132310920 | E28: =SUM(E16:E27) -> 128881401 | F28: =SUM(F16:F27) -> 3429519 | H28: =SUM(H16:H27) -> 121446000 | I28: =SUM(I16:I27) -> -7435401 | K28: =SUM(K16:K27) -> 485784000 | L28: =(K28-C28)/K28 -> 0.58601364 | Q28: Total | R28: =SUM(R18:R27) -> 42515204 | S28: =SUM(S18:S27) -> 20257724 | T28: =SUM(T18:T27) -> 29846308 | U28: =SUM(U18:U27) -> 15171975 | V28: =SUM(R28:U28) -> 107791211 | X28: Total | Y28: =SUM(Y18:Y27) -> 215582422
H30: 107487000 | K30: HIT RATE | L30: =D45/C45 -> 0.5409598 | Q30: Product type | R30: Gajendra | S30: Pradeep | T30: Sasi | V30: South
B31: SOUTH | Q31: Contract | R31: =SUMIF(Gajendra!$J$7:$J$109,"Contract",Gajendra!$N$7:$N$110) -> 5393822.9 | S31: =SUMIF(Pradeep!$J$7:$J$121,"Contract",Pradeep!$N$7:$N$122) -> 5735921 | T31: =SUMIF(Sasi!$J$7:$J$125,"Contract",Sasi!$N$7:$N$126) -> 7382731 | V31: =SUM(R31:U31) -> 18512475
B32: Month | C32: Offers/Value | D32: Order Received | E32: *Order Booked | F32: Dev OR vs Booked | G32: *Orders In-Hand | H32: BU/Monthly | I32: Booked vs BU | J32: % Dev | K32: Offer BU Monthly | L32: % Dev | Q32: BD Spare | R32: =SUMIF(Gajendra!$J$8:$J$110,"BD Spare",Gajendra!$N$8:W34) -> 1640845.2 | S32: =SUMIF(Pradeep!$J$8:$J$122,"BD Spare",Pradeep!$N$8:X34) -> 0 | T32: =SUMIF(Sasi!$J$9:$J$126,"BD Spare",Sasi!$N$9:Y35) -> 1894886 | V32: =SUM(R32:U32) -> 3535731.2
B33: Januray | C33: =Gajendra!AD5+Pradeep!AD4+Sasi!AD4 -> 25413870 | D33: =Gajendra!AE5+Pradeep!AE4+Sasi!AE4 -> 15621491 | E33: 7293960 | F33: =D33-E33 -> 8327531.3 | H33: =$H$30/12 -> 8957250 | I33: =H33-E33 -> 1663290 | J33: =(E33-H33)/E33 -> -0.22803662 | K33: =H33*4 -> 35829000 | L33: =(K33-C33)/K33 -> 0.29068995 | Q33: SPP | R33: =SUMIF(Gajendra!$J$9:$J$111,"SPP",Gajendra!$N$9:$N$111) -> 13110148 | S33: =SUMIF(Pradeep!$J$9:$J$123,"SPP",Pradeep!$N$9:$N$124) -> 6566455 | T33: =SUMIF(Sasi!$J$10:$J$127,"SPP",Sasi!$N$10:$N$128) -> 13729354 | V33: =SUM(R33:U33) -> 33405957
B34: Febraury | C34: =Gajendra!AD6+Pradeep!AD5+Sasi!AD5 -> 11306008 | D34: =Gajendra!AE6+Pradeep!AE5+Sasi!AE5 -> 4063710.4 | E34: 6764704 | F34: =D34-E34 -> -2700993.6 | G34: 4655891 | H34: =$H$30/12 -> 8957250 | I34: =H34-E34 -> 2192546 | J34: =(E34-H34)/E34 -> -0.32411559 | K34: =H34*4 -> 35829000 | L34: =(K34-C34)/K34 -> 0.68444534 | Q34: Relocation | R34: =SUMIF(Gajendra!$J$10:$J$111,"Relocation",Gajendra!$N$10:$N$111) -> 1790070 | S34: =SUMIF(Pradeep!$J$10:$J$124,"Relocation",Pradeep!$N$10:$N$125) -> 260000 | T34: =SUMIF(Sasi!$J$11:$J$128,"Relocation",Sasi!$N$11:$N$129) -> 5287040 | V34: =SUM(R34:U34) -> 7337110
B35: March | C35: =Gajendra!AD7+Pradeep!AD6+Sasi!AD6 -> 14264905 | D35: =Gajendra!AE7+Pradeep!AE6+Sasi!AE6 -> 7013109.6 | E35: 9361455 | F35: =D35-E35 -> -2348345.4 | G35: 3686928 | H35: =$H$30/12 -> 8957250 | I35: =H35-E35 -> -404205 | J35: =(E35-H35)/E35 -> 0.043177583 | K35: =H35*4 -> 35829000 | L35: =(K35-C35)/K35 -> 0.60186148 | Q35: Software | R35: =SUMIF(Gajendra!$J$11:$J$111,"Software",Gajendra!$N$11:$N$111) -> 0 | S35: =SUMIF(Pradeep!$J$11:$J$125,"Software",Pradeep!$N$11:$N$126) -> 0 | T35: =SUMIF(Sasi!$J$12:$J$129,"Software",Sasi!$N$12:$N$130) -> 0 | V35: =SUM(R35:U35) -> 0
B36: April | C36: =Gajendra!AD8+Pradeep!AD7+Sasi!AD7 -> 24355664 | D36: =Gajendra!AE8+Pradeep!AE7+Sasi!AE7 -> 8793519.6 | E36: 8748821 | F36: =D36-E36 -> 44698.58 | G36: 1700874 | H36: =$H$30/12 -> 8957250 | I36: =H36-E36 -> 208429 | J36: =(E36-H36)/E36 -> -0.023823667 | K36: =H36*4 -> 35829000 | L36: =(K36-C36)/K36 -> 0.32022486 | Q36: BD Charges | R36: =SUMIF(Gajendra!$J$12:$J$111,"BD Charges",Gajendra!$N$12:$N$111) -> 33000 | S36: =SUMIF(Pradeep!$J$12:$J$126,"BD Charges",Pradeep!$N$12:$N$127) -> 38500 | T36: =SUMIF(Sasi!$J$13:$J$130,"BD Charges",Sasi!$N$13:$N$131) -> 0 | V36: =SUM(R36:U36) -> 71500
B37: May | C37: =Gajendra!AD9+Pradeep!AD8+Sasi!AD8 -> 7475519.3 | D37: =Gajendra!AE9+Pradeep!AE8+Sasi!AE8 -> 6251988 | E37: 1124932 | F37: =D37-E37 -> 5127056 | G37: 7883167 | H37: =$H$30/12 -> 8957250 | I37: =H37-E37 -> 7832318 | J37: =(E37-H37)/E37 -> -6.9624813 | K37: =H37*4 -> 35829000 | L37: =(K37-C37)/K37 -> 0.79135562 | Q37: Retrofit kit | R37: =SUMIF(Gajendra!$J$13:$J$111,"Gajendra",Rahul!$N$13:$N$128) -> 0 | S37: =SUMIF(Pradeep!$J$13:$J$127,"Pradeep",Rahul!$N$13:$N$128) -> 0 | T37: =SUMIF(Sasi!$J$14:$J$131,"Retrofit kit",Sasi!$N$14:$N$132) -> 3345258 | V37: =SUM(R37:U37) -> 3345258
B38: June | C38: =Gajendra!AD10+Pradeep!AD9+Sasi!AD9 -> 9956476 | D38: =Gajendra!AE10+Pradeep!AE9+Sasi!AE9 -> 6489478.2 | E38: 9214306 | F38: =D38-E38 -> -2724827.8 | G38: 4008704 | H38: =$H$30/12 -> 8957250 | I38: =H38-E38 -> -257056 | J38: =(E38-H38)/E38 -> 0.027897489 | K38: =H38*4 -> 35829000 | L38: =(K38-C38)/K38 -> 0.72211125 | Q38: Upgrade kit | R38: =SUMIF(Gajendra!$J$14:$J$112,"Upgrade kit",Gajendra!$N$14:$N$113) -> 1954675 | S38: =SUMIF(Pradeep!$J$14:$J$128,"Upgrade kit",Pradeep!$N$14:$N$129) -> 2693572 | T38: =SUMIF(Sasi!$J$15:$J$132,"Upgrade kit",Sasi!$N$15:$N$133) -> 1017585 | V38: =SUM(R38:U38) -> 5665832
B39: July | C39: =Gajendra!AD11+Pradeep!AD10+Sasi!AD10 -> 19793873 | D39: =Gajendra!AE11+Pradeep!AE10+Sasi!AE10 -> 6787163.4 | E39: 9229190 | F39: =D39-E39 -> -2442026.6 | G39: 3704956 | H39: =$H$30/12 -> 8957250 | I39: =H39-E39 -> -271940 | J39: =(E39-H39)/E39 -> 0.029465208 | K39: =H39*4 -> 35829000 | L39: =(K39-C39)/K39 -> 0.44754604 | Q39: Training | R39: =SUMIF(Gajendra!$J$15:$J$113,"Training",Gajendra!$N$15:$N$114) -> 0 | S39: =SUMIF(Pradeep!$J$15:$J$129,"Training",Pradeep!$N$15:$N$130) -> 0 | T39: =SUMIF(Sasi!$J$16:$J$133,"Training",Sasi!$N$16:$N$134) -> 0 | V39: =SUM(R39:U39) -> 0
B40: August | C40: =Gajendra!AD12+Pradeep!AD11+Sasi!AD11 -> 16128864 | D40: =Gajendra!AE12+Pradeep!AE11+Sasi!AE11 -> 9060325.6 | E40: 8493405 | F40: =D40-E40 -> 566920.59 | G40: 6470925 | H40: =$H$30/12 -> 8957250 | I40: =H40-E40 -> 463845 | J40: =(E40-H40)/E40 -> -0.054612373 | K40: =H40*4 -> 35829000 | L40: =(K40-C40)/K40 -> 0.54983772 | Q40: Midlife Upgrade | R40: =SUMIF(Gajendra!$J$16:$J$114,"Midlife Upgrade",Gajendra!$N$16:$N$115) -> 6822682.2 | S40: =SUMIF(Pradeep!$J$16:$J$130,"Midlife Upgrade",Pradeep!$N$16:$N$131) -> 2089731 | T40: =SUMIF(Sasi!$J$17:$J$134,"Midlife Upgrade",Sasi!$N$17:$N$135) -> 3705155.7 | V40: =SUM(R40:U40) -> 12617569
B41: September | C41: =Gajendra!AD13+Pradeep!AD12+Sasi!AD12 -> 9615526 | D41: =Gajendra!AE13+Pradeep!AE12+Sasi!AE12 -> 4656791.8 | E41: 8975078 | F41: =D41-E41 -> -4318286.2 | G41: 2238093 | H41: =$H$30/12 -> 8957250 | I41: =H41-E41 -> -17828 | J41: =(E41-H41)/E41 -> 0.0019863894 | K41: =H41*4 -> 35829000 | L41: =(K41-C41)/K41 -> 0.73162729 | Q41: Total | R41: =SUM(R31:R40) -> 30745243 | S41: =SUM(S31:S40) -> 17384179 | T41: =SUM(T31:T40) -> 36362010 | V41: =SUM(V31:V40) -> 84491432
B42: October | C42: =Gajendra!AD14+Pradeep!AD13+Sasi!AD13 -> 22510217 | D42: =Gajendra!AE14+Pradeep!AE13+Sasi!AE13 -> 8516306.7 | E42: 8399872 | F42: =D42-E42 -> 116434.72 | G42: 7691541 | H42: =$H$30/12 -> 8957250 | I42: =H42-E42 -> 557378 | J42: =(E42-H42)/E42 -> -0.066355535 | K42: =H42*4 -> 35829000 | L42: =(K42-C42)/K42 -> 0.37173192
B43: November | C43: =Gajendra!AD15+Pradeep!AD14+Sasi!AD14 -> 10871279 | D43: =Gajendra!AE15+Pradeep!AE14+Sasi!AE14 -> 17857314 | E43: 11404623 | F43: =D43-E43 -> 6452691.1 | G43: 7517227 | H43: =$H$30/12 -> 8957250 | I43: =H43-E43 -> -2447373 | J43: =(E43-H43)/E43 -> 0.21459482 | K43: =H43*4 -> 35829000 | L43: =(K43-C43)/K43 -> 0.69657878 | Q43: Product type | R43: Vinay | S43: Nitin | T43: Pankaj | V43: North and East
B44: December | C44: =Gajendra!AD16+Pradeep!AD15+Sasi!AD15 -> 5171821 | D44: =Gajendra!AE16+Pradeep!AE15+Sasi!AE15 -> 565128 | E44: 11591184 | F44: =D44-E44 -> -11026056 | G44: 2744227 | H44: =$H$30/12 -> 8957250 | I44: =H44-E44 -> -2633934 | J44: =(E44-H44)/E44 -> 0.22723598 | K44: =H44*4 -> 35829000 | L44: =(K44-C44)/K44 -> 0.85565266 | Q44: Contract | R44: =SUMIF(Vinay!$J$7:$J$116,"Contract",Vinay!$N$7:$N$117) -> 1085000 | S44: =SUMIF(Nitin!$J$7:$J$100,"Contract",Nitin!$N$7:$N$101) -> 6015000 | T44: =SUMIF(Pankaj!$J$7:$J$121,"Contract",Pankaj!$N$7:$N$122) -> 3554593 | V44: =SUM(R44:U44) -> 10654593
B45: Total | C45: =SUM(C33:C44) -> 1.7686402e+08 | D45: =SUM(D33:D44) -> 95676327 | E45: =SUM(E33:E44) -> 100601530 | F45: =SUM(F33:F44) -> -4925203.4 | H45: =SUM(H33:H44) -> 107487000 | I45: =SUM(I33:I44) -> 6885470 | Q45: BD Spare | R45: =SUMIF(Vinay!$J$7:$J$117,"BD Spare",Vinay!$N$7:Z29) -> 515799 | S45: =SUMIF(Nitin!$J$8:$J$101,"BD Spare",Nitin!$N$8:AA34) -> 119428 | T45: =SUMIF(Pankaj!$J$8:$J$122,"BD Spare",Pankaj!$N$8:AB34) -> 0 | V45: =SUM(R45:U45) -> 635227
Q46: SPP | R46: =SUMIF(Vinay!$J$9:$J$118,"SPP",Vinay!$N$9:$N$119) -> 14220300 | S46: =SUMIF(Nitin!$J$9:$J$102,"SPP",Nitin!$N$9:$N$103) -> 1520695 | T46: =SUMIF(Pankaj!$J$9:$J$123,"SPP",Pankaj!$N$9:$N$124) -> 8175621 | V46: =SUM(R46:U46) -> 23916616
H47: 39086000 | K47: HIT RATE | L47: =D62/C62 -> 0.25386168 | Q47: Relocation | R47: =SUMIF(Vinay!$J$9:$J$119,"Relocation",Vinay!$N$9:$N$120) -> 0 | S47: =SUMIF(Nitin!$J$10:$J$103,"Relocation",Nitin!$N$10:$N$104) -> 2310000 | T47: =SUMIF(Pankaj!$J$10:$J$124,"Relocation",Pankaj!$N$10:$N$125) -> 0 | V47: =SUM(R47:U47) -> 2310000
B48: NORTH | Q48: Software | R48: =SUMIF(Vinay!$J$9:$J$120,"Software",Vinay!$N$9:$N$121) -> 0 | S48: =SUMIF(Nitin!$J$11:$J$104,"Software",Nitin!$N$11:$N$105) -> 0 | T48: =SUMIF(Pankaj!$J$11:$J$125,"Software",Pankaj!$N$11:$N$126) -> 0 | V48: =SUM(R48:U48) -> 0
B49: Month | C49: Offers/Value | D49: Order Received | E49: *Order Booked | F49: Dev OR vs Booked | G49: *Orders In-Hand | H49: BU/Monthly | I49: Booked vs BU | J49: % Dev | K49: Offer BU Monthly | L49: % Dev | Q49: BD Charges | R49: =SUMIF(Vinay!$J$10:$J$121,"BD Charges",Vinay!$N$10:$N$122) -> 84000 | S49: =SUMIF(Nitin!$J$12:$J$105,"BD Charges",Nitin!$N$12:$N$106) -> 55000 | T49: =SUMIF(Pankaj!$J$12:$J$126,"BD Charges",Pankaj!$N$12:$N$127) -> 100000 | V49: =SUM(R49:U49) -> 239000
B50: Januray | C50: =Vinay!AD3+Nitin!AD4 -> 13940362 | D50: =Vinay!AE3+Nitin!AE4 -> 2588719 | E50: 3061918 | F50: =D50-E50 -> -473199 | H50: =$H$47/12 -> 3257166.7 | I50: =H50-E50 -> 195248.67 | J50: =(E50-H50)/E50 -> -0.063766785 | K50: =H50*4 -> 13028667 | L50: =(K50-C50)/K50 -> -0.069976104 | Q50: Retrofit kit | R50: =SUMIF(Vinay!$J$11:$J$122,"Retrofit kit",Vinay!$N$11:$N$123) -> 3499890 | S50: =SUMIF(Nitin!$J$13:$J$106,"Retrofit kit",Nitin!$N$13:$N$107) -> 0 | T50: =SUMIF(Pankaj!$J$13:$J$127,"Retrofit kit",Pankaj!$N$13:$N$128) -> 0 | V50: =SUM(R50:U50) -> 3499890
B51: Febraury | C51: =Vinay!AD4+Nitin!AD5 -> 7552303 | D51: =Vinay!AE4+Nitin!AE5 -> 1910627 | E51: 2242471 | F51: =D51-E51 -> -331844 | G51: 201000 | H51: =$H$47/12 -> 3257166.7 | I51: =H51-E51 -> 1014695.7 | J51: =(E51-H51)/E51 -> -0.45248998 | K51: =H51*4 -> 13028667 | L51: =(K51-C51)/K51 -> 0.42033186 | Q51: Upgrade kit | R51: =SUMIF(Vinay!$J$12:$J$123,"Upgrade kit",Vinay!$N$12:$N$124) -> 0 | S51: =SUMIF(Nitin!$J$14:$J$107,"Upgrade kit",Nitin!$N$14:$N$108) -> 0 | T51: =SUMIF(Pankaj!$J$14:$J$128,"Upgrade kit",Pankaj!$N$14:$N$129) -> 0 | V51: =SUM(R51:U51) -> 0
B52: March | C52: =Vinay!AD5+Nitin!AD6 -> 4436233 | D52: =Vinay!AE5+Nitin!AE6 -> 2375554 | E52: 2761273 | F52: =D52-E52 -> -385719 | G52: 1581693 | H52: =$H$47/12 -> 3257166.7 | I52: =H52-E52 -> 495893.67 | J52: =(E52-H52)/E52 -> -0.17958879 | K52: =H52*4 -> 13028667 | L52: =(K52-C52)/K52 -> 0.65950215 | Q52: Training | R52: =SUMIF(Vinay!$J$13:$J$124,"Training",Vinay!$N$13:$N$125) -> 0 | S52: =SUMIF(Nitin!$J$15:$J$108,"Training",Nitin!$N$15:$N$109) -> 0 | T52: =SUMIF(Pankaj!$J$15:$J$129,"Training",Pankaj!$N$15:$N$130) -> 0 | V52: =SUM(R52:U52) -> 0
B53: April | C53: =Vinay!AD6+Nitin!AD7 -> 7970891 | D53: =Vinay!AE6+Nitin!AE7 -> 1548932 | E53: 3008913 | F53: =D53-E53 -> -1459981 | G53: 239020 | H53: =$H$47/12 -> 3257166.7 | I53: =H53-E53 -> 248253.67 | J53: =(E53-H53)/E53 -> -0.082506097 | K53: =H53*4 -> 13028667 | L53: =(K53-C53)/K53 -> 0.38820363 | Q53: Midlife Upgrade | R53: =SUMIF(Vinay!$J$13:$J$125,"Midlife Upgrade",Vinay!$N$13:$N$126) -> 0 | S53: =SUMIF(Nitin!$J$16:$J$109,"Midlife Upgrade",Nitin!$N$16:$N$110) -> 3175199 | T53: =SUMIF(Pankaj!$J$16:$J$130,"Midlife Upgrade",Pankaj!$N$16:$N$131) -> 0 | V53: =SUM(R53:U53) -> 3175199
B54: May | C54: =Vinay!AD7+Nitin!AD8 -> 29200900 | D54: =Vinay!AE7+Nitin!AE8 -> 1868436 | E54: 704000 | F54: =D54-E54 -> 1164436 | G54: 1050876 | H54: =$H$47/12 -> 3257166.7 | I54: =H54-E54 -> 2553166.7 | J54: =(E54-H54)/E54 -> -3.6266572 | K54: =H54*4 -> 13028667 | L54: =(K54-C54)/K54 -> -1.2412808 | Q54: Total | R54: =SUM(R44:R53) -> 19404989 | S54: =SUM(S44:S53) -> 13195322 | T54: =SUM(T44:T53) -> 11830214 | V54: =SUM(R54:U54) -> 44430525
B55: June | C55: =Vinay!AD10+Nitin!AD9 -> 13294492 | D55: =Vinay!AE10+Nitin!AE9 -> 4583120 | E55: 3569567 | F55: =D55-E55 -> 1013553 | G55: 760002 | H55: =$H$47/12 -> 3257166.7 | I55: =H55-E55 -> -312400.33 | J55: =(E55-H55)/E55 -> 0.087517711 | K55: =H55*4 -> 13028667 | L55: =(K55-C55)/K55 -> -0.020403111
B56: July | C56: =Vinay!AD11+Nitin!AD10 -> 2432396 | D56: =Vinay!AE11+Nitin!AE10 -> 1012557 | E56: 1681580 | F56: =D56-E56 -> -669023 | G56: 4187972 | H56: =$H$47/12 -> 3257166.7 | I56: =H56-E56 -> 1575586.7 | J56: =(E56-H56)/E56 -> -0.93696801 | K56: =H56*4 -> 13028667 | L56: =(K56-C56)/K56 -> 0.8133043 | P56: PO Expected Month
B57: August | C57: =Vinay!AD12+Nitin!AD11 -> 4331125 | D57: =Vinay!AE12+Nitin!AE11 -> 1736763 | E57: 2564789 | F57: =D57-E57 -> -828026 | G57: 5356496 | H57: =$H$47/12 -> 3257166.7 | I57: =H57-E57 -> 692377.67 | J57: =(E57-H57)/E57 -> -0.26995502 | K57: =H57*4 -> 13028667 | L57: =(K57-C57)/K57 -> 0.66756959 | P57: WEST
B58: September | C58: =Vinay!AD13+Nitin!AD12 -> 7302547 | D58: =Vinay!AE13+Nitin!AE12 -> 1632264 | E58: 2215665 | F58: =D58-E58 -> -583401 | G58: 3603145 | H58: =$H$47/12 -> 3257166.7 | I58: =H58-E58 -> 1041501.7 | J58: =(E58-H58)/E58 -> -0.47006279 | K58: =H58*4 -> 13028667 | L58: =(K58-C58)/K58 -> 0.43950159 | P58: Month | Q58: Yogesh | R58: Ashraf | S58: Rahul | T58: Minesh | U58: Total
B59: October | C59: =Vinay!AD14+Nitin!AD13 -> 8461308 | D59: =Vinay!AE14+Nitin!AE13 -> 2612332 | E59: 4697947 | F59: =D59-E59 -> -2085615 | G59: 3885984 | H59: =$H$47/12 -> 3257166.7 | I59: =H59-E59 -> -1440780.3 | J59: =(E59-H59)/E59 -> 0.30668297 | K59: =H59*4 -> 13028667 | L59: =(K59-C59)/K59 -> 0.35056225 | P59: FEB | Q59: =Yogesh!AE4 -> 738000 | R59: =Ashraf!AE4 -> 1129500 | S59: =Rahul!AE4 -> 4146986 | T59: =Minesh!AE4 -> 1534165 | U59: =SUM(Q59:T59) -> 7548651
B60: November | C60: =Vinay!AD14+Nitin!AD14 -> 2485985 | D60: =Vinay!AE14+Nitin!AE14 -> 3874439 | E60: 3256999 | F60: =D60-E60 -> 617440 | G60: 3510984 | H60: =$H$47/12 -> 3257166.7 | I60: =H60-E60 -> 167.66667 | J60: =(E60-H60)/E60 -> -5.1478882e-05 | K60: =H60*4 -> 13028667 | L60: =(K60-C60)/K60 -> 0.80919114 | P60: MAR | Q60: =Yogesh!AE5 -> 799106 | R60: =Ashraf!AE5 -> 4226358 | S60: =Rahul!AE5 -> 4630660 | T60: =Minesh!AE5 -> 405650 | U60: =SUM(Q60:T60) -> 10061774
B61: December | C61: =Vinay!AD15+Nitin!AD15 -> 0 | D61: =Vinay!AE15+Nitin!AE15 -> 0 | E61: 1948627 | F61: =D61-E61 -> -1948627 | G61: 3131128 | H61: =$H$47/12 -> 3257166.7 | I61: =H61-E61 -> 1308539.7 | J61: =(E61-H61)/E61 -> -0.6715188 | K61: =H61*4 -> 13028667 | L61: =(K61-C61)/K61 -> 1 | P61: APR | Q61: =Yogesh!AE6 -> 29793925 | R61: =Ashraf!AE6 -> 1926050 | S61: =Rahul!AE6 -> 3799298 | T61: =Minesh!AE6 -> 2936340 | U61: =SUM(Q61:T61) -> 38455613
B62: Total | C62: =SUM(C50:C61) -> 101408542 | D62: =SUM(D50:D61) -> 25743743 | E62: =SUM(E50:E61) -> 31713749 | F62: =SUM(F50:F61) -> -5970006 | H62: =SUM(H50:H61) -> 39086000 | I62: =SUM(I50:I61) -> 7372251 | P62: MAY | Q62: =Yogesh!AE7 -> 2155128 | R62: =Ashraf!AE7 -> 5133652 | S62: =Rahul!AE7 -> 5936472 | T62: =Minesh!AE7 -> 2524790 | U62: =SUM(Q62:T62) -> 15750042
P63: JUN | Q63: =Yogesh!AE8 -> 2185972 | R63: =Ashraf!AE8 -> 6433266 | S63: =Rahul!AE8 -> 6140548 | T63: =Minesh!AE8 -> 2174860 | U63: =SUM(Q63:T63) -> 16934646
H64: 11167000 | K64: HIT RATE | L64: =D79/C79 -> 0.37823628 | P64: JULY | Q64: =Yogesh!AE9 -> 1752032 | R64: =Ashraf!AE9 -> 2640380 | S64: =Rahul!AE9 -> 4247261 | T64: =Minesh!AE9 -> 129000 | U64: =SUM(Q64:T64) -> 8768673
B65: EAST | P65: AUG | Q65: =Yogesh!AE10 -> 2652512 | R65: =Ashraf!AE10 -> 4745016 | S65: =Rahul!AE10 -> 1809730 | T65: =Minesh!AE10 -> 4429476 | U65: =SUM(Q65:T65) -> 13636734
B66: Month | C66: Offers/Value | D66: Order Received | E66: *Order Booked | F66: Dev OR vs Booked | G66: *Orders In-Hand | H66: BU/Monthly | I66: Booked vs BU | J66: % Dev | K66: Offer BU Monthly | L66: % Dev | P66: Sept | Q66: =Yogesh!AE11 -> 4109040 | R66: =Ashraf!AE11 -> 1273000 | S66: =Rahul!AE11 -> 1523678 | T66: =Minesh!AE11 -> 2696450 | U66: =SUM(Q66:T66) -> 9602168
B67: Januray | C67: =Pankaj!AD3 -> 1893450 | D67: =Pankaj!AE3 -> 680982 | E67: 1170982 | F67: =D67-E67 -> -490000 | H67: =$H$64/12 -> 930583.33 | I67: =H67-E67 -> -240398.67 | J67: =(E67-H67)/E67 -> 0.20529664 | K67: =H67*4 -> 3722333.3 | L67: =(K67-C67)/K67 -> 0.49132712 | P67: Oct | Q67: =Yogesh!AE12 -> 1603555 | R67: =Ashraf!AE12 -> 2694185 | S67: =Rahul!AE12 -> 2049077 | T67: =Minesh!AE12 -> 2755540 | U67: =SUM(Q67:T67) -> 9102357
B68: Febraury | C68: =Pankaj!AD4 -> 749147 | D68: =Pankaj!AE4 -> 134649 | E68: 199649 | F68: =D68-E68 -> -65000 | G68: 309200 | H68: =$H$64/12 -> 930583.33 | I68: =H68-E68 -> 730934.33 | J68: =(E68-H68)/E68 -> -3.6610969 | K68: =H68*4 -> 3722333.3 | L68: =(K68-C68)/K68 -> 0.79874263 | P68: Nov | Q68: =Yogesh!AE13 -> 1673209 | R68: =Ashraf!AE13 -> 8781521 | S68: =Rahul!AE13 -> 7527818 | T68: =Minesh!AE13 -> 1000130 | U68: =SUM(Q68:T68) -> 18982678
B69: March | C69: =Pankaj!AD5 -> 1434365 | D69: =Pankaj!AE5 -> 878370 | E69: 390956 | F69: =D69-E69 -> 487414 | G69: 742244 | H69: =$H$64/12 -> 930583.33 | I69: =H69-E69 -> 539627.33 | J69: =(E69-H69)/E69 -> -1.3802764 | K69: =H69*4 -> 3722333.3 | L69: =(K69-C69)/K69 -> 0.61465971 | P69: Dec | Q69: =Yogesh!AE14 -> 14809392 | R69: =Ashraf!AE14 -> 8634215 | S69: =Rahul!AE14 -> 8187712 | T69: =Minesh!AE14 -> 3204850 | U69: =SUM(Q69:T69) -> 34836169
B70: April | C70: =Pankaj!AD6 -> 264000 | D70: =Pankaj!AE6 -> 952118 | E70: 548447 | F70: =D70-E70 -> 403671 | G70: 1252414 | H70: =$H$64/12 -> 930583.33 | I70: =H70-E70 -> 382136.33 | J70: =(E70-H70)/E70 -> -0.69676073 | K70: =H70*4 -> 3722333.3 | L70: =(K70-C70)/K70 -> 0.92907674 | P70: SOUTH
B71: May | C71: =Pankaj!AD7 -> 1910946 | D71: =Pankaj!AE7 -> 895062.4 | E71: 237057 | F71: =D71-E71 -> 658005.4 | G71: 950357 | H71: =$H$64/12 -> 930583.33 | I71: =H71-E71 -> 693526.33 | J71: =(E71-H71)/E71 -> -2.9255678 | K71: =H71*4 -> 3722333.3 | L71: =(K71-C71)/K71 -> 0.48662685 | P71: Month | Q71: Gajendra | R71: Pradeep | S71: Sasi | U71: Total
B72: June | C72: =Pankaj!AD8 -> 541728 | D72: =Pankaj!AE8 -> 0 | E72: 0 | F72: =D72-E72 -> 0 | G72: 1823877 | H72: =$H$64/12 -> 930583.33 | I72: =H72-E72 -> 930583.33 | J72: =(E72-H72)/E72 -> #DIV/0! | K72: =H72*4 -> 3722333.3 | L72: =(K72-C72)/K72 -> 0.85446548 | P72: FEB | Q72: =Gajendra!AF6 -> 1618199.8 | R72: =Pradeep!AF5 -> 4397978 | S72: =Sasi!AF5 -> 923262 | T72: =Minesh!AE17 -> 0 | U72: =SUM(Q72:T72) -> 6939439.8
B73: July | C73: =Pankaj!AD9 -> 20478 | D73: =Pankaj!AE9 -> 91060 | E73: 1133105 | F73: =D73-E73 -> -1042045 | G73: 874217 | H73: =$H$64/12 -> 930583.33 | I73: =H73-E73 -> -202521.67 | J73: =(E73-H73)/E73 -> 0.1787316 | K73: =H73*4 -> 3722333.3 | L73: =(K73-C73)/K73 -> 0.99449861 | P73: MAR | Q73: =Gajendra!AF7 -> 227778 | R73: =Pradeep!AF6 -> 8598354 | S73: =Sasi!AF6 -> 1358861.9 | T73: =Minesh!AE18 -> 0 | U73: =SUM(Q73:T73) -> 10184994
B74: August | C74: =Pankaj!AD10 -> 2068998 | D74: =Pankaj!AE10 -> 0 | E74: 362744 | F74: =D74-E74 -> -362744 | G74: 531951 | H74: =$H$64/12 -> 930583.33 | I74: =H74-E74 -> 567839.33 | J74: =(E74-H74)/E74 -> -1.5653997 | K74: =H74*4 -> 3722333.3 | L74: =(K74-C74)/K74 -> 0.44416638 | P74: APR | Q74: =Gajendra!AF8 -> 4482331.8 | R74: =Pradeep!AF7 -> 4994909 | S74: =Sasi!AF7 -> 4409137.7 | T74: =Minesh!AE19 -> 0 | U74: =SUM(Q74:T74) -> 13886379
B75: September | C75: =Pankaj!AD11 -> 1673785 | D75: =Pankaj!AE11 -> 160800 | E75: 181278 | F75: =D75-E75 -> -20478 | G75: 511473 | H75: =$H$64/12 -> 930583.33 | I75: =H75-E75 -> 749305.33 | J75: =(E75-H75)/E75 -> -4.1334598 | K75: =H75*4 -> 3722333.3 | L75: =(K75-C75)/K75 -> 0.55033984 | P75: MAY | Q75: =Gajendra!AF9 -> 2891108.8 | R75: =Pradeep!AF8 -> 1741036 | S75: =Sasi!AF8 -> 298690 | T75: =Minesh!AE20 -> 0 | U75: =SUM(Q75:T75) -> 4930834.8
B76: October | C76: =Pankaj!AD12 -> 1986767 | D76: =Pankaj!AE12 -> 0 | E76: 420413 | F76: =D76-E76 -> -420413 | G76: 366636 | H76: =$H$64/12 -> 930583.33 | I76: =H76-E76 -> 510170.33 | J76: =(E76-H76)/E76 -> -1.213498 | K76: =H76*4 -> 3722333.3 | L76: =(K76-C76)/K76 -> 0.46625763 | P76: JUN | Q76: =Gajendra!AF10 -> 226708 | R76: =Pradeep!AF9 -> 394480 | S76: =Sasi!AF9 -> 2500144 | T76: =Minesh!AE21 -> 0 | U76: =SUM(Q76:T76) -> 3121332
B77: November | C77: =Pankaj!AD13 -> 100000 | D77: =Pankaj!AE13 -> 989251 | E77: 886457 | F77: =D77-E77 -> 102794 | G77: 891636 | H77: =$H$64/12 -> 930583.33 | I77: =H77-E77 -> 44126.333 | J77: =(E77-H77)/E77 -> -0.049778312 | K77: =H77*4 -> 3722333.3 | L77: =(K77-C77)/K77 -> 0.97313513 | P77: JULY | Q77: =Gajendra!AF11 -> 4423990.2 | R77: =Pradeep!AF10 -> 7648092 | S77: =Sasi!AF10 -> 2562908 | T77: =Minesh!AE22 -> 0 | U77: =SUM(Q77:T77) -> 14634990
B78: December | C78: =Pankaj!AD14 -> 0 | D78: =Pankaj!AE14 -> 0 | E78: 437805 | F78: =D78-E78 -> -437805 | G78: 891636 | H78: =$H$64/12 -> 930583.33 | I78: =H78-E78 -> 492778.33 | J78: =(E78-H78)/E78 -> -1.1255658 | K78: =H78*4 -> 3722333.3 | L78: =(K78-C78)/K78 -> 1 | P78: AUG | Q78: =Gajendra!AF12 -> 3722715.6 | R78: =Pradeep!AF11 -> 10028198 | S78: =Sasi!AF11 -> 5700035.7 | T78: =Minesh!AE23 -> 0 | U78: =SUM(Q78:T78) -> 19450949
B79: Total | C79: =SUM(C67:C78) -> 12643664 | D79: =SUM(D67:D78) -> 4782292.4 | E79: =SUM(E67:E78) -> 5968893 | F79: =SUM(F67:F78) -> -1186600.6 | H79: =SUM(H67:H78) -> 11167000 | I79: =SUM(I67:I78) -> 5198107 | P79: Sept | Q79: =Gajendra!AF13 -> 630274.5 | R79: =Pradeep!AF12 -> 11079547 | S79: =Sasi!AF12 -> 4652140 | T79: =Minesh!AE24 -> 0 | U79: =SUM(Q79:T79) -> 16361962
P80: Oct | Q80: =Gajendra!AF14 -> 7388166.6 | R80: =Pradeep!AF13 -> 9075607 | S80: =Sasi!AF13 -> 0 | T80: =Minesh!AE25 -> 0 | U80: =SUM(Q80:T80) -> 16463774
P81: Nov | Q81: =Gajendra!AF15 -> 6881354.9 | R81: =Pradeep!AF14 -> 9450065 | S81: =Sasi!AF14 -> 3675596 | T81: =Minesh!AE26 -> 0 | U81: =SUM(Q81:T81) -> 20007016
P82: Dec | Q82: =Gajendra!AF16 -> 15439392 | R82: =Pradeep!AF15 -> 16796607 | S82: =Sasi!AF15 -> 0 | T82: =Minesh!AE27 -> 0 | U82: =SUM(Q82:T82) -> 32235999
P83: NORTH & EAST
P84: Month | Q84: Vinay | R84: Nitin | S84: Pankaj | U84: Total
P85: FEB | Q85: =Vinay!AF4 -> 0 | R85: =Nitin!AF5 -> 200000 | S85: =Pankaj!AF4 -> 233880 | T85: =Minesh!AE30 -> 0 | U85: =SUM(Q85:T85) -> 433880
P86: MAR | Q86: =Vinay!AF5 -> 1202802 | R86: =Nitin!AF6 -> 145000 | S86: =Pankaj!AF5 -> 1103862 | T86: =Minesh!AE31 -> 0 | U86: =SUM(Q86:T86) -> 2451664
P87: APR | Q87: =Vinay!AF6 -> 1449980 | R87: =Nitin!AF7 -> 1148000 | S87: =Pankaj!AF6 -> 0 | T87: =Minesh!AE32 -> 0 | U87: =SUM(Q87:T87) -> 2597980
P88: MAY | Q88: =Vinay!AF7 -> 670047 | R88: =Nitin!AF8 -> 3897293 | S88: =Pankaj!AF7 -> 1039330 | T88: =Minesh!AE33 -> 0 | U88: =SUM(Q88:T88) -> 5606670
P89: JUN | Q89: =Vinay!AF10 -> 1969554 | R89: =Nitin!AF9 -> 3898977 | S89: =Pankaj!AF8 -> 0 | T89: =Minesh!AE34 -> 0 | U89: =SUM(Q89:T89) -> 5868531
P90: JULY | Q90: =Vinay!AF11 -> 842147 | R90: =Nitin!AF10 -> 1728929 | S90: =Pankaj!AF9 -> 404854 | T90: =Minesh!AE35 -> 0 | U90: =SUM(Q90:T90) -> 2975930
P91: AUG | Q91: =Vinay!AF12 -> 1600092 | R91: =Nitin!AF11 -> 6445932 | S91: =Pankaj!AF10 -> 160176 | T91: =Minesh!AE36 -> 0 | U91: =SUM(Q91:T91) -> 8206200
P92: Sept | Q92: =Vinay!AF13 -> 519444 | R92: =Nitin!AF12 -> 33904128 | S92: =Pankaj!AF11 -> 180576 | T92: =Minesh!AE37 -> 0 | U92: =SUM(Q92:T92) -> 34604148
P93: Oct | Q93: =Vinay!AF14 -> 9074625 | R93: =Nitin!AF13 -> 4224061 | S93: =Pankaj!AF12 -> 869988 | T93: =Minesh!AE38 -> 0 | U93: =SUM(Q93:T93) -> 14168674
P94: Nov | Q94: =Vinay!#REF! -> #REF! | R94: =Nitin!AF14 -> 23545744 | S94: =Pankaj!AF13 -> 3208676 | T94: =Minesh!AE39 -> 0 | U94: =SUM(Q94:T94) -> #REF!
P95: Dec | Q95: =Vinay!AF15 -> 0 | R95: =Nitin!AF15 -> 6355659 | S95: =Pankaj!AF14 -> 3565273 | T95: =Minesh!AE40 -> 0 | U95: =SUM(Q95:T95) -> 9920932
S97: 93 | T97: =((3002*S97)/12)/100 -> 232.655
Q99: Product wise Forecast
P100: WEST | AC100: South | AO100: North & East
P101: Yogesh | Q101: Total | R101: =SUM(R103:R112) -> 799106 | S101: =SUM(S103:S112) -> 29793925 | T101: =SUM(T103:T112) -> 2155128 | U101: =SUM(U103:U112) -> 2185972 | V101: =SUM(V103:V112) -> 1168032 | W101: =SUM(W103:W112) -> 2652512 | X101: =SUM(X103:X112) -> 2077982 | Y101: =SUM(Y103:Y112) -> 1603555 | ... AA101: =SUM(AA103:AA112) -> 14809392 | AC101: Gajendra | AD101: Total | AE101: =SUM(AE103:AE112) -> 4482331.8 | AF101: =SUM(AF103:AF112) -> 2891108.8 | AG101: =SUM(AG103:AG112) -> 226708 | AH101: =SUM(AH103:AH112) -> 4423990.2 | AI101: =SUM(AI103:AI112) -> 3722715.6 | AJ101: =SUM(AJ103:AJ112) -> 630274.5 | AK101: =SUM(AK103:AK112) -> 7388166.6 | AL101: =SUM(AL103:AL112) -> 6881354.9 | AM101: =SUM(AM103:AM112) -> 15439392 | AO101: Vinay | AP101: Total | AQ101: =SUM(AQ103:AQ112) -> 1202802 | AR101: =SUM(AR103:AR112) -> 1182284 | AS101: =SUM(AS103:AS112) -> 670047 | AT101: =SUM(AT103:AT112) -> 1975534 | AU101: =SUM(AU103:AU112) -> 256574 | AV101: =SUM(AV103:AV112) -> 1969554 | AW101: =SUM(AW103:AW112) -> 842147 | AX101: =SUM(AX103:AX112) -> 1600092 | ... AZ101: =SUM(AZ103:AZ112) -> 8794625
Q102: Product type | R102: March | S102: April | T102: May | U102: June | V102: July | W102: August | X102: September | Y102: October | Z102: November | AA102: December | AD102: Product type | AE102: April | AF102: May | AG102: June | AH102: July | AI102: August | AJ102: September | AK102: October | AL102: November | AM102: December | AP102: Product type | AQ102: March | AR102: April | AS102: May | AT102: June | AU102: July | AV102: August | AW102: September | AX102: October | AY102: November | AZ102: December
Q103: Contract | R103: =SUMIFS(Yogesh!$N$13:$N$400,Yogesh!$P$13:$P$400,"March",Yogesh!$J$13:$J$400,"Contract") -> 0 | S103: =SUMIFS(Yogesh!$N$13:$N$400,Yogesh!$P$13:$P$400,"April",Yogesh!$J$13:$J$400,"Contract") -> 1950200 | T103: =SUMIFS(Yogesh!$N$13:$N$400,Yogesh!$P$13:$P$400,"May",Yogesh!$J$13:$J$400,"Contract") -> 565000 | U103: =SUMIFS(Yogesh!$N$13:$N$400,Yogesh!$P$13:$P$400,"June",Yogesh!$J$13:$J$400,"Contract") -> 2022440 | V103: =SUMIFS(Yogesh!$N$13:$N$400,Yogesh!$P$13:$P$400,"July",Yogesh!$J$13:$J$400,"Contract") -> 658000 | W103: =SUMIFS(Yogesh!$N$13:$N$400,Yogesh!$P$13:$P$400,"August",Yogesh!$J$13:$J$400,"Contract") -> 473222 | X103: =SUMIFS(Yogesh!$N$13:$N$400,Yogesh!$P$13:$P$400,"September",Yogesh!$J$13:$J$400,"Contract") -> 0 | Y103: =SUMIFS(Yogesh!$N$13:$N$400,Yogesh!$P$13:$P$400,"October",Yogesh!$J$13:$J$400,"Contract") -> 180000 | Z103: =SUMIFS(Yogesh!$N$13:$N$400,Yogesh!$P$13:$P$400,"November",Yogesh!$J$13:$J$400,"Contract") -> 406009 | AA103: =SUMIFS(Yogesh!$N$13:$N$400,Yogesh!$P$13:$P$400,"December",Yogesh!$J$13:$J$400,"Contract") -> 0 | AD103: Contract | AE103: =SUMIFS(Gajendra!$N$13:$N$373,Gajendra!$P$13:$P$373,"April",Gajendra!$J$13:$J$373,"Contract") -> 1526450 | AF103: =SUMIFS(Gajendra!$N$13:$N$373,Gajendra!$P$13:$P$373,"May",Gajendra!$J$13:$J$373,"Contract") -> 1262552 | AG103: =SUMIFS(Gajendra!$N$13:$N$373,Gajendra!$P$13:$P$373,"June",Gajendra!$J$13:$J$373,"Contract") -> 178000 | AH103: =SUMIFS(Gajendra!$N$13:$N$373,Gajendra!$P$13:$P$373,"July",Gajendra!$J$13:$J$373,"Contract") -> 3094559.7 | AI103: =SUMIFS(Gajendra!$N$13:$N$373,Gajendra!$P$13:$P$373,"August",Gajendra!$J$13:$J$373,"Contract") -> 703000 | AJ103: =SUMIFS(Gajendra!$N$13:$N$373,Gajendra!$P$13:$P$373,"September",Gajendra!$J$13:$J$373,"Contract") -> 0 | AK103: =SUMIFS(Gajendra!$N$13:$N$373,Gajendra!$P$13:$P$373,"October",Gajendra!$J$13:$J$373,"Contract") -> 697200 | AL103: =SUMIFS(Gajendra!$N$13:$N$373,Gajendra!$P$13:$P$373,"November",Gajendra!$J$13:$J$373,"Contract") -> 776400 | AM103: =SUMIFS(Gajendra!$N$13:$N$373,Gajendra!$P$13:$P$373,"December",Gajendra!$J$13:$J$373,"Contract") -> 3716120 | AP103: Contract | AQ103: =SUMIFS(Vinay!$N$13:$N$400,Vinay!$P$13:$P$400,"March",Vinay!$J$13:$J$400,"Contract") -> 0 | AR103: =SUMIFS(Vinay!$N$13:$N$400,Vinay!$P$13:$P$400,"April",Vinay!$J$13:$J$400,"Contract") -> 0 | AS103: =SUMIFS(Vinay!$N$13:$N$400,Vinay!$P$13:$P$400,"May",Vinay!$J$13:$J$400,"Contract") -> 0 | AT103: =SUMIFS(Vinay!$N$13:$N$400,Vinay!$P$13:$P$400,"June",Vinay!$J$13:$J$400,"Contract") -> 350000 | AU103: =SUMIFS(Vinay!$N$13:$N$400,Vinay!$P$13:$P$400,"July",Vinay!$J$13:$J$400,"Contract") -> 0 | AV103: =SUMIFS(Vinay!$N$13:$N$400,Vinay!$P$13:$P$400,"August",Vinay!$J$13:$J$400,"Contract") -> 0 | AW103: =SUMIFS(Vinay!$N$13:$N$400,Vinay!$P$13:$P$400,"September",Vinay!$J$13:$J$400,"Contract") -> 0 | AX103: =SUMIFS(Vinay!$N$13:$N$400,Vinay!$P$13:$P$400,"October",Vinay!$J$13:$J$400,"Contract") -> 615000 | AY103: =SUMIFS(Vinay!$N$13:$N$400,Vinay!$P$13:$P$400,"November",Vinay!$J$13:$J$400,"Contract") -> 0 | AZ103: =SUMIFS(Vinay!$N$13:$N$400,Vinay!$P$13:$P$400,"December",Vinay!$J$13:$J$400,"Contract") -> 120000
Q104: BD Spare | R104: =SUMIFS(Yogesh!$N$13:$N$400,Yogesh!$P$13:$P$400,"March",Yogesh!$J$13:$J$400,"BD Spare") -> 22600 | S104: =SUMIFS(Yogesh!$N$13:$N$400,Yogesh!$P$13:$P$400,"April",Yogesh!$J$13:$J$400,"BD Spare") -> 0 | T104: =SUMIFS(Yogesh!$N$13:$N$400,Yogesh!$P$13:$P$400,"May",Yogesh!$J$13:$J$400,"BD Spare") -> 0 | U104: =SUMIFS(Yogesh!$N$13:$N$400,Yogesh!$P$13:$P$400,"June",Yogesh!$J$13:$J$400,"BD Spare") -> 0 | V104: =SUMIFS(Yogesh!$N$13:$N$400,Yogesh!$P$13:$P$400,"July",Yogesh!$J$13:$J$400,"BD Spare") -> 510032 | W104: =SUMIFS(Yogesh!$N$13:$N$400,Yogesh!$P$13:$P$400,"August",Yogesh!$J$13:$J$400,"BD Spare") -> 0 | X104: =SUMIFS(Yogesh!$N$13:$N$400,Yogesh!$P$13:$P$400,"September",Yogesh!$J$13:$J$400,"BD Spare") -> 0 | Y104: =SUMIFS(Yogesh!$N$13:$N$400,Yogesh!$P$13:$P$400,"October",Yogesh!$J$13:$J$400,"BD Sapre") -> 0 | Z104: =SUMIFS(Yogesh!$N$13:$N$400,Yogesh!$P$13:$P$400,"November",Yogesh!$J$13:$J$400,"BD Sapre") -> 0 | AA104: =SUMIFS(Yogesh!$N$13:$N$400,Yogesh!$P$13:$P$400,"December",Yogesh!$J$13:$J$400,"BD Spare") -> 0 | AD104: BD Spare | AE104: =SUMIFS(Gajendra!$N$13:$N$373,Gajendra!$P$13:$P$373,"April",Gajendra!$J$13:$J$373,"BD Spare") -> 294017 | AF104: =SUMIFS(Gajendra!$N$13:$N$373,Gajendra!$P$13:$P$373,"May",Gajendra!$J$13:$J$373,"BD Spare") -> 202356 | AG104: =SUMIFS(Gajendra!$N$13:$N$373,Gajendra!$P$13:$P$373,"June",Gajendra!$J$13:$J$373,"BD Spare") -> 0 | AH104: =SUMIFS(Gajendra!$N$13:$N$373,Gajendra!$P$13:$P$373,"July",Gajendra!$J$13:$J$373,"BD Spare") -> 0 | AI104: =SUMIFS(Gajendra!$N$13:$N$373,Gajendra!$P$13:$P$373,"August",Gajendra!$J$13:$J$373,"BD Spare") -> 169404.88 | AJ104: =SUMIFS(Gajendra!$N$13:$N$373,Gajendra!$P$13:$P$373,"September",Gajendra!$J$13:$J$373,"BD Spare") -> 30903.5 | AK104: =SUMIFS(Gajendra!$N$13:$N$373,Gajendra!$P$13:$P$373,"October",Gajendra!$J$13:$J$373,"BD Sapre") -> 0 | AL104: =SUMIFS(Gajendra!$N$13:$N$373,Gajendra!$P$13:$P$373,"November",Gajendra!$J$13:$J$373,"BD Sapre") -> 0 | AM104: =SUMIFS(Gajendra!$N$13:$N$373,Gajendra!$P$13:$P$373,"December",Gajendra!$J$13:$J$373,"BD Spare") -> 217000 | AP104: BD Spare | AQ104: =SUMIFS(Vinay!$N$13:$N$400,Vinay!$P$13:$P$400,"March",Vinay!$J$13:$J$400,"BD Spare") -> 0 | AR104: =SUMIFS(Vinay!$N$13:$N$400,Vinay!$P$13:$P$400,"April",Vinay!$J$13:$J$400,"BD Spare") -> 0 | AS104: =SUMIFS(Vinay!$N$13:$N$400,Vinay!$P$13:$P$400,"May",Vinay!$J$13:$J$400,"BD Spare") -> 0 | AT104: =SUMIFS(Vinay!$N$13:$N$400,Vinay!$P$13:$P$400,"June",Vinay!$J$13:$J$400,"BD Spare") -> 0 | AU104: =SUMIFS(Vinay!$N$13:$N$400,Vinay!$P$13:$P$400,"July",Vinay!$J$13:$J$400,"BD Spare") -> 256574 | AV104: =SUMIFS(Vinay!$N$13:$N$400,Vinay!$P$13:$P$400,"August",Vinay!$J$13:$J$400,"BD Spare") -> 259225 | AW104: =SUMIFS(Vinay!$N$13:$N$400,Vinay!$P$13:$P$400,"September",Vinay!$J$13:$J$400,"BD Spare") -> 0 | AX104: =SUMIFS(Vinay!$N$13:$N$400,Vinay!$P$13:$P$400,"October",Vinay!$J$13:$J$400,"BD Sapre") -> 0 | AY104: =SUMIFS(Vinay!$N$13:$N$400,Vinay!$P$13:$P$400,"November",Vinay!$J$13:$J$400,"BD Sapre") -> 0 | AZ104: =SUMIFS(Vinay!$N$13:$N$400,Vinay!$P$13:$P$400,"December",Vinay!$J$13:$J$400,"BD Spare") -> 0
...

Sheet Yogesh
AB1: Month wise data
A2: KARDEX INDIA - LIVE OFFER FUNEL - YOGESH - WEST | AB2: Month | AC2: Offers Total | AD2: Order received | AE2: Forecast | AF2: Forecast- Po Received
U3: Total Offered Value | V3: =SUM(N7:N408) -> 63775451 | AB3: January | AC3: =SUMIF($O$7:$O$408,"January",$N$7:$N$408) -> 7550534 | AD3: =SUMIF($U$7:$U$408,"January",$T$7:$T$408) -> 408580 | AE3: =SUMIF($P$7:$P$427,"January",$N$7:$N$427) -> 1503580 | AF3: =AE3-AD3 -> 1095000
A4: Total Offers | B4: =COUNTA(B7:B1429) -> 96 | R4: =SUMIFS(N13:N24,P13:P24,"April",J13:J24,"Contract") -> 0 | U4: Order Received | V4: =SUM(T7:T408) -> 45660707 | AB4: February | AC4: =SUMIF($O$7:$O$408,"February",$N$7:$N$408) -> 2845724 | AD4: =SUMIF($U$7:$U$408,"February",$T$7:$T$408) -> 1833000 | AE4: =SUMIF($P$7:$P$427,"February",$N$7:$N$427) -> 738000 | AF4: =AE4-AD4 -> -1095000
U5: Open Funnel | V5: =SUM(V7:V408) -> 13599894 | Y5: * Updated by Girija | AB5: March | AC5: =SUMIF($O$7:$O$408,"March",$N$7:$N$408) -> 27185038 | AD5: =SUMIF($U$7:$U$408,"March",$T$7:$T$408) -> 799106 | AE5: =SUMIF($P$7:$P$427,"March",$N$7:$N$427) -> 799106 | AF5: =AE5-AD5 -> 0
A6: SL | B6: Reg Date | C6: Company | D6: Location | E6: Department | F6: Contact Person Name | G6: Contact Number | H6: E-Mail ID | I6: Machine Serial Number | J6: Product Type | K6: Lead | L6: Offer Reference Number | M6: Offer Reference Date | N6: Offer Value | O6: Offer Month | P6: PO Expected Month | Q6: Probabality in Percentage | R6: PO Number | S6: PO Date | T6: PO Value | U6: PO Received Month | V6: Open Funnel | W6: Remarks | X6: Status | Y6: Booking Date in SAP B1 | Z6: Offer Entered in CRM | AA6: Offer Closed in CRM | AB6: April | AC6: =SUMIF($O$7:$O$408,"April",$N$7:$N$408) -> 380716 | AD6: =SUMIF($U$7:$U$408,"April",$T$7:$T$408) -> 29031268 | AE6: =SUMIF($P$7:$P$427,"April",$N$7:$N$427) -> 29793925 | AF6: =AE6-AD6 -> 762657
A7: 1 | B7: 45667 | C7: Tata Motors LTD | D7: Pune | E7: D blockstore | F7: pankaj Badhe | G7: 8237003520 | H7: badhe.pankaj@tatamotors.com | I7: 16002093/001 | J7: Relocation | K7: No | L7: KXIND/W/SPP/YD24-01 | M7: 45394 | N7: 0 | O7: January | P7: March | Q7: 0.5 | T7: 0 | V7: =Table62689345[[#This Row],[Offer Value]]-Table62689345[[#This Row],[PO Value]] -> 0 | W7: Project Postpone with no confirm date. | AB7: May | AC7: =SUMIF($O$7:$O$408,"May",$N$7:$N$408) -> 1732000 | AD7: =SUMIF($U$7:$U$408,"May",$T$7:$T$408) -> 1855692 | AE7: =SUMIF($P$7:$P$427,"May",$N$7:$N$427) -> 2155128 | AF7: =AE7-AD7 -> 299436
A8: 2 | C8: Tata Motors LTD | D8: Pune | E8: D blockstore | F8: pankaj Badhe | G8: 8237003521 | H8: badhe.pankaj@tatamotors.com | I8: 16002093/002 | J8: Relocation | K8: No | L8: KXIND/W/SPP/YD24-01 | M8: 45394 | N8: 0 | O8: January | P8: March | Q8: 0.5 | T8: 0 | V8: =Table62689345[[#This Row],[Offer Value]]-Table62689345[[#This Row],[PO Value]] -> 0 | W8: Project Postpone with no confirm date. | AB8: June | AC8: =SUMIF($O$7:$O$408,"June",$N$7:$N$408) -> 824959 | AD8: =SUMIF($U$7:$U$408,"June",$T$7:$T$408) -> 2134682 | AE8: =SUMIF($P$7:$P$427,"June",$N$7:$N$427) -> 2185972 | AF8: =AE8-AD8 -> 51290
A9: 3 | B9: 45667 | C9: Tetra Pak India Pvt Ltd | D9: Pune | E9: renovation store | F9: Vikas Patil | G9: 88888 78141 | H9: vikas.patil@tetrapak.com | I9: 20004190/001 | J9: Relocation | K9: No | L9: KXIND/W/SPP/YD24-02 | M9: 45394 | N9: 0 | O9: January | P9: March | Q9: 0.5 | T9: 0 | V9: =Table62689345[[#This Row],[Offer Value]]-Table62689345[[#This Row],[PO Value]] -> 0 | W9: Project Postpone with no confirm date. | AB9: July | AC9: =SUMIF($O$7:$O$408,"July",$N$7:$N$408) -> 2136554 | AD9: =SUMIF($U$7:$U$408,"July",$T$7:$T$408) -> 1689392 | AE9: =SUMIF($P$7:$P$427,"July",$N$7:$N$427) -> 1752032 | AF9: =AE9-AD9 -> 62640
A10: 4 | C10: Tetra Pak India Pvt Ltd | D10: Pune | E10: renovation store | F10: Vikas Patil | G10: 88888 78141 | H10: vikas.patil@tetrapak.com | I10: 20004190/002 | J10: Relocation | K10: No | L10: KXIND/W/SPP/YD24-02 | M10: 45394 | N10: 0 | O10: January | P10: March | Q10: 0.5 | T10: 0 | V10: =Table62689345[[#This Row],[Offer Value]]-Table62689345[[#This Row],[PO Value]] -> 0 | W10: Project Postpone with no confirm date. | AB10: August | AC10: =SUMIF($O$7:$O$408,"August",$N$7:$N$408) -> 3732804 | AD10: =SUMIF($U$7:$U$408,"August",$T$7:$T$408) -> 1688932 | AE10: =SUMIF($P$7:$P$427,"August",$N$7:$N$427) -> 2652512 | AF10: =AE10-AD10 -> 963580
A11: 5 | C11: Tetra Pak India Pvt Ltd | D11: Pune | E11: renovation store | F11: Vikas Patil | G11: 88888 78142 | H11: vikas.patil@tetrapak.com | I11: 20004190/003 | J11: Relocation | K11: No | L11: KXIND/W/SPP/YD24-02 | M11: 45394 | N11: 0 | O11: January | P11: March | Q11: 0.5 | T11: 0 | V11: =Table62689345[[#This Row],[Offer Value]]-Table62689345[[#This Row],[PO Value]] -> 0 | W11: Project Postpone with no confirm date. | AB11: September | AC11: =SUMIF($O$7:$O$408,"September",$N$7:$N$408) -> 7153666 | AD11: =SUMIF($U$7:$U$408,"September",$T$7:$T$408) -> 1746740 | AE11: =SUMIF($P$7:$P$427,"September",$N$7:$N$427) -> 4109040 | AF11: =AE11-AD11 -> 2362300
A12: 6 | B12: 45667 | C12: Schaeffler India Limited | D12: Pune | E12: Tool Room | F12: Sandip Gaikwad | G12: 7507568788 | H12: gaikwsnd@schaeffler.com; | I12: 17003031/001 | J12: Retrofit kit | K12: Yes | L12: KXIND/W/YD/SPP/25069R | M12: 45897 | N12: 2031058 | O12: August | P12: September | Q12: 0.5 | R12: 7001063894 | S12: 45922 | T12: 836318 | U12: September | V12: =Table62689345[[#This Row],[Offer Value]]-Table62689345[[#This Row],[PO Value]] -> 1194740 | Z12: Yes | AB12: October | AC12: =SUMIF($O$7:$O$408,"October",$N$7:$N$408) -> 443773 | AD12: =SUMIF($U$7:$U$408,"October",$T$7:$T$408) -> 2094893 | AE12: =SUMIF($P$7:$P$427,"October",$N$7:$N$427) -> 1603555 | AF12: =AE12-AD12 -> -491338
A13: 7 | B13: 45667 | C13: Mahindra Vehicals Mf LTD | D13: Pune | E13: P Blk Store | F13: Anant Jadhav | G13: 9503006627 | H13: anant.jadhav@mahindra.com | I13: 13000097/001 | J13: Contract | K13: No | L13: KXIND/W/YD/MC/24032 | M13: 45419 | N13: 56000 | O13: January | P13: June | Q13: 0.7 | R13: 6500007595 | S13: 45820 | T13: 56000 | U13: June | V13: =Table62689345[[#This Row],[PO Value]]-Table62689345[[#This Row],[Offer Value]] -> 0 | W13: PO received with software contract | AB13: November | AC13: =SUMIF($O$7:$O$408,"November",$N$7:$N$408) -> 7556364 | AD13: =SUMIF($U$7:$U$408,"November",$T$7:$T$408) -> 1087080 | AE13: =SUMIF($P$7:$P$427,"November",$N$7:$N$427) -> 1673209 | AF13: =AE13-AD13 -> 586129
A14: 8 | C14: Mahindra Vehicals Mf LTD | D14: Pune | E14: P Blk Store | F14: Anant Jadhav | G14: 9503006627 | H14: anant.jadhav@mahindra.com | I14: 17001697/001 | J14: Contract | K14: No | L14: KXIND/W/YD/MC/24032 | M14: 45419 | N14: 56000 | O14: January | P14: June | Q14: 0.7 | R14: 6500007595 | S14: 45820 | T14: 56000 | U14: June | V14: =Table62689345[[#This Row],[PO Value]]-Table62689345[[#This Row],[Offer Value]] -> 0 | W14: PO received with software contract | AB14: December | AC14: =SUMIF($O$7:$O$408,"December",$N$7:$N$408) -> 2233319 | AD14: =SUMIF($U$7:$U$408,"December",$T$7:$T$408) -> 1291342 | AE14: =SUMIF($P$7:$P$427,"December",$N$7:$N$427) -> 14809392 | AF14: =AE14-AD14 -> 13518050
A15: 9 | C15: Mahindra Vehicals Mf LTD | D15: Pune | E15: P Blk Store | F15: Anant Jadhav | G15: 9503006627 | H15: anant.jadhav@mahindra.com | I15: 17001697/002 | J15: Contract | K15: No | L15: KXIND/W/YD/MC/24032 | M15: 45419 | N15: 56000 | O15: January | P15: June | Q15: 0.7 | R15: 6500007595 | S15: 45820 | T15: 56000 | U15: June | V15: =Table62689345[[#This Row],[PO Value]]-Table62689345[[#This Row],[Offer Value]] -> 0 | W15: PO received with software contract
A16: 10 | C16: Mahindra Vehicals Mf LTD | D16: Pune | E16: P Blk Store | F16: Anant Jadhav | G16: 9503006627 | H16: anant.jadhav@mahindra.com | I16: 17001697/003 | J16: Contract | K16: No | L16: KXIND/W/YD/MC/24032 | M16: 45419 | N16: 56000 | O16: January | P16: June | Q16: 0.7 | R16: 6500007595 | S16: 45820 | T16: 56000 | U16: June | V16: =Table62689345[[#This Row],[PO Value]]-Table62689345[[#This Row],[Offer Value]] -> 0 | W16: PO received with software contract
A17: 11 | C17: Mahindra Vehicals Mf LTD | D17: Pune | E17: P Blk Store | F17: Anant Jadhav | G17: 9503006627 | H17: anant.jadhav@mahindra.com | I17: 17001697/004 | J17: Contract | K17: No | L17: KXIND/W/YD/MC/24032 | M17: 45419 | N17: 56000 | O17: January | P17: June | Q17: 0.7 | R17: 6500007595 | S17: 45820 | T17: 56000 | U17: June | V17: =Table62689345[[#This Row],[PO Value]]-Table62689345[[#This Row],[Offer Value]] -> 0 | W17: PO received with software contract
A18: 12 | C18: Mahindra Vehicals Mf LTD | D18: Pune | E18: P Blk Store | F18: Anant Jadhav | G18: 9503006627 | H18: anant.jadhav@mahindra.com | I18: 17004630/001 | J18: Contract | K18: No | L18: KXIND/W/YD/MC/24032 | M18: 45419 | N18: 56000 | O18: January | P18: June | Q18: 0.7 | R18: 6500007595 | S18: 45820 | T18: 56000 | U18: June | V18: =Table62689345[[#This Row],[PO Value]]-Table62689345[[#This Row],[Offer Value]] -> 0 | W18: PO received with software contract
A19: 13 | C19: Mahindra Vehicals Mf LTD | D19: Pune | E19: P Blk Store | F19: Anant Jadhav | G19: 9503006627 | H19: anant.jadhav@mahindra.com | I19: 17004630/003 | J19: Contract | K19: No | L19: KXIND/W/YD/MC/24032 | M19: 45419 | N19: 56000 | O19: January | P19: June | Q19: 0.7 | R19: 6500007595 | S19: 45820 | T19: 56000 | U19: June | V19: =Table62689345[[#This Row],[PO Value]]-Table62689345[[#This Row],[Offer Value]] -> 0 | W19: PO received with software contract
A20: 14 | C20: Mahindra Vehicals Mf LTD | D20: Pune | E20: P Blk Store | F20: Anant Jadhav | G20: 9503006627 | H20: anant.jadhav@mahindra.com | I20: 17004630/002 | J20: Contract | K20: No | L20: KXIND/W/YD/MC/24032 | M20: 45419 | N20: 56000 | O20: January | P20: June | Q20: 0.7 | R20: 6500007595 | S20: 45820 | T20: 56000 | U20: June | V20: =Table62689345[[#This Row],[PO Value]]-Table62689345[[#This Row],[Offer Value]] -> 0 | W20: PO received with software contract
A21: 15 | B21: 45667 | C21: Bajaj Auto Ltd | D21: Pune | E21: Engine Assembly | F21: Rajkumar Ajabe | G21: 9613370060 | H21: rrajabe@bajajauto.co.in | I21: 17004630/003 | J21: SPP | K21: Yes | L21: KXIND/W/YD/SPP/25018 | M21: 45701 | N21: 141032 | O21: February | P21: June | Q21: 0.5 | R21: 5210059205 | S21: 45793 | T21: 95742 | U21: June | V21: =Table62689345[[#This Row],[PO Value]]-Table62689345[[#This Row],[Offer Value]] -> -45290
A22: 16 | B22: 45667 | C22: ITC Ltd | D22: Pune | E22: Engineering stores | F22: Navanath Ekatpure | G22: 9730478741 | H22: navanath.ekatpure@itc.in | I22: 09006715/001 | J22: SPP | K22: Yes | L22: KXIND/W/YD/SPP/24052 | M22: 45607 | N22: 739430 | O22: January | P22: May | Q22: 0.5 | R22: 4700392647 | S22: 25.04.2025 | T22: 709852 | U22: May | V22: =Table62689345[[#This Row],[PO Value]]-Table62689345[[#This Row],[Offer Value]] -> -29578 | Z22: Yes
A23: 138 | B23: 45922 | C23: Tata Motors LTD | D23: Pune | E23: Cblk Maint | F23: Amit sharma | G23: 9011018387 | H23: s.amit1@tatamotors.com | I23: 06008006/001 | J23: Software | K23: Yes | L23: KRIND/SA/OTH/520025 | M23: 45916 | N23: 1378000 | O23: September | P23: December | Q23: 0.3 | V23: =Table62689345[[#This Row],[Offer Value]]-Table62689345[[#This Row],[PO Value]] -> 1378000
A24: 18 | B24: 45667 | C24: TOP Hydrofit PVT LTD | D24: Pune | E24: stores | F24: Hemant tarate | G24: 9881134849 | H24: info@tophydrofit.com | I24: 11001071/001 | J24: SPP | K24: Yes | L24: KXIND/W/YD/SPP/24055 | M24: 45334 | N24: 0 | O24: January | P24: July | Q24: 0.3 | T24: 0 | V24: =Table62689345[[#This Row],[PO Value]]-Table62689345[[#This Row],[Offer Value]] -> 0
A25: 19 | B25: 45667 | C25: GIC Instruments Pvt Ltd | D25: Pune | E25: stores | F25: Ajinkya Desale | G25: 9403849891 | H25: ajinkya.dhekale@gicindia.com | I25: 08010151/001 | J25: SPP | K25: Yes | L25: KXIND/W/YD/SPP/24063 | M25: 12/12/204 | N25: 35000 | O25: January | P25: January | Q25: 0.7 | R25: 7356 | S25: 45667 | T25: 35000 | U25: January | V25: =Table62689345[[#This Row],[PO Value]]-Table62689345[[#This Row],[Offer Value]] -> 0 | Y25: 17/1/2025
A26: 20 | B26: 45667 | C26: Mahindra Vehicals Mf LTD | D26: Pune | E26: Pblock Logistics | F26: Rahul Adhav | G26: 8983467616 | H26: ADHAV.RAHUL@mahindra.com | I26: 17001697/004 | J26: SPP | K26: Yes | L26: KXIND/W/YD/SPP/24062 | M26: 45638 | N26: 647302 | O26: January | P26: September | Q26: 0.7 | R26: 66020580 | S26: 45957 | T26: 649648 | U26: October | V26: =Table62689345[[#This Row],[PO Value]]-Table62689345[[#This Row],[Offer Value]] -> 2346 | W26: Customer Budget Peocess unlock on 18th.April so request for Pricing on ARIBA will be received 2nd.Week of May | Z26: yes
A27: 21 | B27: 45668 | C27: Bosch Chassis Systems India Ltd | D27: Pune | E27: maintenance store | F27: Pratap Jagdale | G27: 9970010738 | H27: Pratap.Jagadale@in.bosch.com | I27: 19004857/001 | J27: Contract | K27: No | L27: KXIND/W/YD/MC/24066 | M27: 45644 | N27: 73500 | O27: January | P27: January | Q27: 1 | R27: 85375744 | S27: 45658 | T27: 73500 | U27: January | V27: =Table62689345[[#This Row],[PO Value]]-Table62689345[[#This Row],[Offer Value]] -> 0
A28: 22 | B28: 45668 | C28: Coesia India Pvt.Ltd. | D28: Pune | E28: stores | F28: D.Kadam | G28: 9552599231 | H28: dnyaneshwar.kadam@coesia.com | I28: 16000669/001 | J28: Contract | K28: No | L28: KXIND/W/YD/MC/24069 | M28: 45644 | N28: 83040 | O28: January | P28: January | Q28: 0.8 | R28: CGT250008 | S28: 45677 | T28: 83040 | U28: January | V28: =Table62689345[[#This Row],[PO Value]]-Table62689345[[#This Row],[Offer Value]] -> 0 | W28: PO with software contract S/C value 25043
A29: 23 | C29: Coesia India Pvt.Ltd. | D29: Pune | E29: stores | F29: D.Kadam | G29: 9552599231 | H29: dnyaneshwar.kadam@coesia.com | I29: 16000668/001 | J29: Contract | K29: No | L29: KXIND/W/YD/MC/24069 | M29: 45644 | N29: 83040 | O29: January | P29: January | Q29: 0.8 | R29: CGT250008 | S29: 45677 | T29: 83040 | U29: January | V29: =Table62689345[[#This Row],[PO Value]]-Table62689345[[#This Row],[Offer Value]] -> 0 | W29: PO with software contract S/C value 25043
A30: 24 | B30: 45668 | C30: Eagle Burgmann India Pvt Ltd | D30: Pune | E30: stores | F30: Mahesh Hole | G30: 9373850080 | H30: Mahesh.Hole@in.eagleburgmann.com | I30: 08004851/001 | J30: Contract | K30: No | L30: KXIND/W/YD/MC/24071 | M30: 45644 | N30: 160000 | O30: January | P30: February | Q30: 0.8 | R30: 2481406 | S30: 45673 | T30: 160000 | U30: February | V30: =Table62689345[[#This Row],[PO Value]]-Table62689345[[#This Row],[Offer Value]] -> 0
A31: 25 | B31: 45668 | C31: Harman International (I) Pvt Ltd | D31: Pune | E31: stores | F31: Santosh Deshmukh | G31: 9552599231 | H31: santosh.deshmukh@harman.com | I31: 19005224/001 | J31: Contract | K31: No | L31: KXIND/W/YD/MC/24067 | M31: 45644 | N31: 93000 | O31: January | P31: February | Q31: 0.8 | R31: 7700326717 | S31: 45779 | T31: 93000 | U31: February | V31: =Table62689345[[#This Row],[PO Value]]-Table62689345[[#This Row],[Offer Value]] -> 0
A32: 26 | C32: Harman International (I) Pvt Ltd | D32: Pune | E32: stores | F32: Santosh Deshmukh | G32: 9552599231 | H32: santosh.deshmukh@harman.com | I32: 19005224/002 | J32: Contract | K32: No | L32: KXIND/W/YD/MC/24067 | M32: 45644 | N32: 93000 | O32: January | P32: February | Q32: 0.8 | R32: 7700326717 | S32: 45779 | T32: 93000 | U32: February | V32: =Table62689345[[#This Row],[PO Value]]-Table62689345[[#This Row],[Offer Value]] -> 0
A33: 27 | C33: Harman International (I) Pvt Ltd | D33: Pune | E33: stores | F33: Santosh Deshmukh | G33: 9552599231 | H33: santosh.deshmukh@harman.com | I33: 19005224/003 | J33: Contract | K33: No | L33: KXIND/W/YD/MC/24067 | M33: 45644 | N33: 93000 | O33: January | P33: February | Q33: 0.8 | R33: 7700326717 | S33: 45779 | T33: 93000 | U33: February | V33: =Table62689345[[#This Row],[PO Value]]-Table62689345[[#This Row],[Offer Value]] -> 0
A34: 28 | C34: Harman International (I) Pvt Ltd | D34: Pune | E34: stores | F34: Santosh Deshmukh | G34: 9552599231 | H34: santosh.deshmukh@harman.com | I34: 23002397/001 | J34: Contract | K34: No | L34: KXIND/W/YD/MC/24067 | M34: 45644 | N34: 93000 | O34: January | P34: February | Q34: 0.8 | R34: 7700326717 | S34: 45779 | T34: 93000 | U34: February | V34: =Table62689345[[#This Row],[PO Value]]-Table62689345[[#This Row],[Offer Value]] -> 0
A35: 29 | B35: 45668 | C35: Klug avalon mechatronics | D35: Pune | E35: stores | F35: N.Patil | G35: 9271117805 | H35: rms@klugavalon.com | I35: 16007512/001 | J35: Contract | K35: No | L35: KXIND/W/YD/MC/24072 | M35: 45644 | N35: 60000 | O35: January | P35: February | Q35: 0.8 | R35: 7388 | S35: 45667 | T35: 60000 | U35: February | V35: =Table62689345[[#This Row],[PO Value]]-Table62689345[[#This Row],[Offer Value]] -> 0
A36: 30 | B36: 45668 | C36: Schaeffler India Limited | D36: Pune | E36: Tool Room | F36: Ananda. A | G36: 9923177609 | H36: asoduaan@schaeffler.com | I36: 19004014/001 | J36: Contract | K36: No | L36: KXIND/W/YD/MC/24076 | M36: 45653 | N36: 67000 | O36: January | P36: January | Q36: 0.8 | R36: 0042 / Y20 / 38369028 | S36: 45671 | T36: 67000 | U36: January | V36: =Table62689345[[#This Row],[PO Value]]-Table62689345[[#This Row],[Offer Value]] -> 0
A37: 31 | C37: Schaeffler India Limited | D37: Pune | E37: Tool Room | F37: Ananda. A | G37: 9923177609 | H37: asoduaan@schaeffler.com | I37: 102006187 | J37: Contract | K37: No | L37: KXIND/W/YD/MC/24076 | M37: 45653 | N37: 67000 | O37: January | P37: January | Q37: 0.8 | R37: 0042 / Y20 / 38414491 | S37: 45664 | T37: 67000 | U37: January | V37: =Table62689345[[#This Row],[PO Value]]-Table62689345[[#This Row],[Offer Value]] -> 0
A38: 32 | B38: 45668 | C38: Tetra Pak India Pvt Ltd | D38: Pune | E38: Spare stores | F38: Vivek Kamya | G38: +91 9850 8069 74 | H38: Vivek.Kyama@tetrapak.com | I38: 07009761/001 | J38: Contract | K38: No | L38: KXIND/W/YD/MC/24070 | M38: 45644 | N38: 96000 | O38: January | P38: February | Q38: 0.8 | R38: 927358056 | S38: 45672 | T38: 96000 | U38: February | V38: =Table62689345[[#This Row],[PO Value]]-Table62689345[[#This Row],[Offer Value]] -> 0
A39: 33 | B39: 45668 | C39: Tata motors passenger vehicles Limted (Tata Motors Ltd) | D39: Pune | E39: Logistics | F39: Ravindra wani | G39: 7276004059 | H39: ravindra.wani@tatamotors.com | I39: 08000931/001 | J39: Contract | K39: No | L39: KXIND/W/YD/MC/24057 | M39: 45424 | N39: 82080 | O39: January | P39: April | Q39: 0.7 | R39: 2265005504 | S39: 45754 | T39: 82080 | U39: April | V39: =Table62689345[[#This Row],[PO Value]]-Table62689345[[#This Row],[Offer Value]] -> 0
A40: 34 | C40: Tata motors passenger vehicles Limted (Tata Motors Ltd) | D40: Pune | E40: Logistics | F40: Ravindra wani | G40: 7276004060 | H40: ravindra.wani@tatamotors.com | I40: 08000931/002 | J40: Contract | K40: No | L40: KXIND/W/YD/MC/24057 | M40: 45424 | N40: 82080 | O40: January | P40: April | Q40: 0.7 | R40: 2265005504 | S40: 45754 | T40: 82080 | U40: April | V40: =Table62689345[[#This Row],[PO Value]]-Table62689345[[#This Row],[Offer Value]] -> 0
A41: 35 | C41: Tata motors passenger vehicles Limted (Tata Motors Ltd) | D41: Pune | E41: Logistics | F41: Ravindra wani | G41: 7276004061 | H41: ravindra.wani@tatamotors.com | I41: 07000901/001 | J41: Contract | K41: No | L41: KXIND/W/YD/MC/24057 | M41: 45424 | N41: 82080 | O41: January | P41: April | Q41: 0.7 | R41: 2265005504 | S41: 45754 | T41: 82080 | U41: April | V41: =Table62689345[[#This Row],[PO Value]]-Table62689345[[#This Row],[Offer Value]] -> 0
A42: 36 | C42: Tata motors passenger vehicles Limted (Tata Motors Ltd) | D42: Pune | E42: Logistics | F42: Ravindra wani | G42: 7276004062 | H42: ravindra.wani@tatamotors.com | I42: 07000901/002 | J42: Contract | K42: No | L42: KXIND/W/YD/MC/24057 | M42: 45424 | N42: 82080 | O42: January | P42: April | Q42: 0.7 | R42: 2265005504 | S42: 45754 | T42: 82080 | U42: April | V42: =Table62689345[[#This Row],[PO Value]]-Table62689345[[#This Row],[Offer Value]] -> 0
A43: 37 | C43: Tata motors passenger vehicles Limted (Tata Motors Ltd) | D43: Pune | E43: Logistics | F43: Ravindra wani | G43: 7276004063 | H43: ravindra.wani@tatamotors.com | I43: 07000904/001 | J43: Contract | K43: No | L43: KXIND/W/YD/MC/24057 | M43: 45424 | N43: 82080 | O43: January | P43: April | Q43: 0.7 | R43: 2265005504 | S43: 45754 | T43: 82080 | U43: April | V43: =Table62689345[[#This Row],[PO Value]]-Table62689345[[#This Row],[Offer Value]] -> 0
A44: 38 | C44: Tata motors passenger vehicles Limted (Tata Motors Ltd) | D44: Pune | E44: Logistics | F44: Ravindra wani | G44: 7276004064 | H44: ravindra.wani@tatamotors.com | I44: 07000904/002 | J44: Contract | K44: No | L44: KXIND/W/YD/MC/24057 | M44: 45424 | N44: 82080 | O44: January | P44: April | Q44: 0.7 | R44: 2265005504 | S44: 45754 | T44: 82080 | U44: April | V44: =Table62689345[[#This Row],[PO Value]]-Table62689345[[#This Row],[Offer Value]] -> 0
A45: 39 | C45: Tata motors passenger vehicles Limted (Tata Motors Ltd) | D45: Pune | E45: Logistics | F45: Ravindra wani | G45: 7276004065 | H45: ravindra.wani@tatamotors.com | I45: 07007494/001 | J45: Contract | K45: No | L45: KXIND/W/YD/MC/24057 | M45: 45424 | N45: 82080 | O45: January | P45: April | Q45: 0.7 | R45: 2265005504 | S45: 45754 | T45: 82080 | U45: April | V45: =Table62689345[[#This Row],[PO Value]]-Table62689345[[#This Row],[Offer Value]] -> 0
A46: 40 | C46: Tata motors passenger vehicles Limted (Tata Motors Ltd) | D46: Pune | E46: Logistics | F46: Ravindra wani | G46: 7276004066 | H46: ravindra.wani@tatamotors.com | I46: 06009440/001 | J46: Contract | K46: No | L46: KXIND/W/YD/MC/24057 | M46: 45424 | N46: 82080 | O46: January | P46: April | Q46: 0.7 | R46: 2265005504 | S46: 45754 | T46: 82080 | U46: April | V46: =Table62689345[[#This Row],[PO Value]]-Table62689345[[#This Row],[Offer Value]] -> 0
A47: 41 | C47: Tata motors passenger vehicles Limted (Tata Motors Ltd) | D47: Pune | E47: Logistics | F47: Ravindra wani | G47: 7276004067 | H47: ravindra.wani@tatamotors.com | I47: 06009440/002 | J47: Contract | K47: No | L47: KXIND/W/YD/MC/24057 | M47: 45424 | N47: 82080 | O47: January | P47: April | Q47: 0.7 | R47: 2265005504 | S47: 45754 | T47: 82080 | U47: April | V47: =Table62689345[[#This Row],[PO Value]]-Table62689345[[#This Row],[Offer Value]] -> 0
A48: 42 | C48: Tata motors passenger vehicles Limted (Tata Motors Ltd) | D48: Pune | E48: Logistics | F48: Ravindra wani | G48: 7276004068 | H48: ravindra.wani@tatamotors.com | I48: 06009440/003 | J48: Contract | K48: No | L48: KXIND/W/YD/MC/24057 | M48: 45424 | N48: 82080 | O48: January | P48: April | Q48: 0.7 | R48: 2265005504 | S48: 45754 | T48: 82080 | U48: April | V48: =Table62689345[[#This Row],[PO Value]]-Table62689345[[#This Row],[Offer Value]] -> 0
A49: 43 | C49: Tata motors passenger vehicles Limted (Tata Motors Ltd) | D49: Pune | E49: Logistics | F49: Ravindra wani | G49: 7276004069 | H49: ravindra.wani@tatamotors.com | I49: 07007497/002 | J49: Contract | K49: No | L49: KXIND/W/YD/MC/24057 | M49: 45424 | N49: 82080 | O49: January | P49: April | Q49: 0.7 | R49: 2265005504 | S49: 45754 | T49: 82080 | U49: April | V49: =Table62689345[[#This Row],[PO Value]]-Table62689345[[#This Row],[Offer Value]] -> 0
A50: 44 | C50: Tata motors passenger vehicles Limted (Tata Motors Ltd) | D50: Pune | E50: Logistics | F50: Ravindra wani | G50: 7276004070 | H50: ravindra.wani@tatamotors.com | I50: 05000458/001 | J50: Contract | K50: No | L50: KXIND/W/YD/MC/24057 | M50: 45424 | N50: 82080 | O50: January | P50: April | Q50: 0.7 | R50: 2265005504 | S50: 45754 | T50: 82080 | U50: April | V50: =Table62689345[[#This Row],[PO Value]]-Table62689345[[#This Row],[Offer Value]] -> 0
A51: 45 | C51: Tata motors passenger vehicles Limted (Tata Motors Ltd) | D51: Pune | E51: Logistics | F51: Ravindra wani | G51: 7276004071 | H51: ravindra.wani@tatamotors.com | I51: 05000458/002 | J51: Contract | K51: No | L51: KXIND/W/YD/MC/24057 | M51: 45424 | N51: 82080 | O51: January | P51: April | Q51: 0.7 | R51: 2265005504 | S51: 45754 | T51: 82080 | U51: April | V51: =Table62689345[[#This Row],[PO Value]]-Table62689345[[#This Row],[Offer Value]] -> 0
A52: 46 | B52: 45668 | C52: Minda Industries LTD | D52: Pune | E52: Tool Room | F52: D T Narawade | G52: 7276413858 | H52: dtnarawade@unominda.com | I52: 03007276/001 | J52: BD Charges | K52: No | L52: KXIND/W/YD/SER/2504 | M52: 45666 | N52: 22500 | O52: January | P52: June | Q52: 0.5 | R52: 4300416395 | S52: 45801 | T52: 22500 | U52: June | V52: =Table62689345[[#This Row],[PO Value]]-Table62689345[[#This Row],[Offer Value]] -> 0
A53: 47 | B53: 45668 | C53: Kirloskar Oil Engine LTD | D53: Pune | E53: Stores | F53: Sayajirao Mali | G53: 9881734612 | H53: sayajirao.mali@kirloskar.com | I53: 07000530/001 | J53: Contract | K53: No | L53: KXIND/W/MC/YD/2505 | M53: 45666 | N53: 64000 | O53: January | P53: June | Q53: 0.5 | R53: 7026010733 | S53: 45819 | T53: 64000 | U53: June | V53: =Table62689345[[#This Row],[PO Value]]-Table62689345[[#This Row],[Offer Value]] -> 0
A54: 48 | C54: Kirloskar Oil Engine LTD | D54: Pune | E54: Stores | F54: Sayajirao Mali | G54: 9881734612 | H54: sayajirao.mali@kirloskar.com | I54: 07007199/001 | J54: Contract | K54: No | L54: KXIND/W/MC/YD/2505 | M54: 45666 | N54: 64000 | O54: January | P54: June | Q54: 0.5 | R54: 7026010733 | S54: 45819 | T54: 64000 | U54: June | V54: =Table62689345[[#This Row],[PO Value]]-Table62689345[[#This Row],[Offer Value]] -> 0
A55: 49 | C55: Kirloskar Oil Engine LTD | D55: Pune | E55: Stores | F55: Sayajirao Mali | G55: 9881734612 | H55: sayajirao.mali@kirloskar.com | I55: 07007204/001 | J55: Contract | K55: No | L55: KXIND/W/MC/YD/2505 | M55: 45666 | N55: 64000 | O55: January | P55: June | Q55: 0.5 | R55: 7026010733 | S55: 45819 | T55: 64000 | U55: June | V55: =Table62689345[[#This Row],[PO Value]]-Table62689345[[#This Row],[Offer Value]] -> 0
A56: 50 | C56: Kirloskar Oil Engine LTD | D56: Pune | E56: Stores | F56: Sayajirao Mali | G56: 9881734612 | H56: sayajirao.mali@kirloskar.com | I56: 07008022/001 | J56: Contract | K56: No | L56: KXIND/W/MC/YD/2505 | M56: 45666 | N56: 64000 | O56: January | P56: June | Q56: 0.5 | R56: 7026010733 | S56: 45819 | T56: 64000 | U56: June | V56: =Table62689345[[#This Row],[PO Value]]-Table62689345[[#This Row],[Offer Value]] -> 0
A57: 51 | C57: Kirloskar Oil Engine LTD | D57: Pune | E57: Stores | F57: Sayajirao Mali | G57: 9881734612 | H57: sayajirao.mali@kirloskar.com | I57: 07008406/001 | J57: Contract | K57: No | L57: KXIND/W/MC/YD/2505 | M57: 45666 | N57: 64000 | O57: January | P57: June | Q57: 0.5 | R57: 7026010733 | S57: 45819 | T57: 64000 | U57: June | V57: =Table62689345[[#This Row],[PO Value]]-Table62689345[[#This Row],[Offer Value]] -> 0
A58: 52 | C58: Kirloskar Oil Engine LTD | D58: Pune | E58: Stores | F58: Sayajirao Mali | G58: 9881734612 | H58: sayajirao.mali@kirloskar.com | I58: 07010686/001 | J58: Contract | K58: No | L58: KXIND/W/MC/YD/2505 | M58: 45666 | N58: 64000 | O58: January | P58: June | Q58: 0.5 | R58: 7026010733 | S58: 45819 | T58: 64000 | U58: June | V58: =Table62689345[[#This Row],[PO Value]]-Table62689345[[#This Row],[Offer Value]] -> 0
A59: 53 | C59: Kirloskar Oil Engine LTD | D59: Pune | E59: Stores | F59: Sayajirao Mali | G59: 9881734612 | H59: sayajirao.mali@kirloskar.com | I59: 16000438/002 | J59: Contract | K59: No | L59: KXIND/W/MC/YD/2505 | M59: 45666 | N59: 64000 | O59: January | P59: June | Q59: 0.5 | R59: 7026010733 | S59: 45819 | T59: 64000 | U59: June | V59: =Table62689345[[#This Row],[PO Value]]-Table62689345[[#This Row],[Offer Value]] -> 0
A60: 54 | C60: Kirloskar Oil Engine LTD | D60: Pune | E60: Stores | F60: Sayajirao Mali | G60: 9881734612 | H60: sayajirao.mali@kirloskar.com | I60: 16000438/001 | J60: Contract | K60: No | L60: KXIND/W/MC/YD/2505 | M60: 45666 | N60: 64000 | O60: January | P60: June | Q60: 0.5 | R60: 7026010733 | S60: 45819 | T60: 64000 | U60: June | V60: =Table62689345[[#This Row],[PO Value]]-Table62689345[[#This Row],[Offer Value]] -> 0
A61: 55 | B61: 45668 | C61: Tata motors passenger vehicles Limted (Tata Motors Ltd) | D61: Pune | E61: Tool Crib | F61: sagar kulkarni | G61: 9511742041 | H61: sagar.kulkarni@tatamotors.com | I61: 04006517/001 | J61: Contract | K61: No | L61: KXIND/W/MC/YD/24077 | M61: 45653 | N61: 82080 | O61: January | P61: April | Q61: 0.6 | R61: 2265005320 | S61: 45722 | T61: 82080 | U61: April | V61: =Table62689345[[#This Row],[PO Value]]-Table62689345[[#This Row],[Offer Value]] -> 0
A62: 56 | C62: Tata motors passenger vehicles Limted (Tata Motors Ltd) | D62: Pune | E62: Tool Crib | F62: sagar kulkarni | G62: 9511742041 | H62: sagar.kulkarni@tatamotors.com | I62: 04006517/002 | J62: Contract | K62: No | L62: KXIND/W/MC/YD/24077 | M62: 45653 | N62: 82080 | O62: January | P62: April | Q62: 0.6 | R62: 2265005320 | S62: 45722 | T62: 82080 | U62: April | V62: =Table62689345[[#This Row],[PO Value]]-Table62689345[[#This Row],[Offer Value]] -> 0
A63: 17 | B63: 45999 | C63: Tata motors passenger vehicles Limted (Tata Motors Ltd) | D63: Pune | E63: TCF | F63: Depak Dalvi | G63: 9850341560 | H63: DGD793450@tatamotors.com | I63: 08000931/001 | J63: SPP | K63: Yes | L63: KXIND/W/YD/SPP/25088 | M63: 45989 | N63: 346200 | O63: November | P63: December | Q63: 0.2 | T63: 0 | V63: =Table62689345[[#This Row],[PO Value]]-Table62689345[[#This Row],[Offer Value]] -> -346200 | W63: Purchase will be plan after budgetin after 31st.March | Z63: yes
A64: 58 | B64: 45668 | C64: Klug avalon mechatronics | D64: Pune | E64: stores | F64: N.Patil | G64: 9271117805 | H64: rms@klugavalon.com | I64: 16007512/001 | J64: SPP | K64: Yes | L64: KXIND/W/YD/SPP/2505 | M64: 45666 | N64: 0 | O64: January | P64: July | Q64: 0.2 | V64: =Table62689345[[#This Row],[PO Value]]-Table62689345[[#This Row],[Offer Value]] -> 0 | W64: Not Appoved by management
A65: 59 | B65: 45668 | C65: Merck Life Science Pvt Ltd | D65: Mumbai | E65: stores | F65: Kalpesh Patil | G65: 9762817803 | H65: Kalpesh.patil@external.merckgroup.com | I65: 23004830/001 | J65: SPP | K65: Yes | L65: KXIND/W/YD/SPP/24068 | M65: 45644 | N65: 1276654 | O65: January | P65: April | Q65: 0.4 | R65: 5030114286 | S65: 45750 | T65: 584024 | U65: April | V65: =Table62689345[[#This Row],[PO Value]]-Table62689345[[#This Row],[Offer Value]] -> -692630 | Z65: yes | AA65: Yes
A66: 60 | B66: 45705 | C66: Lupin Limited | D66: Nagpur | E66: Stores | F66: Mukesh Namdev | G66: +91 8959678211 | H66: mukeshnamdev@lupin.com | I66: 23005504/001 | J66: Contract | K66: Yes | L66: KXIND/W/YD/MC/2509R | M66: 45863 | N66: 55000 | O66: July | P66: August | Q66: 0.5 | V66: =Table62689345[[#This Row],[PO Value]]-Table62689345[[#This Row],[Offer Value]] -> -55000 | W66: Revised offer submitted
A67: 61 | B67: 45705 | C67: GIC Instruments Pvt Ltd | D67: Pune | E67: stores | F67: Ajinkya Desale | G67: 9403849891 | H67: ajinkya.dhekale@gicindia.com | I67: 22005568/001 | J67: Contract | K67: Yes | L67: KXIND/W/YD/MC/25010 | M67: 29/01/2025 | N67: 78000 | O67: January | P67: May | Q67: 0.5 | R67: 26001159 | S67: 45798 | T67: 78000 | U67: May | V67: =Table62689345[[#This Row],[PO Value]]-Table62689345[[#This Row],[Offer Value]] -> 0
A68: 62 | B68: 45705 | C68: Bajaj Auto Ltd | D68: Pune | E68: MTD store | F68: KIRAN S MAKHAMALE | G68: (020)66106409 | H68: ksmakhamale@bajajauto.co.in | I68: 14006953/001 | J68: Contract | K68: No | L68: KXIND/W/YD/MC/25014R | M68: 45993 | N68: 50000 | O68: February | P68: February | Q68: 0.6 | R68: 3110014461 | S68: 45700 | T68: 50000 | U68: February | V68: =Table62689345[[#This Row],[PO Value]]-Table62689345[[#This Row],[Offer Value]] -> 0
A69: 63 | B69: 45705 | C69: Fiat india Automobiles Pvt. LTD | D69: Pune | E69: stores | F69: Ajinkya Suryavanshi | G69: 7875555910 | H69: Ajinkya.Suryavanshi@fiapl.com | I69: 08008916/001 | J69: Contract | K69: No | L69: KXIND/W/YD/MC/25015 | M69: 45993 | N69: 46500 | O69: February | P69: June | Q69: 0.5 | R69: 4518004947 | S69: 45812 | T69: 46500 | U69: June | V69: =Table62689345[[#This Row],[PO Value]]-Table62689345[[#This Row],[Offer Value]] -> 0 | W69: Offer including SW contract
A70: 64 | C70: Fiat india Automobiles Pvt. LTD | D70: Pune | E70: stores | F70: Ajinkya Suryavanshi | G70: 7875555910 | H70: Ajinkya.Suryavanshi@fiapl.com | I70: 08008916/002 | J70: Contract | K70: No | L70: KXIND/W/YD/MC/25015 | M70: 45993 | N70: 46500 | O70: February | P70: June | Q70: 0.5 | R70: 4518004947 | S70: 45812 | T70: 46500 | U70: June | V70: =Table62689345[[#This Row],[PO Value]]-Table62689345[[#This Row],[Offer Value]] -> 0 | W70: Offer including SW contract
A71: 65 | C71: Fiat india Automobiles Pvt. LTD | D71: Pune | E71: Stores | F71: Ajinkya Suryavanshi | G71: 7875555910 | H71: Ajinkya.Suryavanshi@fiapl.com | I71: 10005771/001 | J71: Contract | K71: No | L71: KXIND/W/YD/MC/25015 | M71: 45993 | N71: 46500 | O71: February | P71: June | Q71: 0.5 | R71: 4518004947 | S71: 45812 | T71: 46500 | U71: June | V71: =Table62689345[[#This Row],[PO Value]]-Table62689345[[#This Row],[Offer Value]] -> 0 | W71: Offer including SW contract
A72: 66 | C72: Fiat india Automobiles Pvt. LTD | D72: Pune | E72: stores | F72: Ajinkya Suryavanshi | G72: 7875555910 | H72: Ajinkya.Suryavanshi@fiapl.com | I72: 10005770/001 | J72: Contract | K72: No | L72: KXIND/W/YD/MC/25015 | M72: 45993 | N72: 46500 | O72: February | P72: June | Q72: 0.5 | R72: 4518004947 | S72: 45812 | T72: 46500 | U72: June | V72: =Table62689345[[#This Row],[PO Value]]-Table62689345[[#This Row],[Offer Value]] -> 0 | W72: Offer including SW contract
A73: 67 | B73: 45705 | C73: Skoda Auto Volkswagen India Pvt Ltd | D73: Pune | E73: stores | F73: Pranav shinde | G73: 7744051513 | H73: pranav.shinde1@skoda-vw.co.in | I73: 102008505 | J73: SPP | K73: Yes | L73: KXIND/W/YD/SPP/25013 | M73: 45687 | N73: 651370 | O73: February | P73: April | Q73: 0.5 | R73: 8000155101 | S73: 45758 | T73: 625314 | U73: April | V73: =Table62689345[[#This Row],[PO Value]]-Table62689345[[#This Row],[Offer Value]] -> -26056 | Z73: Yes | AA73: Yes
A74: 137 | B74: 45922 | C74: Tata Motors LTD | D74: Pune | E74: Cblk Maint | F74: Amit sharma | G74: 9011018387 | H74: s.amit1@tatamotors.com | I74: 06008006/001 | J74: Relocation | K74: Yes | L74: KRIND/W/YD/RE/25069 | M74: 15-092025 | N74: 1160000 | O74: September | P74: December | Q74: 0.3 | V74: =Table62689345[[#This Row],[Offer Value]]-Table62689345[[#This Row],[PO Value]] -> 1160000
A75: 69 | B75: 45705 | C75: Carraro India Pvt Limited | D75: Pune | E75: stores | F75: Ravindra khambayat | G75: 9822840261 | H75: Ravindra_Khambayat@carraro.com | I75: 23004830/001 | J75: SPP | K75: Yes | L75: KXIND/W/YD/SPP/25012 | M75: 45687 | N75: 85916 | O75: February | P75: April | Q75: 0.5 | R75: 4500527548 | S75: 45740 | T75: 52380 | U75: April | V75: =Table62689345[[#This Row],[PO Value]]-Table62689345[[#This Row],[Offer Value]] -> -33536
A76: 70 | B76: 45705 | C76: Bajaj Auto Ltd | D76: Pune | E76: veh.store | F76: Ganesh Navale | G76: 9503050525 | H76: ganesh.navale@bajaj.co.in | I76: 18001594/001 | J76: SPP | K76: Yes | L76: KXIND/W/YD/SPP/24025 | M76: 13/02/2025 | N76: 185900 | O76: January | P76: April | Q76: 0.5 | R76: 5210058236 | S76: 45737 | T76: 178464 | U76: April | V76: =Table62689345[[#This Row],[PO Value]]-Table62689345[[#This Row],[Offer Value]] -> -7436
A77: 71 | B77: 45705 | C77: Skoda Auto Volkswagen India Pvt Ltd | D77: Pune | E77: stores | F77: Pranav shinde | G77: 7744051513 | H77: pranav.shinde1@skoda-vw.co.in | I77: 102008505 | J77: Contract | K77: No | L77: KXIND/W/YD/SPP/2519 | M77: 17/02/2025 | N77: 127200 | O77: February | P77: April | Q77: 0.5 | R77: 8000155292 | S77: 45768 | T77: 127200 | U77: April | V77: =Table62689345[[#This Row],[PO Value]]-Table62689345[[#This Row],[Offer Value]] -> 0 | W77: Offer including SW contract
A78: 72 | C78: Skoda Auto Volkswagen India Pvt Ltd | D78: Pune | E78: stores | F78: Pranav shinde | G78: 7744051513 | H78: pranav.shinde1@skoda-vw.co.in | I78: 102008506 | J78: Contract | K78: No | L78: KXIND/W/YD/SPP/2519 | M78: 17/02/2025 | N78: 127200 | O78: February | P78: April | Q78: 0.5 | R78: 8000155292 | S78: 45768 | T78: 127200 | U78: April | V78: =Table62689345[[#This Row],[PO Value]]-Table62689345[[#This Row],[Offer Value]] -> 0 | W78: Offer including SW contract
A79: 73 | C79: Skoda Auto Volkswagen India Pvt Ltd | D79: Pune | E79: stores | F79: Pranav shinde | G79: 7744051513 | H79: pranav.shinde1@skoda-vw.co.in | I79: 102008507 | J79: Contract | K79: No | L79: KXIND/W/YD/SPP/2519 | M79: 17/02/2025 | N79: 127200 | O79: February | P79: April | Q79: 0.5 | R79: 8000155292 | S79: 45768 | T79: 127200 | U79: April | V79: =Table62689345[[#This Row],[PO Value]]-Table62689345[[#This Row],[Offer Value]] -> 0 | W79: Offer including SW contract
A80: 74 | C80: Skoda Auto Volkswagen India Pvt Ltd | D80: Pune | E80: stores | F80: Pranav shinde | G80: 7744051513 | H80: pranav.shinde1@skoda-vw.co.in | I80: 102008508 | J80: Contract | K80: No | L80: KXIND/W/YD/SPP/2519 | M80: 17/02/2025 | N80: 127200 | O80: February | P80: April | Q80: 0.5 | R80: 8000155292 | S80: 45768 | T80: 127200 | U80: April | V80: =Table62689345[[#This Row],[PO Value]]-Table62689345[[#This Row],[Offer Value]] -> 0 | W80: Offer including SW contract
A81: 75 | C81: Skoda Auto Volkswagen India Pvt Ltd | D81: Pune | E81: stores | F81: Pranav shinde | G81: 7744051513 | H81: pranav.shinde1@skoda-vw.co.in | I81: 102008509 | J81: Contract | K81: No | L81: KXIND/W/YD/SPP/2519 | M81: 17/02/2025 | N81: 127200 | O81: February | P81: April | Q81: 0.5 | R81: 8000155292 | S81: 45768 | T81: 127200 | U81: April | V81: =Table62689345[[#This Row],[PO Value]]-Table62689345[[#This Row],[Offer Value]] -> 0 | W81: Offer including SW contract
A82: 76 | B82: 45715 | C82: Kaeser Compressor (I) Pvt Ltd | D82: Pune | E82: stores | F82: Pravin Ingale | G82: 9881071995 | H82: pravin.ingle@kaeser.com | I82: 22004776/001 | J82: Upgrade kit | K82: Yes | L82: KXIND/W/YD/SPP/25024 | M82: 45714 | N82: 0 | O82: February | P82: May | Q82: 0.2 | V82: =Table62689345[[#This Row],[PO Value]]-Table62689345[[#This Row],[Offer Value]] -> 0
A83: 77 | B83: 45715 | C83: Harman International (I) Pvt Ltd | D83: Pune | E83: stores | F83: Santosh Deshmukh | G83: 9552599231 | H83: santosh.deshmukh@harman.com | I83: 23002397/001 | J83: SPP | K83: Yes | L83: KXIND/W/SPP/YD/25021 | M83: 45712 | N83: 426306 | O83: February | P83: March | Q83: 0.8 | R83: 7700331210 | S83: 45717 | T83: 426306 | U83: March | V83: =Table62689345[[#This Row],[PO Value]]-Table62689345[[#This Row],[Offer Value]] -> 0 | Z83: Yes | AA83: Yes
A84: 78 | B84: 45715 | C84: Tetra Pak India Pvt Ltd | D84: Pune | E84: stors | F84: Mohan Kumar | H84: mg.mohan@tetrapak.com | I84: 13004913/001 | J84: SPP | K84: Yes | L84: KXIND/W/SPP/YD/25022 | M84: 45713 | N84: 85320 | O84: February | P84: May | Q84: 0.3 | R84: 927602141 | S84: 45729 | T84: 85320 | U84: May | V84: =Table62689345[[#This Row],[PO Value]]-Table62689345[[#This Row],[Offer Value]] -> 0
A85: 79 | B85: 45715 | C85: Kirloskar Oil Engine LTD | D85: Pune | E85: Stores | F85: Sayajirao Mali | G85: 9881734612 | H85: sayajirao.mali@kirloskar.com | I85: 16000438/001 | J85: SPP | K85: Yes | L85: KXIND/W/SPP/YD/25023 | M85: 45713 | N85: 25200 | O85: February | P85: March | Q85: 0.6 | R85: 7025041263 | S85: 45717 | T85: 25200 | U85: March | V85: =Table62689345[[#This Row],[PO Value]]-Table62689345[[#This Row],[Offer Value]] -> 0
A86: 80 | B86: 45726 | C86: J K Sales | D86: Pune | E86: stores | F86: Nilesh nazare | G86: 9860247575 | H86: nilesh.nazre@jksales.in | I86: 19009236/001 | J86: Contract | K86: No | L86: KXIND/W/YD/MC/25024 | M86: 45718 | N86: 83000 | O86: March | P86: April | Q86: 0.6 | R86: JK/PO/25-26/0041 | S86: 45761 | T86: 80001 | U86: April | V86: =Table62689345[[#This Row],[PO Value]]-Table62689345[[#This Row],[Offer Value]] -> -2999
A87: 81 | B87: 45740 | C87: Rieter India Pvt Ltd | D87: Pune | E87: stores | F87: Manoj Rasal | G87: 9822192492 | H87: manoj.rasal@rieter.com | I87: 21002906/001 | J87: Contract | K87: No | L87: KXIND/W/MC/YD/25025 | M87: 45718 | N87: 67000 | O87: March | P87: May | Q87: 0.3 | R87: 4504578229 | S87: 45779 | T87: 67000 | U87: May | V87: =Table62689345[[#This Row],[PO Value]]-Table62689345[[#This Row],[Offer Value]] -> 0
A88: 82 | B88: 45740 | C88: GIC Instruments Pvt Ltd | D88: Pune | E88: stores | F88: Ajinkya Desale | G88: 9403849891 | H88: ajinkya.dhekale@gicindia.com | I88: 08010151/001 | J88: SPP | K88: Yes | L88: KXIND/W/YD/SPP/25033 | M88: 45740 | N88: 509102 | O88: March | P88: May | Q88: 0.3 | R88: 26001228 | S88: 23.05.2025 | T88: 239244 | U88: May | V88: =Table62689345[[#This Row],[PO Value]]-Table62689345[[#This Row],[Offer Value]] -> -269858 | Z88: Yes | AA88: Yes
A89: 83 | B89: 45740 | C89: Jabil Circuit India private Limited | D89: Pune | E89: Stores | F89: Kelly Zhu | G89: +86 181-6832-9955 | H89: Kelly_Zhu33@Jabil.com | I89: 24005161/001 | J89: Retrofit kit | K89: Yes | L89: KXIND/W/YD/SPP/25031 | M89: 45736 | N89: 25643885 | O89: March | P89: April | Q89: 0.6 | R89: C-10003127958 | S89: 45775 | T89: 25643885 | U89: April | V89: =Table62689345[[#This Row],[PO Value]]-Table62689345[[#This Row],[Offer Value]] -> 0 | Z89: Yes | AA89: Yes
A90: 84 | B90: 45740 | C90: Mahindra Vehicals Mf LTD | D90: Pune | E90: P block stores | F90: KiranKapgate | G90: 9552571724 | H90: KAPGATE.KIRAN@mahindra.com | I90: 13000097/001 | J90: BD Spare | K90: No | L90: KXIND/W/SPP/YD25026 | M90: 45723 | N90: 22600 | O90: March | P90: March | Q90: 1 | R90: 66011802 | S90: 45734 | T90: 22600 | U90: March | V90: =Table62689345[[#This Row],[PO Value]]-Table62689345[[#This Row],[Offer Value]] -> 0
A91: 85 | B91: 45741 | C91: LMT Tools India Pvt Ltd | D91: Pune | E91: Stores | F91: Ramesh Thorat | G91: 9158883568 | H91: RKthorat@lmt-tools.com | I91: 99006602/001 | J91: Relocation | K91: No | L91: KRIND/W/RE/25027R | M91: 45726 | N91: 325000 | O91: March | P91: March | Q91: 1 | R91: 4521002912 | S91: 45733 | T91: 325000 | U91: March | V91: =Table62689345[[#This Row],[PO Value]]-Table62689345[[#This Row],[Offer Value]] -> 0
A92: 86 | B92: 45741 | C92: LMT Tools India Pvt Ltd | D92: Pune | E92: Stores | F92: Ramesh Thorat | G92: 9158883568 | H92: RKthorat@lmt-tools.com | I92: 99006602/001 | J92: Contract | K92: Yes | L92: KXIND/W/YD/MC/25027 | M92: 45723 | N92: 76000 | O92: March | P92: June | Q92: 0.5 | R92: 4521013686 | S92: 24.05.2025 | T92: 70000 | U92: June | V92: =Table62689345[[#This Row],[PO Value]]-Table62689345[[#This Row],[Offer Value]] -> -6000
A93: 87 | B93: 45799 | C93: GIC Instruments Pvt Ltd | D93: Pune | E93: stores | F93: Ajinkya Desale | G93: 9403849891 | H93: ajinkya.dhekale@gicindia.com | I93: 08010151/001 | J93: Contract | K93: No | L93: KXIND/W/YD/MC/25010 | M93: 45686 | N93: 78000 | O93: January | P93: May | Q93: 0.9 | R93: 2611160 | S93: 45797 | T93: 78000 | U93: May | V93: =Table62689345[[#This Row],[PO Value]]-Table62689345[[#This Row],[Offer Value]] -> 0
A94: 88 | C94: Kaeser Compressor (I) Pvt Ltd | D94: Pune | E94: stores | F94: Pravin Ingale | G94: 9881071995 | H94: pravin.ingle@kaeser.com | I94: 22004776/001 | J94: Contract | K94: Yes | L94: KXIND/W/YD/MC/25034R | M94: 45791 | N94: 85500 | O94: May | P94: May | Q94: 0.9 | R94: 4510868028 | S94: 45798 | T94: 85500 | U94: May | V94: =Table62689345[[#This Row],[PO Value]]-Table62689345[[#This Row],[Offer Value]] -> 0 | W94: PO for two years with software contract
A95: 89 | C95: Kaeser Compressor (I) Pvt Ltd | D95: Pune | E95: stores | F95: Pravin Ingale | G95: 9881071995 | H95: pravin.ingle@kaeser.com | I95: 22004776/002 | J95: Contract | K95: Yes | L95: KXIND/W/YD/MC/25034R | M95: 45791 | N95: 85500 | O95: May | P95: May | Q95: 0.9 | R95: 4510868028 | S95: 45798 | T95: 85500 | U95: May | V95: =Table62689345[[#This Row],[PO Value]]-Table62689345[[#This Row],[Offer Value]] -> 0 | W95: PO for two years with software contract
A96: 90 | C96: Kaeser Compressor (I) Pvt Ltd | D96: Pune | E96: stores | F96: Pravin Ingale | G96: 9881071995 | H96: pravin.ingle@kaeser.com | I96: 22004776/003 | J96: Contract | K96: Yes | L96: KXIND/W/YD/MC/25034R | M96: 45791 | N96: 85500 | O96: May | P96: May | Q96: 0.9 | R96: 4510868028 | S96: 45798 | T96: 85500 | U96: May | V96: =Table62689345[[#This Row],[PO Value]]-Table62689345[[#This Row],[Offer Value]] -> 0 | W96: PO for two years with software contract
A97: 91 | C97: Kaeser Compressor (I) Pvt Ltd | D97: Pune | E97: stores | F97: Pravin Ingale | G97: 9881071995 | H97: pravin.ingle@kaeser.com | I97: 22004776/004 | J97: Contract | K97: Yes | L97: KXIND/W/YD/MC/25034R | M97: 45791 | N97: 85500 | O97: May | P97: May | Q97: 0.9 | R97: 4510868028 | S97: 45798 | T97: 85500 | U97: May | V97: =Table62689345[[#This Row],[PO Value]]-Table62689345[[#This Row],[Offer Value]] -> 0 | W97: PO for two years with software contract
A98: 92 | B98: 45803 | C98: Sedmac Mechatronics Pvt.Ltd. | D98: Pune | E98: stores | F98: Vinay Shinde | G98: 9967967472 | H98: vinay.shinde@sedemac.com | I98: 18008976/001 | J98: SPP | K98: Yes | L98: KXIND/W/YD/SPP/25042 | M98: 45771 | N98: 256276 | O98: April | P98: May | Q98: 0.8 | R98: CP1/ IP2009681 | S98: 45799 | T98: 256276 | U98: May | V98: =Table62689345[[#This Row],[PO Value]]-Table62689345[[#This Row],[Offer Value]] -> 0
A99: 93 | B99: 45819 | C99: Bajaj Auto Ltd | D99: Pune | E99: veh.store | F99: Ganesh Navale | G99: 9503050525 | H99: ganesh.navale@bajaj.co.in | I99: 18001594/001 | J99: Contract | K99: No | L99: KXIND/W/YD/MC/25039 | M99: 45782 | N99: 60000 | O99: May | P99: June | Q99: 0.5 | R99: 3110015090 | S99: 45792 | T99: 60000 | U99: June | V99: =Table62689345[[#This Row],[PO Value]]-Table62689345[[#This Row],[Offer Value]] -> 0
A100: 94 | C100: Bajaj Auto Ltd | D100: Pune | E100: veh.store | F100: Ganesh Navale | G100: 9503050526 | H100: ganesh.navale@bajaj.co.in | I100: 00011128/002 | J100: Contract | K100: No | L100: KXIND/W/YD/MC/25039 | M100: 45782 | N100: 60000 | O100: May | P100: June | Q100: 0.5 | R100: 3110015090 | S100: 45792 | T100: 60000 | U100: June | V100: =Table62689345[[#This Row],[PO Value]]-Table62689345[[#This Row],[Offer Value]] -> 0
...

Sheet Ashraf
AB2: Month | AC2: Offers Total | AD2: Order received | AE2: Forecast | AF2: Forecast- Po Received
A3: KARDEX INDIA - LIVE OFFER FUNEL - ASHRAF - WEST | AB3: January | AC3: =SUMIF($O$8:$O$426,"January",$N$8:$N$426) -> 9757532 | AD3: =SUMIF($U$8:$U$426,"January",$T$8:$T$426) -> 2531948 | AE3: =SUMIF($P$8:$P$431,"January",$N$8:$N$431) -> 2967340 | AF3: =AE3-AD3 -> 435392
Q4: 0.01 | U4: Total Offered Value | V4: =SUM(N8:N426) -> 50584483 | AB4: February | AC4: =SUMIF($O$8:$O$426,"February",$N$8:$N$426) -> 4840185 | AD4: =SUMIF($U$8:$U$426,"February",$T$8:$T$426) -> 1652533 | AE4: =SUMIF($P$8:$P$431,"February",$N$8:$N$431) -> 1129500 | AF4: =AE4-AD4 -> -523033
A5: Total Offers | B5: =COUNTA(B8:B1466) -> 112 | U5: Order Received | V5: =SUM(T8:T426) -> 35560386 | AB5: March | AC5: =SUMIF($O$8:$O$426,"March",$N$8:$N$426) -> 2602772 | AD5: =SUMIF($U$8:$U$426,"March",$T$8:$T$426) -> 3651314 | AE5: =SUMIF($P$8:$P$431,"March",$N$8:$N$431) -> 4226358 | AF5: =AE5-AD5 -> 575044
U6: Open Funnel | V6: =SUM(V8:V426) -> 13539398 | Y6: * Updated by Girija | AB6: April | AC6: =SUMIF($O$8:$O$426,"April",$N$8:$N$426) -> 3583731 | AD6: =SUMIF($U$8:$U$426,"April",$T$8:$T$426) -> 1776550 | AE6: =SUMIF($P$8:$P$431,"April",$N$8:$N$431) -> 1926050 | AF6: =AE6-AD6 -> 149500
A7: SL | B7: Reg Date | C7: Company | D7: Location | E7: Department | F7: Contact Person Name | G7: Contact Number | H7: E-Mail ID | I7: Machine Serial Number | J7: Product Type | K7: Lead | L7: Offer Reference Number | M7: Offer Reference Date | N7: Offer Value | O7: Offer Month | P7: PO Expected Month | Q7: Probabality in Percentage | R7: PO Number | S7: PO Date | T7: PO Value | U7: PO Received Month | V7: Open Funnel | W7: Remarks | X7: Status | Y7: Booking Date in SAP B1 | Z7: Offer Entered in CRM | AA7: Offer Closed in CRM | AB7: May | AC7: =SUMIF($O$8:$O$426,"May",$N$8:$N$426) -> 5141304 | AD7: =SUMIF($U$8:$U$426,"May",$T$8:$T$426) -> 4694500 | AE7: =SUMIF($P$8:$P$431,"May",$N$8:$N$431) -> 5133652 | AF7: =AE7-AD7 -> 439152
A8: 1 | B8: 45666 | C8: Cummins Technologis India Pvt Ltd | D8: phaltan | E8: PCP1 | F8: Sagar Jagatap | G8: 9373155620 | H8: sagar.jagatap@cummins.com | I8: 18007324/001 | J8: Upgrade kit | K8: Yes | L8: KRIND/W/SPP/AB/24005 | M8: 45341 | N8: 1246800 | O8: January | P8: August | Q8: 1 | R8: IND8202828 | S8: 45751 | T8: 1029360 | U8: August | V8: 0 | Z8: Yes | AB8: June | AC8: =SUMIF($O$8:$O$426,"June",$N$8:$N$426) -> 5050287 | AD8: =SUMIF($U$8:$U$426,"June",$T$8:$T$426) -> 6037535 | AE8: =SUMIF($P$8:$P$431,"June",$N$8:$N$431) -> 6433266 | AF8: =AE8-AD8 -> 395731
A9: 2 | B9: 45666 | C9: Hiteco TMS India Pvt Ltd | D9: Pune | E9: Stores tool | F9: Wasim Sheikh | G9: 9881275059 | H9: XPNCN24@hmil.net | I9: 09008827/001 | J9: SPP | K9: Yes | L9: KRIND/W/SPP/AB24018 | M9: 45412 | N9: 604356 | O9: January | P9: August | Q9: 1 | V9: 0 | Z9: Yes | AB9: July | AC9: =SUMIF($O$8:$O$426,"July",$N$8:$N$426) -> 3175477 | AD9: =SUMIF($U$8:$U$426,"July",$T$8:$T$426) -> 3214688 | AE9: =SUMIF($P$8:$P$431,"July",$N$8:$N$431) -> 2640380 | AF9: =AE9-AD9 -> -574308
A10: 3 | B10: 45666 | C10: Bharat Electronics Ltd | D10: Pune | E10: Stores | F10: Vilas Khade | G10: 2022903115 | H10: vilaskhade@bel.co.in | I10: 04002775/002 | J10: SPP | K10: Yes | L10: KRIND/W/SPP/AB240026 | M10: 45329 | N10: 1197980 | O10: January | P10: July | Q10: 1 | R10: 4000513646 | S10: 45832 | T10: 1406141 | U10: June | V10: 0 | Z10: yes | AB10: August | AC10: =SUMIF($O$8:$O$426,"August",$N$8:$N$426) -> 5170000 | AD10: =SUMIF($U$8:$U$426,"August",$T$8:$T$426) -> 2953103 | AE10: =SUMIF($P$8:$P$431,"August",$N$8:$N$431) -> 4745016 | AF10: =AE10-AD10 -> 1791913
A11: 4 | B11: 45666 | C11: Sulzer Pumps India Pvt Ltd | D11: Mumbai | E11: store | F11: Anant Tarniker | G11: 9833345459 | H11: anant.ternikar@sulzer.com | I11: 102006834 | J11: SPP | K11: Yes | L11: KRIND/W/SPP/AB24032 | M11: 45516 | N11: 643950 | O11: January | P11: December | Q11: 0.4 | V11: =Table626893456[[#This Row],[Offer Value]]-Table626893456[[#This Row],[PO Value]] -> 643950 | X11: discussion happened | Z11: Yes | AB11: September | AC11: =SUMIF($O$8:$O$426,"September",$N$8:$N$426) -> 4142775 | AD11: =SUMIF($U$8:$U$426,"September",$T$8:$T$426) -> 1750522 | AE11: =SUMIF($P$8:$P$431,"September",$N$8:$N$431) -> 1273000 | AF11: =AE11-AD11 -> -477522
A12: 5 | B12: 45666 | C12: Seco Tools India PVT LTD | D12: Pune | E12: Document Store | F12: Prasanna Godbole | G12: 7774083585 | H12: prasanna.godbole@secotools.com | I12: 16008208/001 | J12: Contract | K12: No | L12: KXIND/W/MC/AB24030 | M12: 45511 | N12: 62000 | O12: January | P12: February | Q12: 1 | R12: 10082197 | S12: 45636 | T12: 55000 | U12: January | V12: =Table626893456[[#This Row],[Offer Value]]-Table626893456[[#This Row],[PO Value]] -> 7000 | AB12: October | AC12: =SUMIF($O$8:$O$426,"October",$N$8:$N$426) -> 4747151 | AD12: =SUMIF($U$8:$U$426,"October",$T$8:$T$426) -> 2616357 | AE12: =SUMIF($P$8:$P$431,"October",$N$8:$N$431) -> 2694185 | AF12: =AE12-AD12 -> 77828
A13: 5 | C13: Seco Tools India PVT LTD | D13: Pune | E13: DTA | F13: Prasanna Godbole | G13: 7774083585 | H13: prasanna.godbole@secotools.com | I13: 16007507/001 | J13: Contract | K13: No | L13: KXIND/W/MC/AB24030 | M13: 45511 | N13: 62000 | O13: January | P13: February | Q13: 1 | R13: 10082196 | S13: 45636 | T13: 55000 | U13: January | V13: =Table626893456[[#This Row],[Offer Value]]-Table626893456[[#This Row],[PO Value]] -> 7000 | AB13: November | AC13: =SUMIF($O$8:$O$426,"November",$N$8:$N$426) -> 1326760 | AD13: =SUMIF($U$8:$U$426,"November",$T$8:$T$426) -> 3568228 | AE13: =SUMIF($P$8:$P$431,"November",$N$8:$N$431) -> 8781521 | AF13: =AE13-AD13 -> 5213293
A14: 5 | C14: Seco Tools India PVT LTD | D14: Pune | E14: Tool Room | F14: Prasanna Godbole | G14: 7774083585 | H14: prasanna.godbole@secotools.com | I14: 11010676/001 | J14: Contract | K14: No | L14: KXIND/W/MC/AB24030 | M14: 45511 | N14: 62000 | O14: January | P14: February | Q14: 1 | R14: 10082196 | S14: 45636 | T14: 55000 | U14: January | V14: =Table626893456[[#This Row],[Offer Value]]-Table626893456[[#This Row],[PO Value]] -> 7000 | AB14: December | AC14: =SUMIF($O$8:$O$426,"December",$N$8:$N$426) -> 1046509 | AD14: =SUMIF($U$8:$U$426,"December",$T$8:$T$426) -> 573108 | AE14: =SUMIF($P$8:$P$431,"December",$N$8:$N$431) -> 8634215 | AF14: =AE14-AD14 -> 8061107
A15: 6 | B15: 45666 | C15: Sandvik Coromant India Pvt Ltd | D15: Pune | E15: Soft Tools | F15: Vivek Khodade | G15: 9823332725 | H15: vivek.khodade@sandvik.com | I15: 21003645/001 | J15: Relocation | K15: NO | L15: KRIND/W/RF/AB24048 | M15: 45610 | N15: 560000 | O15: January | P15: June | Q15: 1 | R15: 4512705805 | S15: 45814 | T15: 520000 | U15: June | V15: 0
A16: 7 | B16: 45666 | C16: Seco Tools India PVT LTD | D16: Pune | E16: IGS | F16: Arun kadam | G16: 9552579436 | H16: Arun.Kadam@secotools.com | I16: 13005433/001 | J16: Contract | K16: No | L16: KXIND/W/MC/AB24036 | M16: 45609 | N16: 62000 | O16: January | P16: May | Q16: 1 | R16: 10083149 | S16: 45650 | T16: 55000 | U16: January
A17: 7 | C17: Seco Tools India PVT LTD | D17: Pune | E17: Press shop | F17: Arun kadam | G17: 9552579436 | H17: Arun.Kadam@secotools.com | I17: 11010646/001 | J17: Contract | K17: No | L17: KXIND/W/MC/AB24036 | M17: 45609 | N17: 62000 | O17: January | P17: January | Q17: 1 | R17: 10083157 | S17: 45650 | T17: 55000 | U17: January | V17: 0
A18: 7 | C18: Seco Tools India PVT LTD | D18: Pune | E18: Sinter | F18: Arun kadam | G18: 9552579436 | H18: Arun.Kadam@secotools.com | I18: 13001978/001 | J18: Contract | K18: No | L18: KXIND/W/MC/AB24036 | M18: 45609 | N18: 62000 | O18: January | P18: January | Q18: 1 | R18: 10083150 | S18: 45650 | T18: 55000 | U18: January | V18: 0
A19: 8 | B19: 45666 | C19: Bharat Forge LTD | D19: Pune | E19: Aerospace | F19: Kiran Patil | G19: 9881340014 | H19: Kiran.Patil@bharatforge.com | I19: 17007143/001 | J19: Contract | K19: No | L19: KXIND/W/MC/AB/24038 | M19: 45610 | N19: 85000 | O19: January | P19: May | Q19: 1 | R19: 4601450532 | S19: 45796 | T19: 75000 | U19: May | V19: 0
A20: 9 | B20: 45666 | C20: Cummins India Ltd | D20: Pune | E20: KV & NHNT | F20: Vishal B Kalshetti | G20: 8888869627 | H20: Vishal.Kalshetti@cummins.com | I20: 07002616/001 | J20: Contract | K20: No | L20: KRIND/W/MC/AB/240039 | M20: 45610 | N20: 80000 | O20: January | P20: January | Q20: 1 | R20: IND7985383 | S20: 45663 | T20: 80000 | U20: January | V20: =Table626893456[[#This Row],[Offer Value]]-Table626893456[[#This Row],[PO Value]] -> 0 | W20: Please share the PO copy
A21: 9 | C21: Cummins India Ltd | D21: Pune | E21: KV & NHNT | F21: Vishal B Kalshetti | G21: 8888869627 | H21: Vishal.Kalshetti@cummins.com | I21: 00009908/002 | J21: Contract | K21: No | L21: KRIND/W/MC/AB/240039 | M21: 45610 | N21: 80000 | O21: January | P21: January | Q21: 1 | R21: IND7985383 | S21: 45663 | T21: 80000 | U21: January | V21: =Table626893456[[#This Row],[Offer Value]]-Table626893456[[#This Row],[PO Value]] -> 0
A22: 9 | C22: Cummins India Ltd | D22: Pune | E22: KV & NHNT | F22: Vishal B Kalshetti | G22: 8888869627 | H22: Vishal.Kalshetti@cummins.com | I22: 00009908/003 | J22: Contract | K22: No | L22: KRIND/W/MC/AB/240039 | M22: 45610 | N22: 80000 | O22: January | P22: January | Q22: 1 | R22: IND7985383 | S22: 45663 | T22: 80000 | U22: January | V22: =Table626893456[[#This Row],[Offer Value]]-Table626893456[[#This Row],[PO Value]] -> 0
A23: 9 | C23: Cummins India Ltd | D23: Pune | E23: KV & NHNT | F23: Vishal B Kalshetti | G23: 8888869627 | H23: Vishal.Kalshetti@cummins.com | I23: 00009908/004 | J23: Contract | K23: No | L23: KRIND/W/MC/AB/240039 | M23: 45610 | N23: 80000 | O23: January | P23: January | Q23: 1 | R23: IND7985383 | S23: 45663 | T23: 80000 | U23: January | V23: =Table626893456[[#This Row],[Offer Value]]-Table626893456[[#This Row],[PO Value]] -> 0
A24: 9 | C24: Cummins India Ltd | D24: Pune | E24: KV & NHNT | F24: Vishal B Kalshetti | G24: 8888869627 | H24: Vishal.Kalshetti@cummins.com | I24: 00009908/005 | J24: Contract | K24: No | L24: KRIND/W/MC/AB/240039 | M24: 45610 | N24: 80000 | O24: January | P24: January | Q24: 1 | R24: IND7985383 | S24: 45663 | T24: 80000 | U24: January | V24: =Table626893456[[#This Row],[Offer Value]]-Table626893456[[#This Row],[PO Value]] -> 0
A25: 9 | C25: Cummins India Ltd | D25: Pune | E25: KV & NHNT | F25: Vishal B Kalshetti | G25: 8888869627 | H25: Vishal.Kalshetti@cummins.com | I25: 01000708/001 | J25: Contract | K25: No | L25: KRIND/W/MC/AB/240039 | M25: 45610 | N25: 80000 | O25: January | P25: January | Q25: 1 | R25: IND7985383 | S25: 45663 | T25: 80000 | U25: January | V25: =Table626893456[[#This Row],[Offer Value]]-Table626893456[[#This Row],[PO Value]] -> 0
A26: 9 | C26: Cummins India Ltd | D26: Pune | E26: KV & NHNT | F26: Vishal B Kalshetti | G26: 8888869627 | H26: Vishal.Kalshetti@cummins.com | I26: 00009908/001 | J26: Contract | K26: No | L26: KRIND/W/MC/AB/240039 | M26: 45610 | N26: 80000 | O26: January | P26: January | Q26: 1 | R26: IND7985383 | S26: 45663 | T26: 80000 | U26: January | V26: =Table626893456[[#This Row],[Offer Value]]-Table626893456[[#This Row],[PO Value]] -> 0
A27: 10 | B27: 45666 | C27: Alfa Laval India LTD | D27: Pune | E27: Decanter | F27: Sagar Pawar | G27: 7798824040 | H27: Sagar.Pawar@alfalaval.com | I27: 05004742/001 | J27: Contract | K27: No | L27: KXIND/W/MC/AB24040 | M27: 45610 | N27: 77500 | O27: January | P27: February | Q27: 1 | R27: 8172731 | S27: 45700 | T27: 77500 | U27: February | V27: =Table626893456[[#This Row],[Offer Value]]-Table626893456[[#This Row],[PO Value]] -> 0
A28: 10 | C28: Alfa Laval India LTD | D28: Pune | E28: Decanter | F28: Sagar Pawar | G28: 7798824040 | H28: Sagar.Pawar@alfalaval.com | I28: 07005169/001 | J28: Contract | K28: No | L28: KXIND/W/MC/AB24040 | M28: 45610 | N28: 77500 | O28: January | P28: February | Q28: 1 | R28: 8172731 | S28: 45700 | T28: 77500 | U28: February | V28: =Table626893456[[#This Row],[Offer Value]]-Table626893456[[#This Row],[PO Value]] -> 0
A29: 10 | C29: Alfa Laval India LTD | D29: Pune | E29: Decanter | F29: Sagar Pawar | G29: 7798824040 | H29: Sagar.Pawar@alfalaval.com | I29: 07005164/001 | J29: Contract | K29: No | L29: KXIND/W/MC/AB24040 | M29: 45610 | N29: 77500 | O29: January | P29: February | Q29: 1 | R29: 8172731 | S29: 45700 | T29: 77500 | U29: February | V29: =Table626893456[[#This Row],[Offer Value]]-Table626893456[[#This Row],[PO Value]] -> 0
A30: 10 | C30: Alfa Laval India LTD | D30: Pune | E30: Decanter | F30: Sagar Pawar | G30: 7798824040 | H30: Sagar.Pawar@alfalaval.com | I30: 10010116/001 | J30: Contract | K30: No | L30: KXIND/W/MC/AB24040 | M30: 45610 | N30: 77500 | O30: January | P30: February | Q30: 1 | R30: 8172731 | S30: 45700 | T30: 77500 | U30: February | V30: =Table626893456[[#This Row],[Offer Value]]-Table626893456[[#This Row],[PO Value]] -> 0
A31: 11 | B31: 45666 | C31: Alfa Laval India LTD | D31: Pune | E31: DLC | F31: Ranjit Shinde | G31: 7045525011 | H31: ranjit.shinde@alfalaval.com | I31: 07010871/001 | J31: Contract | K31: No | L31: KXIND/W/MC/AB24041 | M31: 45610 | N31: 77500 | O31: January | P31: February | Q31: 1 | R31: 8172511 | S31: 45693 | T31: 77500 | U31: February | V31: =Table626893456[[#This Row],[Offer Value]]-Table626893456[[#This Row],[PO Value]] -> 0
A32: 11 | C32: Alfa Laval India LTD | D32: Pune | E32: DLC | F32: Ranjit Shinde | G32: 7045525011 | H32: ranjit.shinde@alfalaval.com | I32: 19008264/001 | J32: Contract | K32: No | L32: KXIND/W/MC/AB24041 | M32: 45610 | N32: 77500 | O32: January | P32: February | Q32: 1 | R32: 8172511 | S32: 45693 | T32: 77500 | U32: February | V32: =Table626893456[[#This Row],[Offer Value]]-Table626893456[[#This Row],[PO Value]] -> 0
A33: 11 | C33: Alfa Laval India LTD | D33: Pune | E33: DLC | F33: Ranjit Shinde | G33: 7045525011 | H33: ranjit.shinde@alfalaval.com | I33: 22008500/001 | J33: Contract | K33: yes | L33: KXIND/W/MC/AB24041 | M33: 45610 | N33: 77500 | O33: January | P33: February | Q33: 1 | R33: 8172511 | S33: 45693 | T33: 77500 | U33: February | V33: =Table626893456[[#This Row],[Offer Value]]-Table626893456[[#This Row],[PO Value]] -> 0
A34: 12 | B34: 45666 | C34: Alfa Laval India LTD | D34: Pune | E34: Stores | F34: Jitu Shirke | G34: 9623003468 | H34: jitendra.shirke@alfalaval.com | I34: 07008042/001 | J34: Contract | K34: No | L34: KXIND/W/MC/AB24042 | M34: 45618 | N34: 77500 | O34: January | P34: January | Q34: 1 | R34: 8171479 | S34: 45663 | T34: 77500 | U34: January | V34: =Table626893456[[#This Row],[Offer Value]]-Table626893456[[#This Row],[PO Value]] -> 0
A35: 12 | C35: Alfa Laval India LTD | D35: Pune | E35: Stores | F35: Jitu Shirke | G35: 9623003468 | H35: jitendra.shirke@alfalaval.com | I35: 1100003/001 | J35: Contract | K35: No | L35: KXIND/W/MC/AB24042 | M35: 45618 | N35: 77500 | O35: January | P35: January | Q35: 1 | R35: 8171479 | S35: 45663 | T35: 77500 | U35: January | V35: =Table626893456[[#This Row],[Offer Value]]-Table626893456[[#This Row],[PO Value]] -> 0
A36: 12 | C36: Alfa Laval India LTD | D36: Pune | E36: Stores | F36: Jitu Shirke | G36: 9623003468 | H36: jitendra.shirke@alfalaval.com | I36: 22006265/001 | J36: Contract | K36: YES | L36: KXIND/W/MC/AB24042 | M36: 45618 | N36: 77500 | O36: January | P36: January | Q36: 1 | R36: 8171479 | S36: 45663 | T36: 77500 | U36: January | V36: =Table626893456[[#This Row],[Offer Value]]-Table626893456[[#This Row],[PO Value]] -> 0
A37: 13 | B37: 45666 | C37: Bharat Forge LTD | D37: Pune | E37: Aerospace | F37: Kiran Patil | G37: 9881340014 | H37: Kiran.Patil@bharatforge.com | I37: 17007143/001 | J37: Relocation | K37: No | L37: KAR/IND/RE/AB/007 | M37: 45580 | N37: 350000 | O37: January | P37: December | Q37: 0.5 | V37: =Table626893456[[#This Row],[Offer Value]]-Table626893456[[#This Row],[PO Value]] -> 350000
A38: 14 | B38: 45666 | C38: Siemens Ltd. | D38: Pune | E38: Switchboard | F38: Amar Gurav | G38: 8879112999 | H38: amar.gurav@siemens.com | I38: 09002885/001 | J38: Relocation | K38: No | L38: KAR/IND/RE/AB/008 | M38: 45614 | N38: 395000 | O38: January | P38: January | Q38: 1 | R38: 4513271995 | S38: 45664 | T38: 390000 | U38: January | V38: =Table626893456[[#This Row],[Offer Value]]-Table626893456[[#This Row],[PO Value]] -> 5000 | Y38: 45901
A39: 15 | B39: 45666 | C39: Seco Tools India PVT LTD | D39: Pune | E39: Final Ins | F39: Arun kadam | G39: 9552579436 | H39: Arun.Kadam@secotools.com | I39: 22005009/001 | J39: Contract | K39: Yes | L39: KXIND/W/MC/AB24046 | M39: 45645 | N39: 55000 | O39: January | P39: January | Q39: 1 | R39: 10083147 | S39: 24/12/2025 | T39: 55000 | U39: January | V39: =Table626893456[[#This Row],[Offer Value]]-Table626893456[[#This Row],[PO Value]] -> 0
A40: 16 | B40: 45666 | C40: Sandvik Coromant India Pvt Ltd | D40: pune | E40: Lapping | F40: Mahesh Ambawale | G40: 9881379339 | H40: mahesh.ambawale@sandvik.com | I40: 17008268/001 | J40: SPP | K40: Yes | L40: KRIND/W/SPP/AB24049 | M40: 45654 | N40: 156091 | O40: January | P40: January | Q40: 1 | R40: 4512110539 | S40: 20/01/2025 | T40: 151408 | U40: January | V40: =Table626893456[[#This Row],[Offer Value]]-Table626893456[[#This Row],[PO Value]] -> 4683 | Y40: 29/1/2025
A41: 17 | B41: 45666 | C41: Wirtgen India Pvt.Ltd. | D41: Pune | E41: Stores | F41: Sagar Brijpuriya | G41: 8956509715 | H41: sagar.brijpuriya@wirtgen-group.com | I41: 16004741/001 | J41: Contract | K41: NO | L41: KXIND/W/MC/AB/25001 | M41: 45663 | N41: 67000 | O41: January | P41: January | Q41: 1 | R41: 4504516357 | S41: 45712 | T41: 65000 | U41: February | V41: 0
A42: 17 | C42: Wirtgen India Pvt.Ltd. | D42: Pune | E42: Stores | F42: Sagar Brijpuriya | G42: 8956509715 | H42: sagar.brijpuriya@wirtgen-group.com | I42: 16004741/002 | J42: Contract | K42: NO | L42: KXIND/W/MC/AB/25001 | M42: 45663 | N42: 67000 | O42: January | P42: February | Q42: 1 | R42: 4504516357 | S42: 45712 | T42: 65000 | U42: February | V42: 0
A43: 18 | B43: 45666 | C43: Firmenich Aerometics I Pvt.ltd. | D43: Mumbai | E43: Flavours | F43: Utkarsh Kumar | G43: 9004412241 | H43: utkarsh.kumar@dsm-firmenich.com | I43: 18007781/001 | J43: Contract | K43: NO | L43: KXIND/W/MC/AB/25002 | M43: 45663 | N43: 58000 | O43: January | P43: February | Q43: 1 | R43: 3001029670 | S43: 45714 | T43: 58000 | U43: February | V43: =Table626893456[[#This Row],[Offer Value]]-Table626893456[[#This Row],[PO Value]] -> 0
A44: 18 | C44: Firmenich Aerometics I Pvt.ltd. | D44: Mumbai | E44: Flavours | F44: Utkarsh Kumar | G44: 9004412241 | H44: utkarsh.kumar@dsm-firmenich.com | I44: 18007778/001 | J44: Contract | K44: NO | L44: KXIND/W/MC/AB/25002 | M44: 45663 | N44: 58000 | O44: January | P44: February | Q44: 1 | R44: 3001029670 | S44: 45714 | T44: 58000 | U44: February | V44: =Table626893456[[#This Row],[Offer Value]]-Table626893456[[#This Row],[PO Value]] -> 0
A45: 18 | C45: Firmenich Aerometics I Pvt.ltd. | D45: Mumbai | E45: Flavours | F45: Utkarsh Kumar | G45: 9004412241 | H45: utkarsh.kumar@dsm-firmenich.com | I45: 18007778/002 | J45: Contract | K45: NO | L45: KXIND/W/MC/AB/25002 | M45: 45663 | N45: 58000 | O45: January | P45: February | Q45: 1 | R45: 3001029670 | S45: 45714 | T45: 58000 | U45: February | V45: =Table626893456[[#This Row],[Offer Value]]-Table626893456[[#This Row],[PO Value]] -> 0
A46: 19 | B46: 45666 | C46: Bajaj Auto Ltd | D46: Pune | E46: Stores | F46: N R PAtil | G46: 9890500449 | H46: nrpatil@bajajauto.co.in | I46: 04005026/001 | J46: Contract | K46: No | L46: Old PO Ref | M46: 45666 | N46: 45000 | O46: January | P46: January | Q46: 1 | R46: 7710025677 | S46: 45664 | T46: 45000 | U46: January | V46: =Table626893456[[#This Row],[Offer Value]]-Table626893456[[#This Row],[PO Value]] -> 0 | Y46: 31/1/2025
A47: 19 | C47: Bajaj Auto Ltd | D47: Pune | E47: Stores | F47: N R PAtil | G47: 9890500449 | H47: nrpatil@bajajauto.co.in | I47: 04005026/002 | J47: Contract | K47: No | L47: Old PO Ref | M47: 45666 | N47: 45000 | O47: January | P47: January | Q47: 1 | R47: 7710025677 | S47: 45664 | T47: 45000 | U47: January | V47: =Table626893456[[#This Row],[Offer Value]]-Table626893456[[#This Row],[PO Value]] -> 0 | Y47: 31/1/2025
A48: 19 | C48: Bajaj Auto Ltd | D48: Pune | E48: Stores | F48: N R PAtil | G48: 9890500449 | H48: nrpatil@bajajauto.co.in | I48: 04005017/001 | J48: Contract | K48: No | L48: Old PO Ref | M48: 45666 | N48: 45000 | O48: January | P48: January | Q48: 1 | R48: 7710025677 | S48: 45664 | T48: 45000 | U48: January | V48: =Table626893456[[#This Row],[Offer Value]]-Table626893456[[#This Row],[PO Value]] -> 0 | Y48: 31/1/2025
A49: 19 | C49: Bajaj Auto Ltd | D49: Pune | E49: Stores | F49: N R PAtil | G49: 9890500449 | H49: nrpatil@bajajauto.co.in | I49: 04005017/002 | J49: Contract | K49: No | L49: Old PO Ref | M49: 45666 | N49: 45000 | O49: January | P49: January | Q49: 1 | R49: 7710025677 | S49: 45664 | T49: 45000 | U49: January | V49: =Table626893456[[#This Row],[Offer Value]]-Table626893456[[#This Row],[PO Value]] -> 0 | Y49: 31/1/2025
A50: 19 | C50: Bajaj Auto Ltd | D50: Pune | E50: Stores | F50: N R PAtil | G50: 9890500449 | H50: nrpatil@bajajauto.co.in | I50: 05007141/001 | J50: Contract | K50: No | L50: Old PO Ref | M50: 45666 | N50: 45000 | O50: January | P50: January | Q50: 1 | R50: 7710025677 | S50: 45664 | T50: 45000 | U50: January | V50: =Table626893456[[#This Row],[Offer Value]]-Table626893456[[#This Row],[PO Value]] -> 0 | Y50: 31/1/2025
A51: 19 | C51: Bajaj Auto Ltd | D51: Pune | E51: Stores | F51: N R PAtil | G51: 9890500449 | H51: nrpatil@bajajauto.co.in | I51: 12002374/001 | J51: Contract | K51: No | L51: Old PO Ref | M51: 45666 | N51: 45000 | O51: January | P51: January | Q51: 1 | R51: 7710025677 | S51: 45664 | T51: 45000 | U51: January | V51: =Table626893456[[#This Row],[Offer Value]]-Table626893456[[#This Row],[PO Value]] -> 0 | Y51: 31/1/2025
A52: 19 | C52: Bajaj Auto Ltd | D52: Pune | E52: Stores | F52: N R PAtil | G52: 9890500449 | H52: nrpatil@bajajauto.co.in | I52: 05007142/001 | J52: Contract | K52: No | L52: Old PO Ref | M52: 45666 | N52: 45000 | O52: January | P52: January | Q52: 1 | R52: 7710025677 | S52: 45664 | T52: 45000 | U52: January | V52: =Table626893456[[#This Row],[Offer Value]]-Table626893456[[#This Row],[PO Value]] -> 0 | Y52: 31/1/2025
A53: 19 | C53: Bajaj Auto Ltd | D53: Pune | E53: Stores | F53: N R PAtil | G53: 9890500449 | H53: nrpatil@bajajauto.co.in | I53: 12002320/001 | J53: Contract | K53: No | L53: Old PO Ref | M53: 45666 | N53: 45000 | O53: January | P53: January | Q53: 1 | R53: 7710025677 | S53: 45664 | T53: 45000 | U53: January | V53: =Table626893456[[#This Row],[Offer Value]]-Table626893456[[#This Row],[PO Value]] -> 0 | Y53: 31/1/2025
A54: 19 | C54: Bajaj Auto Ltd | D54: Pune | E54: Stores | F54: N R PAtil | G54: 9890500449 | H54: nrpatil@bajajauto.co.in | I54: 12002279/001 | J54: Contract | K54: No | L54: Old PO Ref | M54: 45666 | N54: 45000 | O54: January | P54: January | Q54: 1 | R54: 7710025677 | S54: 45664 | T54: 45000 | U54: January | V54: =Table626893456[[#This Row],[Offer Value]]-Table626893456[[#This Row],[PO Value]] -> 0 | Y54: 31/1/2025
A55: 19 | C55: Bajaj Auto Ltd | D55: Pune | E55: Stores | F55: N R PAtil | G55: 9890500449 | H55: nrpatil@bajajauto.co.in | I55: 12002280/001 | J55: Contract | K55: No | L55: Old PO Ref | M55: 45666 | N55: 45000 | O55: January | P55: January | Q55: 1 | R55: 7710025677 | S55: 45664 | T55: 45000 | U55: January | V55: =Table626893456[[#This Row],[Offer Value]]-Table626893456[[#This Row],[PO Value]] -> 0 | Y55: 31/1/2025
A56: 20 | B56: 45666 | C56: Bharat Bijlee Ltd | D56: Mumbai | E56: stores | F56: sachin Lad | G56: 9833236099 | H56: Sachin.Lad@bharatbijlee.com | I56: 11001977/001 | J56: SPP | K56: Yes | L56: KRIND/W/SPP/AB240027 | M56: 45444 | N56: 295000 | O56: January | P56: January | Q56: 1 | R56: 3000004978 & 5000015774 | S56: 45668 | T56: 292000 | U56: January | V56: =Table626893456[[#This Row],[Offer Value]]-Table626893456[[#This Row],[PO Value]] -> 3000
A57: 21 | B57: 45666 | C57: Cummins Technologis India Pvt Ltd | D57: Pune | E57: PCP1 | F57: Bapu Shinde | G57: 9922560304 | H57: bapu.b.shinde@cummins.com | I57: 16005685/001 | J57: Contract | K57: NO | L57: KRIND/W/MC/AB24049 | M57: 45656 | N57: 80000 | O57: January | P57: February | Q57: 1 | R57: IND8022852 | S57: 45696 | T57: 80000 | U57: February | V57: =Table626893456[[#This Row],[Offer Value]]-Table626893456[[#This Row],[PO Value]] -> 0
A58: 21 | C58: Cummins Technologis India Pvt Ltd | D58: Pune | E58: PCP1 | F58: Bapu Shinde | G58: 9922560304 | H58: bapu.b.shinde@cummins.com | I58: 19002965/001 | J58: Contract | K58: YES | L58: KRIND/W/MC/AB24049 | M58: 45656 | N58: 80000 | O58: January | P58: February | Q58: 1 | R58: IND8022852 | S58: 45696 | T58: 80000 | U58: February | V58: =Table626893456[[#This Row],[Offer Value]]-Table626893456[[#This Row],[PO Value]] -> 0
A59: 21 | C59: Cummins Technologis India Pvt Ltd | D59: Pune | E59: PCP1 | F59: Bapu Shinde | G59: 9922560304 | H59: bapu.b.shinde@cummins.com | I59: 18007324/001 | J59: Contract | K59: NO | L59: KRIND/W/MC/AB24049 | M59: 45656 | N59: 0 | O59: January | Q59: 0 | V59: 0
A60: 22 | B60: 45666 | C60: Seco Tools India PVT LTD | D60: Pune | E60: IGS | F60: Rohida Adawale | H60: Rohidas.Adawale@secotools.com | I60: 11010645/001 | J60: SPP | K60: YES | L60: KRIND/W/SPP/AB24031 | M60: 45504 | N60: 71040 | O60: January | P60: January | Q60: 1 | R60: 6620501 | S60: 45661 | T60: 71040 | U60: January | V60: =Table626893456[[#This Row],[Offer Value]]-Table626893456[[#This Row],[PO Value]] -> 0 | Y60: 17/1/2025
A61: 23 | B61: 45666 | C61: GE India Industrial Pvt.Ltd. | D61: Pune | E61: Tool Room | F61: Pravin Gaikwad | G61: 9689348228 | H61: pravin.gaikwad@ge.com | I61: 16004510/001 | J61: SPP | K61: Yes | L61: KRIND/W/SPP/AB/25001 | M61: 45666 | N61: 446525 | O61: January | P61: June | Q61: 1 | R61: 2008042 | S61: 45804 | T61: 1151200 | U61: June | V61: 0 | X61: final discount has been extended. | Z61: Yes
A62: 24 | B62: 45668 | C62: KSB Pumps LTD | D62: Chinchwad | E62: Stores | F62: Navnath Tarade | H62: Navnath.Tarade@ksb.com | I62: 01004097/001 | J62: Midlife Upgrade | K62: Yes | L62: KRIND/W/SPP/AB/25002 | M62: 45668 | N62: 188390 | O62: January | P62: December | Q62: 0.5 | V62: =Table626893456[[#This Row],[Offer Value]]-Table626893456[[#This Row],[PO Value]] -> 188390 | X62: budgeted in april
A63: 25 | B63: 45667 | C63: KSB Pumps LTD | D63: Pimpri | E63: Stores | F63: Sarang Budale | G63: 9763858155 | H63: Sarang.Budale@ksb.com | I63: 14005057/001 | J63: SPP | K63: Yes | L63: KRIND/W/SPP/AB/25003 | M63: 45667 | N63: 837400 | O63: January | P63: July | Q63: 1 | R63: 4507602012 | S63: 10.7.2025 | T63: 664608 | U63: July | V63: 0 | Z63: Yes | AA63: yes
A64: 26 | B64: 45840 | C64: KSB Pumps LTD | D64: shirwal | E64: Stores | F64: Sachine Pawar | G64: 9822412607 | H64: sachin.pawar@ksb.com | I64: 02002336/002 | J64: SPP | K64: YES | L64: KRIND/W/SPP/AB/25005 | M64: 45840 | N64: 916358 | O64: February | P64: June | Q64: 1 | R64: 4507707924 | S64: 24/09/2025 | T64: 335717 | U64: September | V64: 0 | Z64: yes | AA64: yes
A65: 27 | B65: 45840 | C65: Seco Tools India PVT LTD | D65: Pune | E65: Stores tool | F65: Amol Patil | H65: amol.s.patil@secotools.com | I65: 13001978/001 | J65: SPP | K65: Yes | L65: KRIND/W/SPP/AB25006 | M65: 45840 | N65: 351591 | O65: February | P65: December | Q65: 0.5 | V65: =Table626893456[[#This Row],[Offer Value]]-Table626893456[[#This Row],[PO Value]] -> 351591
A66: 28 | B66: 45871 | C66: Sandvik Coromant India Pvt Ltd | D66: pune | E66: Round Tools | F66: Sunny Rangire | G66: 9860084034 | H66: sunny.rangire@sandvik.com | I66: 18005569/001 | J66: SPP | K66: Yes | L66: KRIND/W/SPP/AB25007 | M66: 45696 | N66: 666014 | O66: February | P66: March | Q66: 1 | R66: 4512239733 | S66: 45707 | T66: 646033 | U66: February | V66: 0 | Z66: Yes | AA66: yes
A67: 29 | B67: 45705 | C67: Mahindra & Mahindra LTD | D67: Mumbai | E67: FED | F67: Atul Patil. | H67: patil.atul@mahindra.com | I67: 17001696/001 | J67: Contract | K67: No | L67: KRIND/W/MC/AB/250003 | M67: 45705 | N67: 68000 | O67: February | P67: March | Q67: 1 | R67: ARP/3400771773 | S67: 45705 | T67: 68000 | U67: March | V67: =Table626893456[[#This Row],[Offer Value]]-Table626893456[[#This Row],[PO Value]] -> 0
A68: 30 | B68: 45705 | C68: Sulzer Pumps India Pvt Ltd | D68: Mumbai | E68: Stores | F68: Anant.Ternikar | G68: 9833345459 | H68: Anant.Ternikar@sulzer.com | I68: 102006834 | J68: Contract | K68: No | L68: KRIND/W/MC/AB/250004 | M68: 45705 | N68: 74000 | O68: February | P68: June | Q68: 1 | R68: 4502348009 | S68: 45853 | T68: 432000 | U68: July | V68: 0
A69: 30 | C69: Sulzer Pumps India Pvt Ltd | D69: Mumbai | E69: Stores | F69: Anant.Ternikar | G69: 9833345459 | H69: Anant.Ternikar@sulzer.com | I69: 102006831 | J69: Contract | K69: No | L69: KRIND/W/MC/AB/250004 | M69: 45705 | N69: 74000 | O69: February | P69: June | Q69: 1 | R69: 4502348009 | S69: 45853 | T69: 432000 | U69: July | V69: 0
A70: 31 | B70: 45698 | C70: Tata Cummins Pvt Ltd | D70: phaltan | E70: Stores | F70: vijay Pawar | G70: 7796646965 | H70: vijay.pawar@cummins.com | I70: 10006286/001 | J70: Contract | K70: No | L70: KRIND/W/MC/AB/250005 | M70: 45698 | N70: 80000 | O70: February | P70: March | Q70: 1 | R70: 50055662 | S70: 45743 | T70: 80000 | U70: March | V70: =Table626893456[[#This Row],[Offer Value]]-Table626893456[[#This Row],[PO Value]] -> 0
A71: 31 | C71: Tata Cummins Pvt Ltd | D71: phaltan | E71: Stores | F71: vijay Pawar | G71: 7796646965 | H71: vijay.pawar@cummins.com | I71: 10006271/001 | J71: Contract | K71: No | L71: KRIND/W/MC/AB/250005 | M71: 45698 | N71: 80000 | O71: February | P71: March | Q71: 1 | R71: 50055662 | S71: 45743 | T71: 80000 | U71: March | V71: =Table626893456[[#This Row],[Offer Value]]-Table626893456[[#This Row],[PO Value]] -> 0
A72: 31 | C72: Tata Cummins Pvt Ltd | D72: phaltan | E72: Stores | F72: vijay Pawar | G72: 7796646965 | H72: vijay.pawar@cummins.com | I72: 10006464/001 | J72: Contract | K72: No | L72: KRIND/W/MC/AB/250005 | M72: 45698 | N72: 45000 | O72: February | P72: March | Q72: 1 | R72: 50055662 | S72: 45743 | T72: 45000 | U72: March | V72: =Table626893456[[#This Row],[Offer Value]]-Table626893456[[#This Row],[PO Value]] -> 0
A73: 31 | C73: Tata Cummins Pvt Ltd | D73: phaltan | E73: Stores | F73: vijay Pawar | G73: 7796646965 | H73: vijay.pawar@cummins.com | I73: 10006465/001 | J73: Contract | K73: No | L73: KRIND/W/MC/AB/250005 | M73: 45698 | N73: 45000 | O73: February | P73: March | Q73: 1 | R73: 50055662 | S73: 45743 | T73: 45000 | U73: March | V73: =Table626893456[[#This Row],[Offer Value]]-Table626893456[[#This Row],[PO Value]] -> 0
A74: 31 | C74: Tata Cummins Pvt Ltd | D74: phaltan | E74: Stores | F74: vijay Pawar | G74: 7796646965 | H74: vijay.pawar@cummins.com | I74: 10006466/001 | J74: Contract | K74: No | L74: KRIND/W/MC/AB/250005 | M74: 45698 | N74: 45000 | O74: February | P74: March | Q74: 1 | R74: 50055662 | S74: 45743 | T74: 45000 | U74: March | V74: =Table626893456[[#This Row],[Offer Value]]-Table626893456[[#This Row],[PO Value]] -> 0
A75: 31 | C75: Tata Cummins Pvt Ltd | D75: phaltan | E75: Stores | F75: vijay Pawar | G75: 7796646965 | H75: vijay.pawar@cummins.com | I75: 10006467/001 | J75: Contract | K75: No | L75: KRIND/W/MC/AB/250005 | M75: 45698 | N75: 45000 | O75: February | P75: March | Q75: 1 | R75: 50055662 | S75: 45743 | T75: 45000 | U75: March | V75: =Table626893456[[#This Row],[Offer Value]]-Table626893456[[#This Row],[PO Value]] -> 0
A76: 31 | C76: Tata Cummins Pvt Ltd | D76: phaltan | E76: Stores | F76: vijay Pawar | G76: 7796646965 | H76: vijay.pawar@cummins.com | I76: 10004163/001 | J76: Contract | K76: No | L76: KRIND/W/MC/AB/250005 | M76: 45698 | N76: 45000 | O76: February | P76: March | Q76: 1 | R76: 50055662 | S76: 45743 | T76: 45000 | U76: March | V76: =Table626893456[[#This Row],[Offer Value]]-Table626893456[[#This Row],[PO Value]] -> 0
A77: 31 | C77: Tata Cummins Pvt Ltd | D77: phaltan | E77: Stores | F77: vijay Pawar | G77: 7796646965 | H77: vijay.pawar@cummins.com | I77: 10006269/001 | J77: Contract | K77: No | L77: KRIND/W/MC/AB/250005 | M77: 45698 | N77: 45000 | O77: February | P77: March | Q77: 1 | R77: 50055662 | S77: 45743 | T77: 45000 | U77: March | V77: =Table626893456[[#This Row],[Offer Value]]-Table626893456[[#This Row],[PO Value]] -> 0
A78: 31 | C78: Tata Cummins Pvt Ltd | D78: phaltan | E78: Stores | F78: vijay Pawar | G78: 7796646965 | H78: vijay.pawar@cummins.com | I78: 10006270/001 | J78: Contract | K78: No | L78: KRIND/W/MC/AB/250005 | M78: 45698 | N78: 45000 | O78: February | P78: March | Q78: 1 | R78: 50055662 | S78: 45743 | T78: 45000 | U78: March | V78: =Table626893456[[#This Row],[Offer Value]]-Table626893456[[#This Row],[PO Value]] -> 0
A79: 31 | C79: Tata Cummins Pvt Ltd | D79: phaltan | E79: Stores | F79: vijay Pawar | G79: 7796646965 | H79: vijay.pawar@cummins.com | I79: 12007409/001 | J79: Contract | K79: No | L79: KRIND/W/MC/AB/250005 | M79: 45698 | N79: 45000 | O79: February | P79: March | Q79: 1 | R79: 50055662 | S79: 45743 | T79: 45000 | U79: March | V79: =Table626893456[[#This Row],[Offer Value]]-Table626893456[[#This Row],[PO Value]] -> 0
A80: 31 | C80: Tata Cummins Pvt Ltd | D80: phaltan | E80: Stores | F80: vijay Pawar | G80: 7796646965 | H80: vijay.pawar@cummins.com | I80: 12007483/001 | J80: Contract | K80: No | L80: KRIND/W/MC/AB/250005 | M80: 45698 | N80: 45000 | O80: February | P80: March | Q80: 1 | R80: 50055662 | S80: 45743 | T80: 45000 | U80: March | V80: =Table626893456[[#This Row],[Offer Value]]-Table626893456[[#This Row],[PO Value]] -> 0
A81: 31 | C81: Tata Cummins Pvt Ltd | D81: phaltan | E81: Stores | F81: vijay Pawar | G81: 7796646965 | H81: vijay.pawar@cummins.com | I81: 13000026/001 | J81: Contract | K81: No | L81: KRIND/W/MC/AB/250005 | M81: 45698 | N81: 45000 | O81: February | P81: March | Q81: 1 | R81: 50055662 | S81: 45743 | T81: 45000 | U81: March | V81: =Table626893456[[#This Row],[Offer Value]]-Table626893456[[#This Row],[PO Value]] -> 0
A82: 31 | C82: Tata Cummins Pvt Ltd | D82: phaltan | E82: Stores | F82: vijay Pawar | G82: 7796646965 | H82: vijay.pawar@cummins.com | I82: 13000027/001 | J82: Contract | K82: No | L82: KRIND/W/MC/AB/250005 | M82: 45698 | N82: 45000 | O82: February | P82: March | Q82: 1 | R82: 50055662 | S82: 45743 | T82: 45000 | U82: March | V82: =Table626893456[[#This Row],[Offer Value]]-Table626893456[[#This Row],[PO Value]] -> 0
... A84: 31 | C84: Tata Cummins Pvt Ltd | D84: phaltan | E84: Stores | F84: vijay Pawar | G84: 7796646965 | H84: vijay.pawar@cummins.com | I84: 14006903/001 | J84: Contract | K84: No | L84: KRIND/W/MC/AB/250005 | M84: 45698 | N84: 45000 | O84: February | P84: March | Q84: 1 | R84: 50055662 | S84: 45743 | T84: 45000 | U84: March | V84: =Table626893456[[#This Row],[Offer Value]]-Table626893456[[#This Row],[PO Value]] -> 0
A85: 32 | B85: 45698 | C85: Tata Cummins Pvt Ltd | D85: phaltan | E85: Stores | F85: vijay Pawar | G85: 7796646965 | H85: vijay.pawar@cummins.com | I85: 14006903/001 | J85: Upgrade kit | K85: YES | L85: KRIND/W/SPP/AB25009 | M85: 45698 | N85: 1499595 | O85: February | P85: March | Q85: 1 | R85: 50055312 | S85: 45719 | T85: 1455917 | U85: March | V85: 0 | Z85: no | AA85: no
A86: 33 | B86: 45707 | C86: GE India Industrial Pvt.Ltd. | D86: Pune | E86: Stores | F86: vishal.khaware | G86: 8975397991 | H86: vishal.khaware@geaerospace.com | I86: 16004510/001 | J86: SPP | K86: YES | L86: KRIND/W/SPP/AB/25008 | M86: 45707 | N86: 445627 | O86: February | P86: March | Q86: 1 | R86: 2006269 | S86: 45728 | T86: 367397 | U86: March | V86: 0 | Z86: Yes | AA86: yes
A87: 34 | B87: 45717 | C87: GE India Industrial Pvt.Ltd. | D87: Pune | E87: Stores | F87: vishal.khaware | G87: 8975397991 | H87: vishal.khaware@geaerospace.com | I87: 16005398/001 | J87: Contract | K87: NO | L87: KRIND/W/MC/AB/250006 | M87: 45717 | N87: 72000 | O87: March | P87: March | Q87: 1 | R87: 2006637 | S87: 45729 | T87: 72000 | U87: March | V87: =Table626893456[[#This Row],[Offer Value]]-Table626893456[[#This Row],[PO Value]] -> 0
A88: 34 | C88: GE India Industrial Pvt.Ltd. | D88: Pune | E88: Stores | F88: vishal.khaware | G88: 8975397991 | H88: vishal.khaware@geaerospace.com | I88: 16005398/002 | J88: Contract | K88: NO | L88: KRIND/W/MC/AB/250006 | M88: 45717 | N88: 72000 | O88: March | P88: March | Q88: 1 | R88: 2006637 | S88: 45729 | T88: 72000 | U88: March | V88: =Table626893456[[#This Row],[Offer Value]]-Table626893456[[#This Row],[PO Value]] -> 0
A89: 34 | C89: GE India Industrial Pvt.Ltd. | D89: Pune | E89: Stores | F89: vishal.khaware | G89: 8975397991 | H89: vishal.khaware@geaerospace.com | I89: 16004510/001 | J89: Contract | K89: NO | L89: KRIND/W/MC/AB/250006 | M89: 45717 | N89: 72000 | O89: March | P89: March | Q89: 1 | R89: 2006637 | S89: 45729 | T89: 72000 | U89: March | V89: =Table626893456[[#This Row],[Offer Value]]-Table626893456[[#This Row],[PO Value]] -> 0
A90: 34 | C90: GE India Industrial Pvt.Ltd. | D90: Pune | E90: Stores | F90: vishal.khaware | G90: 8975397991 | H90: vishal.khaware@geaerospace.com | I90: 19008263/001 | J90: Contract | K90: NO | L90: KRIND/W/MC/AB/250006 | M90: 45717 | N90: 72000 | O90: March | P90: March | Q90: 1 | R90: 2006637 | S90: 45729 | T90: 72000 | U90: March | V90: =Table626893456[[#This Row],[Offer Value]]-Table626893456[[#This Row],[PO Value]] -> 0
A91: 35 | B91: 45717 | C91: Firmenich Aerometics I Pvt.ltd. | D91: Mumbai | E91: QC | F91: Sonal Rane | G91: 8422085743 | H91: sonal.rane@dsm-firmenich.com | I91: 18007780/001 | J91: Contract | K91: NO | L91: LPO | M91: 45721 | N91: 58000 | O91: March | P91: March | Q91: 1 | R91: 3001030991 | S91: 45719 | T91: 58000 | U91: March | V91: =Table626893456[[#This Row],[Offer Value]]-Table626893456[[#This Row],[PO Value]] -> 0
A92: 35 | C92: Firmenich Aerometics I Pvt.ltd. | D92: Mumbai | E92: QC | F92: Sonal Rane | G92: 8422085743 | H92: sonal.rane@dsm-firmenich.com | I92: 18007781/001 | J92: Contract | K92: NO | L92: LPO | M92: 45721 | N92: 58000 | O92: March | P92: March | Q92: 1 | R92: 3001030991 | S92: 45719 | T92: 58000 | U92: March | V92: =Table626893456[[#This Row],[Offer Value]]-Table626893456[[#This Row],[PO Value]] -> 0
A93: 36 | B93: 45722 | C93: KSB Pumps LTD | D93: shirwal | E93: Stores | F93: Sachine Pawar | G93: 9822412607 | H93: sachin.pawar@ksb.com | I93: 03006736/001 | J93: Contract | K93: NO | L93: KRIND/W/MC/AB/250007 | M93: 45722 | N93: 68000 | O93: March | P93: May | Q93: 1 | R93: 4507494931 | S93: 45771 | T93: 62000 | U93: May | V93: 0
A94: 36 | C94: KSB Pumps LTD | D94: shirwal | E94: Stores | F94: Sachine Pawar | G94: 9822412607 | H94: sachin.pawar@ksb.com | I94: 02002336/001 | J94: Contract | K94: NO | L94: KRIND/W/MC/AB/250007 | M94: 45722 | N94: 68000 | O94: March | P94: May | Q94: 1 | R94: 4507494931 | S94: 45771 | T94: 62000 | U94: May | V94: 0
A95: 36 | C95: KSB Pumps LTD | D95: shirwal | E95: Stores | F95: Sachine Pawar | G95: 9822412607 | H95: sachin.pawar@ksb.com | I95: 02002336/002 | J95: Contract | K95: NO | L95: KRIND/W/MC/AB/250007 | M95: 45722 | N95: 68000 | O95: March | P95: May | Q95: 1 | R95: 4507494931 | S95: 45771 | T95: 62000 | U95: May | V95: 0
A96: 36 | C96: KSB Pumps LTD | D96: shirwal | E96: Stores | F96: Sachine Pawar | G96: 9822412607 | H96: sachin.pawar@ksb.com | I96: 10004055/001 | J96: Contract | K96: NO | L96: KRIND/W/MC/AB/250007 | M96: 45722 | N96: 68000 | O96: March | P96: May | Q96: 1 | R96: 4507494931 | S96: 45771 | T96: 62000 | U96: May | V96: 0
A97: 36 | C97: KSB Pumps LTD | D97: shirwal | E97: Stores | F97: Sachine Pawar | G97: 9822412607 | H97: sachin.pawar@ksb.com | I97: 08002469/001 | J97: Contract | K97: NO | L97: KRIND/W/MC/AB/250007 | M97: 45722 | N97: 68000 | O97: March | P97: May | Q97: 1 | R97: 4507494931 | S97: 45771 | T97: 62000 | U97: May | V97: 0
A98: 36 | C98: KSB Pumps LTD | D98: shirwal | E98: Stores | F98: Sachine Pawar | G98: 9822412607 | H98: sachin.pawar@ksb.com | I98: 19003348/001 | J98: Contract | K98: NO | L98: KRIND/W/MC/AB/250007 | M98: 45722 | N98: 68000 | O98: March | P98: May | Q98: 1 | R98: 4507494931 | S98: 45771 | T98: 62000 | U98: May | V98: 0
A99: 37 | B99: 45729 | C99: Sandvik Coromant India Pvt Ltd | D99: Pune | E99: Stores | F99: Umesh Nagdeote | H99: umesh.nagdeote@sandvik.com | I99: 12005696/001 | J99: Contract | K99: NO | L99: KXIND/W/MC/AB25009 | M99: 45729 | N99: 46000 | O99: March | P99: April | Q99: 1 | R99: 4512404840 | S99: 45742 | T99: 46000 | U99: March | V99: =Table626893456[[#This Row],[Offer Value]]-Table626893456[[#This Row],[PO Value]] -> 0
A100: 37 | C100: Sandvik Coromant India Pvt Ltd | D100: Pune | E100: Stores | F100: Umesh Nagdeote | H100: umesh.nagdeote@sandvik.com | I100: 17007934/001 | J100: Contract | K100: NO | L100: KXIND/W/MC/AB25009 | M100: 45729 | N100: 46000 | O100: March | P100: April | Q100: 1 | R100: 4512404840 | S100: 45742 | T100: 46000 | U100: March | V100: =Table626893456[[#This Row],[Offer Value]]-Table626893456[[#This Row],[PO Value]] -> 0
A101: 38 | B101: 45729 | C101: Sandvik Coromant India Pvt Ltd | D101: Pune | E101: PVD | F101: Alop Vibhute | G101: 9922423997 | H101: alop.vibhute@sandvik.com | I101: 13006092/001 | J101: Contract | K101: NO | L101: KXIND/W/MC/AB250010 | M101: 45729 | N101: 46000 | O101: March | P101: April | Q101: 1 | R101: 4512404853 | S101: 45742 | T101: 46000 | U101: March | V101: =Table626893456[[#This Row],[Offer Value]]-Table626893456[[#This Row],[PO Value]] -> 0
A102: 38 | C102: Sandvik Coromant India Pvt Ltd | D102: Pune | E102: CVD | F102: Alop Vibhute | G102: 9922423997 | H102: alop.vibhute@sandvik.com | I102: 16003851/001 | J102: Contract | K102: NO | L102: KXIND/W/MC/AB250010 | M102: 45729 | N102: 46000 | O102: March | P102: April | Q102: 1 | R102: 4512404853 | S102: 45742 | T102: 46000 | U102: March | V102: =Table626893456[[#This Row],[Offer Value]]-Table626893456[[#This Row],[PO Value]] -> 0
...

Sheet Rahul
H1: 2062108 | AB1: Month wise data
A2: KARDEX INDIA - LIVE OFFER FUNEL - RAHUL - WEST | AB2: Month | AC2: Offers Total | AD2: Order received | AE2: Forecast | AF2: Forecast- Po Received
U3: Total Offered Value | V3: =SUM(N7:N397) -> 56159754 | AB3: January | AC3: =SUMIF($O$7:$O$397,"January",$N$7:$N$397) -> 18381668 | AD3: =SUMIF($U$7:$U$397,"January",$T$7:$T$397) -> 5747102 | AE3: =SUMIF($P$7:$P$427,"January",$N$7:$N$427) -> 6160514 | AF3: =AE3-AD3 -> 413412
A4: Total Offers | B4: =COUNTA(B7:B1419) -> 208 | U4: Order Received | V4: =SUM(T7:T397) -> 30514486 | AB4: February | AC4: =SUMIF($O$7:$O$397,"February",$N$7:$N$397) -> 6168252 | AD4: =SUMIF($U$7:$U$397,"February",$T$7:$T$397) -> 539332 | AE4: =SUMIF($P$7:$P$427,"February",$N$7:$N$427) -> 4146986 | AF4: =AE4-AD4 -> 3607654
U5: Open Funnel | V5: =SUM(V7:V398) -> 15274441 | Y5: * Updated by Girija | AB5: March | AC5: =SUMIF($O$7:$O$397,"March",$N$7:$N$397) -> 3329622 | AD5: =SUMIF($U$7:$U$397,"March",$T$7:$T$397) -> 7502698 | AE5: =SUMIF($P$7:$P$427,"March",$N$7:$N$427) -> 4630660 | AF5: =AE5-AD5 -> -2872038
A6: SL | B6: Reg Date | C6: Company | D6: Location | E6: Department | F6: Contact Person Name | G6: Contact Number | H6: E-Mail ID | I6: Machine Serial Number | J6: Product Type | K6: Lead | L6: Offer Reference Number | M6: September | N6: Offer Value | O6: Offer Month | P6: PO Expected Month | Q6: Probabality in Percentage | R6: PO Number | S6: PO Date | T6: PO Value | U6: PO Received Month | V6: Open Funnel | W6: Remarks | X6: Status | Y6: Booking Date in SAP B1 | Z6: Offer Entered in CRM | AA6: Offer Closed in CRM | AB6: April | AC6: =SUMIF($O$7:$O$397,"April",$N$7:$N$397) -> 2227333 | AD6: =SUMIF($U$7:$U$397,"April",$T$7:$T$397) -> 1946444 | AE6: =SUMIF($P$7:$P$427,"April",$N$7:$N$427) -> 3799298 | AF6: =AE6-AD6 -> 1852854
A7: 1 | B7: 45658 | C7: Mylan Laboratories LTD | D7: Nashik | E7: QA | F7: Kiran Mapari | G7: 251674799 | H7: kiran.mapari@viatris.com | I7: 15003032/001 | J7: Contract | K7: No | L7: KXIND/W/MC/RV24-060 | M7: 45658 | N7: 118335 | O7: January | P7: February | Q7: 1 | R7: 5700166357 | S7: 22-01-2025 | T7: 118335 | U7: January | V7: 0 | W7: Please share the PO copy | X7: As discussion, quotation reference no not mentionin po and i have alarded send the email but till have not received the amendment po copy | Z7: yes | AA7: yes | AB7: May | AC7: =SUMIF($O$7:$O$397,"May",$N$7:$N$397) -> 9418264 | AD7: =SUMIF($U$7:$U$397,"May",$T$7:$T$397) -> 2023542 | AE7: =SUMIF($P$7:$P$427,"May",$N$7:$N$427) -> 5936472 | AF7: =AE7-AD7 -> 3912930
A8: 2 | C8: Mylan Laboratories LTD | D8: Nashik | E8: QA | F8: Kiran Mapari | G8: 251674799 | H8: kiran.mapari@viatris.com | I8: 15003032/002 | J8: Contract | K8: No | L8: KXIND/W/MC/RV24-060 | M8: 45658 | N8: 118335 | O8: January | P8: February | Q8: 1 | R8: 5700166357 | S8: 22-01-2025 | T8: 118335 | U8: January | V8: 0 | W8: Please share the PO copy | AB8: June | AC8: =SUMIF($O$7:$O$397,"June",$N$7:$N$397) -> 1697290 | AD8: =SUMIF($U$7:$U$397,"June",$T$7:$T$397) -> 2252051 | AE8: =SUMIF($P$7:$P$427,"June",$N$7:$N$427) -> 6140548 | AF8: =AE8-AD8 -> 3888497
A9: 3 | C9: Mylan Laboratories LTD | D9: Nashik | E9: QA | F9: Kiran Mapari | G9: 251674799 | H9: kiran.mapari@viatris.com | I9: 18005565/001 | J9: Contract | K9: No | L9: KXIND/W/MC/RV24-060 | M9: 45658 | N9: 118335 | O9: January | P9: February | Q9: 1 | R9: 5700166357 | S9: 22-01-2025 | T9: 118335 | U9: January | V9: 0 | W9: Please share the PO copy | AB9: July | AC9: =SUMIF($O$7:$O$397,"July",$N$7:$N$397) -> 877510 | AD9: =SUMIF($U$7:$U$397,"July",$T$7:$T$397) -> 2954131 | AE9: =SUMIF($P$7:$P$427,"July",$N$7:$N$427) -> 4247261 | AF9: =AE9-AD9 -> 1293130
A10: 4 | C10: Mylan Laboratories LTD | D10: Nashik | E10: QA | F10: Kiran Mapari | G10: 251674799 | H10: kiran.mapari@viatris.com | I10: 18005565/002 | J10: Contract | K10: No | L10: KXIND/W/MC/RV24-060 | M10: 45658 | N10: 118335 | O10: January | P10: February | Q10: 1 | R10: 5700166357 | S10: 22-01-2025 | T10: 118335 | U10: January | V10: 0 | W10: Please share the PO copy | AB10: August | AC10: =SUMIF($O$7:$O$397,"August",$N$7:$N$397) -> 2373197 | AD10: =SUMIF($U$7:$U$397,"August",$T$7:$T$397) -> 1905084 | AE10: =SUMIF($P$7:$P$427,"August",$N$7:$N$427) -> 1809730 | AF10: =AE10-AD10 -> -95354
A11: 5 | C11: Mylan Laboratories LTD | D11: Nashik | E11: QA | F11: Kiran Mapari | G11: 251674799 | H11: kiran.mapari@viatris.com | I11: 18005565/003 | J11: Contract | K11: No | L11: KXIND/W/MC/RV24-060 | M11: 45658 | N11: 118335 | O11: January | P11: February | Q11: 1 | R11: 5700166357 | S11: 22-01-2025 | T11: 118335 | U11: January | V11: 0 | W11: Please share the PO copy | AB11: September | AC11: =SUMIF($O$7:$O$397,"September",$N$7:$N$397) -> 824820 | AD11: =SUMIF($U$7:$U$397,"September",$T$7:$T$397) -> 779050 | AE11: =SUMIF($P$7:$P$427,"September",$N$7:$N$427) -> 1523678 | AF11: =AE11-AD11 -> 744628
A12: 6 | C12: Mylan Laboratories LTD | D12: Nashik | E12: QA | F12: Kiran Mapari | G12: 251674799 | H12: kiran.mapari@viatris.com | I12: 18005565/004 | J12: Contract | K12: No | L12: KXIND/W/MC/RV24-060 | M12: 45658 | N12: 118335 | O12: January | P12: February | Q12: 1 | R12: 5700166357 | S12: 22-01-2025 | T12: 118335 | U12: January | V12: 0 | W12: Please share the PO copy | AB12: October | AC12: =SUMIF($O$7:$O$397,"October",$N$7:$N$397) -> 2241390 | AD12: =SUMIF($U$7:$U$397,"October",$T$7:$T$397) -> 697320 | AE12: =SUMIF($P$7:$P$427,"October",$N$7:$N$427) -> 2049077 | AF12: =AE12-AD12 -> 1351757
A13: 7 | C13: Mylan Laboratories LTD | D13: Nashik | E13: QA | F13: Kiran Mapari | G13: 251674799 | H13: kiran.mapari@viatris.com | I13: 18005565/005 | J13: Contract | K13: No | L13: KXIND/W/MC/RV24-060 | M13: 45658 | N13: 118335 | O13: January | P13: February | Q13: 1 | R13: 5700166357 | S13: 22-01-2025 | T13: 118335 | U13: January | V13: 0 | W13: Please share the PO copy | AB13: November | AC13: =SUMIF($O$7:$O$397,"November",$N$7:$N$397) -> 4549000 | AD13: =SUMIF($U$7:$U$397,"November",$T$7:$T$397) -> 1021853 | AE13: =SUMIF($P$7:$P$427,"November",$N$7:$N$427) -> 7527818 | AF13: =AE13-AD13 -> 6505965
A14: 8 | C14: Mylan Laboratories LTD | D14: Nashik | E14: QA | F14: Kiran Mapari | G14: 251674799 | H14: kiran.mapari@viatris.com | I14: 21003710/001 | J14: Contract | K14: No | L14: KXIND/W/MC/RV24-060 | M14: 45658 | N14: 118335 | O14: January | P14: February | Q14: 1 | R14: 5700166357 | S14: 22-01-2025 | T14: 118335 | U14: January | V14: 0 | W14: Please share the PO copy | AB14: December | AC14: =SUMIF($O$7:$O$397,"December",$N$7:$N$397) -> 4071408 | AD14: =SUMIF($U$7:$U$397,"December",$T$7:$T$397) -> 2950499 | AE14: =SUMIF($P$7:$P$427,"December",$N$7:$N$427) -> 8187712 | AF14: =AE14-AD14 -> 5237213
A15: 9 | B15: 45658 | C15: Sterlite Infra Tech PVT LTD | D15: Aurangabad | E15: Store | F15: Mujtaba Shaikh | G15: 8552913019 | H15: shaikh.mujtaba@stl.tech | I15: 10009100/001 | J15: Contract | K15: No | L15: KXIND/W/MC/RV24-062 | M15: 25-07-2024 | N15: 69500 | O15: January | P15: August | Q15: 1 | R15: 6550003687-0 | S15: 45846 | T15: 65000 | U15: July | V15: 0 | W15: Customer condition not good and no budget
A16: 10 | C16: Sterlite Infra Tech PVT LTD | D16: Aurangabad | E16: Store | F16: Mujtaba Shaikh | G16: 8552913019 | H16: shaikh.mujtaba@stl.tech | I16: 10009101/001 | J16: Contract | K16: No | L16: KXIND/W/MC/RV24-062 | M16: 25-07-2024 | N16: 69500 | O16: January | P16: August | Q16: 1 | R16: 6550003687-0 | S16: 45846 | T16: 65000 | U16: July | V16: 0 | W16: Customer condition not good and no budget
A17: 11 | C17: Sterlite Infra Tech PVT LTD | D17: Aurangabad | E17: Store | F17: Mujtaba Shaikh | G17: 8552913019 | H17: shaikh.mujtaba@stl.tech | I17: 12003615/001 | J17: Contract | K17: No | L17: KXIND/W/MC/RV24-062 | M17: 25-07-2024 | N17: 69500 | O17: January | P17: August | Q17: 1 | R17: 6550003687-0 | S17: 45846 | T17: 65000 | U17: July | V17: 0
A18: 12 | C18: Sterlite Infra Tech PVT LTD | D18: Aurangabad | E18: Store | F18: Mujtaba Shaikh | G18: 8552913019 | H18: shaikh.mujtaba@stl.tech | I18: 12003616/001 | J18: Contract | K18: No | L18: KXIND/W/MC/RV24-062 | M18: 25-07-2024 | N18: 69500 | O18: January | P18: August | Q18: 1 | R18: 6550003687-0 | S18: 45846 | T18: 65000 | U18: July | V18: 0
A19: 13 | C19: Sterlite Infra Tech PVT LTD | D19: Aurangabad | E19: Store | F19: Mujtaba Shaikh | G19: 8552913019 | H19: shaikh.mujtaba@stl.tech | I19: 17008417/001 | J19: Contract | K19: No | L19: KXIND/W/MC/RV24-062 | M19: 25-07-2024 | N19: 69500 | O19: January | P19: August | Q19: 1 | R19: 6550003687-0 | S19: 45846 | T19: 65000 | U19: July | V19: 0
A20: 14 | C20: Sterlite Infra Tech PVT LTD | D20: Aurangabad | E20: Store | F20: Mujtaba Shaikh | G20: 8552913019 | H20: shaikh.mujtaba@stl.tech | I20: 17008417/002 | J20: Contract | K20: No | L20: KXIND/W/MC/RV24-062 | M20: 25-07-2024 | N20: 69500 | O20: January | P20: August | Q20: 1 | R20: 6550003687-0 | S20: 45846 | T20: 65000 | U20: July | V20: 0
A21: 15 | C21: Sterlite Infra Tech PVT LTD | D21: Aurangabad | E21: Store | F21: Mujtaba Shaikh | G21: 8552913019 | H21: shaikh.mujtaba@stl.tech | I21: 17008417/003 | J21: Contract | K21: No | L21: KXIND/W/MC/RV24-062 | M21: 25-07-2024 | N21: 69500 | O21: January | P21: August | Q21: 1 | R21: 6550003687-0 | S21: 45846 | T21: 65000 | U21: July | V21: 0
A22: 16 | B22: 45658 | C22: Hindustan Aeronautics LTD | D22: Nashik | E22: SU30 | F22: Ramesh Dodve | G22: 9405209839 | H22: ramesh.dodve@hal-india.co.in | I22: 15000048/001 | J22: Midlife Upgrade | K22: Yes | L22: KXIND/W/MLU/RV24-067 | M22: 45360 | N22: 1618603 | O22: January | P22: November | Q22: 0.9 | V22: 1618603 | W22: PO will be received in Dec 25 | Z22: Yes
A23: 17 | B23: 45658 | C23: Hindustan Aeronautics LTD | D23: Nashik | E23: SU30 | F23: Ramesh Dodve | G23: 9405209839 | H23: ramesh.dodve@hal-india.co.in | I23: 15000048/001 | J23: Contract | K23: Yes | L23: KXIND/W/MC/RV24-068 | M23: 45360 | N23: 92000 | O23: January | P23: November | Q23: 0.9 | V23: 92000 | W23: PO will be received in Dec 25
A24: 18 | B24: 45658 | C24: Hindustan Aeronautics LTD | D24: Nashik | E24: SU30 | F24: Ramesh Dodve | G24: 9405209839 | H24: ramesh.dodve@hal-india.co.in | I24: 15000049/001 | J24: Contract | K24: Yes | L24: KXIND/W/MC/RV24-068 | M24: 45360 | N24: 92000 | O24: January | P24: November | Q24: 0.9 | V24: 92000 | W24: PO will be received in Dec 25
A25: 19 | B25: 45658 | C25: Hindustan Aeronautics LTD | D25: Nashik | E25: Shop 09 | F25: Sajul Rameshroy | G25: 9970460493 | H25: sajal.roy@hal-india.com | I25: 10002485/001 | J25: SPP | K25: Yes | L25: KXIND/W/SPP/RV24-073 | M25: 21/10/2024 | N25: 85384 | O25: January | P25: April | Q25: 1 | R25: GEMC-511687723731375 | S25: 31/3/2025 | T25: 85384 | U25: March | V25: 0
A26: 20 | B26: 45658 | C26: Siemens Ltd. | D26: Mumbai | E26: Switchgear | F26: Dattaram Bagaytkar | G26: 9819509486 | H26: dattaram.bagayatkar@siemens.com | I26: 05006083/001 | J26: Contract | K26: No | L26: KXIND/W/MC/RV24-076 | M26: 16/10/2024 | N26: 73063 | O26: January | P26: February | Q26: 1 | R26: 9708942802 | S26: 24-01-2025 | T26: 73063 | U26: January | V26: 0
A27: 21 | C27: Siemens Ltd. | D27: Mumbai | E27: Switchgear | F27: Dattaram Bagaytkar | G27: 9819509486 | H27: dattaram.bagayatkar@siemens.com | I27: 06008965/001 | J27: Contract | K27: No | L27: KXIND/W/MC/RV24-076 | M27: 16/10/2024 | N27: 73063 | O27: January | P27: February | Q27: 1 | R27: 9708942802 | S27: 24-01-2025 | T27: 73063 | U27: January | V27: 0
A28: 22 | C28: Siemens Ltd. | D28: Mumbai | E28: Switchgear | F28: Dattaram Bagaytkar | G28: 9819509486 | H28: dattaram.bagayatkar@siemens.com | I28: 06008965/002 | J28: Contract | K28: No | L28: KXIND/W/MC/RV24-076 | M28: 16/10/2024 | N28: 73063 | O28: January | P28: February | Q28: 1 | R28: 9708942802 | S28: 24-01-2025 | T28: 73063 | U28: January | V28: 0
A29: 23 | C29: Siemens Ltd. | D29: Mumbai | E29: Switchgear | F29: Dattaram Bagaytkar | G29: 9819509486 | H29: dattaram.bagayatkar@siemens.com | I29: 06006147/001 | J29: Contract | K29: No | L29: KXIND/W/MC/RV24-076 | M29: 16/10/2024 | N29: 73063 | O29: January | P29: February | Q29: 1 | R29: 9708942802 | S29: 24-01-2025 | T29: 73063 | U29: January | V29: 0
A30: 24 | C30: Siemens Ltd. | D30: Mumbai | E30: Switchgear | F30: Dattaram Bagaytkar | G30: 9819509486 | H30: dattaram.bagayatkar@siemens.com | I30: 10001386/001 | J30: Contract | K30: No | L30: KXIND/W/MC/RV24-076 | M30: 16/10/2024 | N30: 73063 | O30: January | P30: February | Q30: 1 | R30: 9708942802 | S30: 24-01-2025 | T30: 73063 | U30: January | V30: 0
A31: 25 | C31: Siemens Ltd. | D31: Mumbai | E31: Switchgear | F31: Dattaram Bagaytkar | G31: 9819509486 | H31: dattaram.bagayatkar@siemens.com | I31: 10002925/001 | J31: Contract | K31: No | L31: KXIND/W/MC/RV24-076 | M31: 16/10/2024 | N31: 73063 | O31: January | P31: February | Q31: 1 | R31: 9708942802 | S31: 24-01-2025 | T31: 73063 | U31: January | V31: 0
A32: 26 | C32: Siemens Ltd. | D32: Mumbai | E32: Switchgear | F32: Dattaram Bagaytkar | G32: 9819509486 | H32: dattaram.bagayatkar@siemens.com | I32: 08006407/001 | J32: Contract | K32: No | L32: KXIND/W/MC/RV24-076 | M32: 16/10/2024 | N32: 73063 | O32: January | P32: February | Q32: 1 | R32: 9708942802 | S32: 24-01-2025 | T32: 73063 | U32: January | V32: 0
A33: 27 | C33: Siemens Ltd. | D33: Mumbai | E33: Switchgear | F33: Dattaram Bagaytkar | G33: 9819509486 | H33: dattaram.bagayatkar@siemens.com | I33: 11002921/001 | J33: Contract | K33: No | L33: KXIND/W/MC/RV24-076 | M33: 16/10/2024 | N33: 73063 | O33: January | P33: February | Q33: 1 | R33: 9708942802 | S33: 24-01-2025 | T33: 73063 | U33: January | V33: 0
A34: 28 | C34: Siemens Ltd. | D34: Mumbai | E34: Switchgear | F34: Dattaram Bagaytkar | G34: 9819509486 | H34: dattaram.bagayatkar@siemens.com | J34: Contract | K34: No | L34: KXIND/W/MC/RV24-076 | M34: 16/10/2024 | N34: 73063 | O34: January | P34: February | Q34: 1 | R34: 9708942802 | S34: 24-01-2025 | T34: 73063 | U34: January | V34: 0
A35: 29 | C35: Siemens Ltd. | D35: Mumbai | E35: Switchgear | F35: Dattaram Bagaytkar | G35: 9819509486 | H35: dattaram.bagayatkar@siemens.com | J35: Contract | K35: No | L35: KXIND/W/MC/RV24-076 | M35: 16/10/2024 | N35: 73063 | O35: January | P35: February | Q35: 1 | R35: 9708942802 | S35: 24-01-2025 | T35: 73063 | U35: January | V35: 0
A36: 30 | C36: Siemens Ltd. | D36: Mumbai | E36: Switchgear | F36: Dattaram Bagaytkar | G36: 9819509486 | H36: dattaram.bagayatkar@siemens.com | I36: 11004947/001 | J36: Contract | K36: No | L36: KXIND/W/MC/RV24-076 | M36: 16/10/2024 | N36: 73063 | O36: January | P36: February | Q36: 1 | R36: 9708942802 | S36: 24-01-2025 | T36: 73063 | U36: January | V36: 0
A37: 31 | C37: Siemens Ltd. | D37: Mumbai | E37: Switchgear | F37: Dattaram Bagaytkar | G37: 9819509486 | H37: dattaram.bagayatkar@siemens.com | I37: 11004359/001 | J37: Contract | K37: No | L37: KXIND/W/MC/RV24-076 | M37: 16/10/2024 | N37: 73063 | O37: January | P37: February | Q37: 1 | R37: 9708942802 | S37: 24-01-2025 | T37: 73063 | U37: January | V37: 0
A38: 32 | C38: Siemens Ltd. | D38: Mumbai | E38: Switchgear | F38: Dattaram Bagaytkar | G38: 9819509486 | H38: dattaram.bagayatkar@siemens.com | I38: 09002884/001 | J38: Contract | K38: No | L38: KXIND/W/MC/RV24-076 | M38: 16/10/2024 | N38: 73063 | O38: January | P38: February | Q38: 1 | R38: 9708942802 | S38: 24-01-2025 | T38: 73063 | U38: January | V38: 0
A39: 33 | B39: 45658 | C39: Siemens Ltd. | D39: Nashik | E39: Tool | F39: Prasad Dusane | G39: 9850225626 | H39: prasad.dusane@siemens.com | I39: 16002528/001 | J39: Midlife Upgrade | K39: Yes | L39: KXIND/W/MLU/RV24-077 | M39: 27-10-2024 | N39: 1147898 | O39: January | P39: June | Q39: 1 | R39: 9709250604 | S39: 15/7/2025 | T39: 232218 | U39: July | V39: 0 | W39: Under discussion | Z39: Yes | AA39: yes
A40: 34 | B40: 45658 | C40: Bajaj Auto Ltd | D40: Aurangabad | E40: 3WH | F40: Chandrashekhar Pathak | G40: 7757057351 | H40: cspathak@bajajauto.co.in | I40: 14002435/001 | J40: Contract | K40: No | L40: KXIND/W/MC/RV24-081 | M40: 45628 | N40: 97200 | O40: January | P40: February | Q40: 1 | R40: 3110014225 | S40: 45666 | T40: 93312 | U40: January | V40: 0
A41: 35 | B41: 45658 | C41: Mylan Laboratories LTD | D41: Aurangabad | F41: Shahed Lathif | G41: 8888827337 | H41: shahed.lathif@viatris.com | I41: 12009614/001 | J41: Contract | K41: No | L41: KXIND/W/MC/RV24-082 | M41: 45628 | N41: 102900 | O41: January | P41: February | Q41: 1 | R41: 5700166359 | S41: 27-01-2025 | T41: 102900 | U41: January | V41: 0 | X41: As discussion, quotation reference no not mentionin po and i have alarded send the email but till have not received the amendment po copy
A42: 36 | C42: Mylan Laboratories LTD | D42: Aurangabad | F42: Shahed Lathif | G42: 8888827337 | H42: shahed.lathif@viatris.com | I42: 13006585/001 | J42: Contract | K42: No | L42: KXIND/W/MC/RV24-082 | M42: 45628 | N42: 102900 | O42: January | P42: February | Q42: 1 | R42: 5700166359 | S42: 27-01-2025 | T42: 102900 | U42: January | V42: 0
A43: 37 | C43: Mylan Laboratories LTD | D43: Aurangabad | F43: Shahed Lathif | G43: 8888827337 | H43: shahed.lathif@viatris.com | I43: 15003921/001 | J43: Contract | K43: No | L43: KXIND/W/MC/RV24-082 | M43: 45628 | N43: 102900 | O43: January | P43: February | Q43: 1 | R43: 5700166359 | S43: 27-01-2025 | T43: 102900 | U43: January | V43: 0
A44: 38 | C44: Mylan Laboratories LTD | D44: Aurangabad | F44: Shahed Lathif | G44: 8888827337 | H44: shahed.lathif@viatris.com | I44: 15003709/001 | J44: Contract | K44: No | L44: KXIND/W/MC/RV24-082 | M44: 45628 | N44: 118335 | O44: January | P44: February | Q44: 1 | R44: 5700166359 | S44: 27-01-2025 | T44: 118335 | U44: January | V44: 0
A45: 39 | C45: Mylan Laboratories LTD | D45: Aurangabad | F45: Shahed Lathif | G45: 8888827337 | H45: shahed.lathif@viatris.com | I45: 16002947/001 | J45: Contract | K45: No | L45: KXIND/W/MC/RV24-082 | M45: 45628 | N45: 118335 | O45: January | P45: February | Q45: 1 | R45: 5700166359 | S45: 27-01-2025 | T45: 118335 | U45: January | V45: 0
A46: 40 | C46: Mylan Laboratories LTD | D46: Aurangabad | F46: Shahed Lathif | G46: 8888827337 | H46: shahed.lathif@viatris.com | I46: 16002948/001 | J46: Contract | K46: No | L46: KXIND/W/MC/RV24-082 | M46: 45628 | N46: 118335 | O46: January | P46: February | Q46: 1 | R46: 5700166359 | S46: 27-01-2025 | T46: 118335 | U46: January | V46: 0
A47: 41 | C47: Mylan Laboratories LTD | D47: Aurangabad | F47: Shahed Lathif | G47: 8888827337 | H47: shahed.lathif@viatris.com | I47: 20007338/001 | J47: Contract | K47: No | L47: KXIND/W/MC/RV24-082 | M47: 45628 | N47: 118335 | O47: January | P47: February | Q47: 1 | R47: 5700166359 | S47: 27-01-2025 | T47: 118335 | U47: January | V47: 0
A48: 42 | C48: Mylan Laboratories LTD | D48: Aurangabad | F48: Shahed Lathif | G48: 8888827337 | H48: shahed.lathif@viatris.com | I48: 20005831/001 | J48: Contract | K48: Yes | L48: KXIND/W/MC/RV24-082 | M48: 45628 | N48: 118335 | O48: January | P48: February | Q48: 1 | R48: 5700166359 | S48: 27-01-2025 | T48: 118335 | U48: January | V48: 0
A49: 43 | C49: Mylan Laboratories LTD | D49: Aurangabad | F49: Shahed Lathif | G49: 8888827337 | H49: shahed.lathif@viatris.com | I49: 21003712/001 | J49: Contract | K49: Yes | L49: KXIND/W/MC/RV24-082 | M49: 45628 | N49: 118335 | O49: January | P49: February | Q49: 1 | R49: 5700166359 | S49: 27-01-2025 | T49: 118335 | U49: January | V49: 0
A50: 44 | C50: Mylan Laboratories LTD | D50: Aurangabad | F50: Shahed Lathif | G50: 8888827337 | H50: shahed.lathif@viatris.com | I50: 22001840/001 | J50: Contract | K50: Yes | L50: KXIND/W/MC/RV24-082 | M50: 45628 | N50: 118335 | O50: January | P50: February | Q50: 1 | R50: 5700166359 | S50: 27-01-2025 | T50: 118335 | U50: January | V50: 0
A51: 45 | C51: Mylan Laboratories LTD | D51: Aurangabad | F51: Shahed Lathif | G51: 8888827337 | H51: shahed.lathif@viatris.com | I51: 19004083/001 | J51: Contract | K51: Yes | L51: KXIND/W/MC/RV24-082 | M51: 45628 | N51: 118335 | O51: January | P51: February | Q51: 1 | R51: 5700166359 | S51: 27-01-2025 | T51: 118335 | U51: January | V51: 0
A52: 46 | B52: 45658 | C52: Bosch Ltd | D52: Nashik | E52: 106 | F52: Rahul Raut | G52: 9604444138 | H52: rahul.raut@in.bosch.com | I52: 97007156/001 | J52: SPP | K52: Yes | L52: KXIND/W/SPP/RV24-083 | M52: 45631 | N52: 207279 | O52: January | P52: February | Q52: 1 | R52: 85378473 | S52: 17-01-2025 | T52: 98780 | U52: January | V52: 0 | Y52: 28/1/2025
A53: 47 | B53: 45658 | C53: Siemens Ltd. | D53: Nashik | E53: Tool | F53: Trilok Girhepumje | G53: 9850225626 | H53: trilok.girhepunje@siemens.com | I53: 12006597/001 | J53: SPP | K53: Yes | L53: KXIND/W/SPP/RV23-087 | M53: 14-12-2024 | N53: 0 | O53: January | P53: June | Q53: 0.3 | V53: 0 | W53: Project cancel | Z53: Yes
A54: 48 | B54: 45658 | C54: KSB Pumps LTD | D54: Nashik | E54: Store | F54: Dinkar Tarale | G54: 9960460637 | H54: dinkar.tarale@ksb.com | I54: 13004466/001 | J54: SPP | K54: Yes | L54: KXIND/W/SPP/RV23-088 | M54: 14-12-2024 | N54: 2775650 | O54: January | P54: June | Q54: 1 | R54: 4507448904 | S54: 25/3/2025 | T54: 2635917 | U54: March | V54: 0 | W54: Under discussion | Z54: Yes | AA54: Yes
A55: 49 | B55: 45658 | C55: ASB International | D55: Mumbai | E55: B85 | F55: Satish Kothavade | G55: 8898945871 | H55: satish.kothavade@nisseiasb.com | I55: 18000431/001 | J55: Contract | K55: No | L55: KXIND/W/MC/RV24-089 | M55: 17-12-2024 | N55: 0 | O55: January | P55: January | Q55: 1 | R55: ZPSC/6400001695 | S55: 26-12-2024 | T55: 0 | U55: January | V55: 0 | W55: Already booked in Dec-2024 | X55: Remove from offer sheet | Y55: 31/12/2024
A56: 50 | C56: ASB International | D56: Mumbai | E56: B85 | F56: Satish Kothavade | G56: 8898945871 | H56: satish.kothavade@nisseiasb.com | I56: 18000431/002 | J56: Contract | K56: No | L56: KXIND/W/MC/RV24-089 | M56: 17-12-2024 | N56: 0 | O56: January | P56: January | Q56: 1 | R56: ZPSC/6400001695 | S56: 26-12-2024 | T56: 0 | U56: January | V56: 0 | W56: Already booked in Dec-2024 | X56: Remove from offer sheet | Y56: 31/12/2024
A57: 51 | C57: ASB International | D57: Mumbai | E57: B85 | F57: Satish Kothavade | G57: 8898945871 | H57: satish.kothavade@nisseiasb.com | I57: 18002088/001 | J57: Contract | K57: No | L57: KXIND/W/MC/RV24-089 | M57: 17-12-2024 | N57: 0 | O57: January | P57: January | Q57: 1 | R57: ZPSC/6400001695 | S57: 26-12-2024 | T57: 0 | U57: January | V57: 0 | W57: Already booked in Dec-2024 | X57: Remove from offer sheet | Y57: 31/12/2024
A58: 52 | C58: ASB International | D58: Mumbai | E58: B85 | F58: Satish Kothavade | G58: 8898945871 | H58: satish.kothavade@nisseiasb.com | I58: 18000433/001 | J58: Contract | K58: No | L58: KXIND/W/MC/RV24-089 | M58: 17-12-2024 | N58: 0 | O58: January | P58: January | Q58: 1 | R58: ZPSC/6400001695 | S58: 26-12-2024 | T58: 0 | U58: January | V58: 0 | W58: Already booked in Dec-2024 | X58: Remove from offer sheet | Y58: 31/12/2024
A59: 53 | B59: 45658 | C59: ASB International | D59: Mumbai | E59: E9 | F59: Milind Kadam | G59: 9011049428 | H59: milind.kadam@nisseiasb.com | I59: 12005273/001 | J59: Contract | K59: No | L59: KXIND/W/MC/RV24-090 | M59: 17-12-2024 | N59: 0 | O59: January | P59: January | Q59: 1 | R59: ZPSC/4400012278 | S59: 26-12-2024 | T59: 0 | U59: January | V59: 0 | W59: Already booked in Dec-2024 | X59: Remove from offer sheet | Y59: 31/12/2024
A60: 54 | C60: ASB International | D60: Mumbai | E60: E9 | F60: Milind Kadam | G60: 9011049428 | H60: milind.kadam@nisseiasb.com | I60: 12005300/001 | J60: Contract | K60: No | L60: KXIND/W/MC/RV24-090 | M60: 17-12-2024 | N60: 0 | O60: January | P60: January | Q60: 1 | R60: ZPSC/4400012278 | S60: 26-12-2024 | T60: 0 | U60: January | V60: 0 | W60: Already booked in Dec-2024 | X60: Remove from offer sheet | Y60: 31/12/2024
A61: 55 | C61: ASB International | D61: Mumbai | E61: E9 | F61: Milind Kadam | G61: 9011049428 | H61: milind.kadam@nisseiasb.com | I61: 12005301/001 | J61: Contract | K61: No | L61: KXIND/W/MC/RV24-090 | M61: 17-12-2024 | N61: 0 | O61: January | P61: January | Q61: 1 | R61: ZPSC/4400012278 | S61: 26-12-2024 | T61: 0 | U61: January | V61: 0 | W61: Already booked in Dec-2024 | X61: Remove from offer sheet | Y61: 31/12/2024
A62: 56 | C62: ASB International | D62: Mumbai | E62: E9 | F62: Milind Kadam | G62: 9011049428 | H62: milind.kadam@nisseiasb.com | I62: 14000072/001 | J62: Contract | K62: No | L62: KXIND/W/MC/RV24-090 | M62: 17-12-2024 | N62: 0 | O62: January | P62: January | Q62: 1 | R62: ZPSC/4400012278 | S62: 26-12-2024 | T62: 0 | U62: January | V62: 0 | W62: Already booked in Dec-2024 | X62: Remove from offer sheet | Y62: 31/12/2024
A63: 57 | C63: ASB International | D63: Mumbai | E63: E9 | F63: Milind Kadam | G63: 9011049428 | H63: milind.kadam@nisseiasb.com | I63: 14000073/001 | J63: Contract | K63: No | L63: KXIND/W/MC/RV24-090 | M63: 17-12-2024 | N63: 0 | O63: January | P63: January | Q63: 1 | R63: ZPSC/4400012278 | S63: 26-12-2024 | T63: 0 | U63: January | V63: 0 | W63: Already booked in Dec-2024 | X63: Remove from offer sheet | Y63: 31/12/2024
A64: 58 | C64: ASB International | D64: Mumbai | E64: E9 | F64: Milind Kadam | G64: 9011049428 | H64: milind.kadam@nisseiasb.com | I64: 15008008/001 | J64: Contract | K64: No | L64: KXIND/W/MC/RV24-090 | M64: 17-12-2024 | N64: 0 | O64: January | P64: January | Q64: 1 | R64: ZPSC/4400012278 | S64: 26-12-2024 | T64: 0 | U64: January | V64: 0 | W64: Already booked in Dec-2024 | X64: Remove from offer sheet | Y64: 31/12/2024
A65: 59 | B65: 45658 | C65: Mylan Laboratories LTD | D65: Nashik | E65: QA | F65: Kiran Mapari | G65: 251674799 | H65: kiran.mapari@viatris.com | I65: 15003032/001 | J65: Midlife Upgrade | K65: Yes | L65: KXIND/W/MLU/RV24-061 | M65: 24-07-2024 | N65: 961935 | O65: January | P65: January | Q65: 1 | R65: 5700158957 | S65: 45608 | T65: 923457 | U65: January | V65: 0 | Y65: 30/01/2025 | Z65: yes | AA65: Yes
A66: 60 | B66: 45658 | C66: KSPG Automotive India PVT LTD | D66: Supa | F66: Baban Thube | G66: 7030676837 | H66: baban.thube@in.rheinmetall.com | J66: Contract | K66: Yes | L66: KXIND/W/MC/RV24-050 | M66: 45449 | N66: 89000 | O66: January | P66: January | Q66: 1 | R66: 4500082807 | S66: 45545 | T66: 80000 | U66: January | V66: 0 | Y66: 21/2/2025
A67: 61 | B67: 45658 | C67: Sandoz Pharmaciticals Ltd. | D67: Mumbai | F67: Nitin Sonar | G67: 9004040348 | H67: nitin.sonar@sandoz.com | I67: 06006939/001 | J67: Contract | K67: No | L67: KXIND/W/MC/RV24-058 | M67: 45511 | N67: 81000 | O67: January | P67: January | Q67: 1 | R67: 3006277654 | S67: 23-09-2025 | T67: 81000 | U67: January | V67: 0 | Y67: 45665
A68: 62 | B68: 45658 | C68: Siemens Ltd. | D68: Aurangabad | F68: Masngesh Masne | G68: 9096796959 | H68: mangesh.masne@siemens.com | I68: 10009903/001 | J68: Contract | K68: No | L68: KRIND/RV/MC/220025 | M68: 45658 | N68: 102168 | O68: January | P68: January | Q68: 1 | R68: 4511831616 | S68: 18-12-2022 | T68: 102168 | U68: January | V68: 0 | W68: Three Year AMC PO | X68: Yes
A69: 63 | C69: Siemens Ltd. | D69: Aurangabad | F69: Masngesh Masne | G69: 9096796959 | H69: mangesh.masne@siemens.com | I69: 10009904/001 | J69: Contract | K69: No | L69: KRIND/RV/MC/220025 | M69: 45658 | N69: 102168 | O69: January | P69: January | Q69: 1 | R69: 4511831616 | S69: 18-12-2022 | T69: 102168 | U69: January | V69: 0 | W69: Three Year AMC PO
A70: 64 | C70: Siemens Ltd. | D70: Aurangabad | F70: Masngesh Masne | G70: 9096796959 | H70: mangesh.masne@siemens.com | I70: 11007450/001 | J70: Contract | K70: No | L70: KRIND/RV/MC/220025 | M70: 45658 | N70: 102168 | O70: January | P70: January | Q70: 1 | R70: 4511831616 | S70: 18-12-2022 | T70: 102168 | U70: January | V70: 0 | W70: Three Year AMC PO
A71: 65 | B71: 45659 | C71: Mylan Laboratories LTD | D71: Aurangabad | F71: Sambhaji Sakare | G71: 8888800585 | H71: sambhaji.sakhare@viatris.com | I71: 20007338/001 | J71: Retrofit kit | K71: Yes | L71: KXIND/W/RF/RV25-001 | M71: 45659 | N71: 2346200 | O71: January | P71: March | Q71: 1 | R71: 4700032972 / 4501525565 | S71: 13/3/2025 | T71: 2350000 | U71: March | V71: 0 | W71: retrofit Kit and Installation PO received | Z71: Yes | AA71: Yes
A72: 66 | B72: 45659 | C72: Mylan Laboratories LTD | D72: Aurangabad | F72: Sambhaji Sakare | G72: 8888800585 | H72: sambhaji.sakhare@viatris.com | I72: 20007338/001 | J72: Retrofit kit | K72: Yes | L72: KXIND/W/RF/RV25-002 | M72: 45659 | N72: 292500 | O72: January | P72: April | Q72: 1 | R72: 4501525563 | S72: 13/03/2025 | T72: 292500 | U72: March | V72: 0 | W72: PO received
A73: 67 | B73: 45659 | C73: Bharat Bijlee Ltd | D73: Mumbai | F73: Sachin Lad | G73: 9326387581 | H73: sachin.lad@bharatbijlee.com | I73: 08005177/001 | J73: Contract | K73: No | L73: KXIND/W/MC/RV25-003 | M73: 45659 | N73: 68900 | O73: January | P73: February | Q73: 1 | R73: 6000057329 | S73: 18-01-2025 | T73: 66144 | U73: January | V73: 0
A74: 68 | C74: Bharat Bijlee Ltd | D74: Mumbai | F74: Sachin Lad | G74: 9326387581 | H74: sachin.lad@bharatbijlee.com | I74: 08005177/002 | J74: Contract | K74: No | L74: KXIND/W/MC/RV25-003 | M74: 45659 | N74: 68900 | O74: January | P74: February | Q74: 1 | R74: 6000057329 | S74: 18-01-2025 | T74: 66144 | U74: January | V74: 0
A75: 69 | C75: Bharat Bijlee Ltd | D75: Mumbai | F75: Sachin Lad | G75: 9326387581 | H75: sachin.lad@bharatbijlee.com | I75: 11001977/001 | J75: Contract | K75: No | L75: KXIND/W/MC/RV25-003 | M75: 45659 | N75: 68900 | O75: January | P75: February | Q75: 1 | R75: 6000057329 | S75: 18-01-2025 | T75: 66144 | U75: January | V75: 0
A76: 70 | C76: Bharat Bijlee Ltd | D76: Mumbai | F76: Sachin Lad | G76: 9326387581 | H76: sachin.lad@bharatbijlee.com | I76: 11001978/001 | J76: Contract | K76: No | L76: KXIND/W/MC/RV25-003 | M76: 45659 | N76: 68900 | O76: January | P76: February | Q76: 1 | R76: 6000057329 | S76: 18-01-2025 | T76: 66144 | U76: January | V76: 0
A77: 71 | B77: 45659 | C77: Bosch Ltd | D77: Nashik | E77: HR | F77: Rina Pagar | G77: 9823395295 | H77: rina.pagar@in.bosch.com | I77: 06009235/001 | J77: Contract | K77: No | L77: KXIND/W/MC/RV25-004 | M77: 45659 | N77: 73500 | O77: January | P77: March | Q77: 1 | R77: 85385903 | S77: 26/2/2025 | T77: 73500 | U77: February | V77: 0
A78: 72 | C78: Bosch Ltd | D78: Nashik | E78: Med | F78: Rina Pagar | G78: 9823395295 | H78: rina.pagar@in.bosch.com | I78: 101001594 | J78: Contract | K78: No | L78: KXIND/W/MC/RV25-004 | M78: 45659 | N78: 73500 | O78: January | P78: March | Q78: 1 | R78: 85385903 | S78: 26/2/2025 | T78: 73500 | U78: February | V78: 0
A79: 73 | B79: 45658 | C79: Siemens Ltd. | D79: Mumbai | E79: Motor | F79: Suraj Musmade | G79: 9422906585 | H79: suraj.musmade@siemens.com | I79: 06005996/001 | J79: Contract | K79: No | L79: KXIND/W/MC/RV25-005 | M79: 45659 | N79: 73063 | O79: January | P79: February | Q79: 1 | R79: 9708949653 | S79: 29-01-2025 | T79: 73063 | U79: January | V79: 0
A80: 74 | C80: Siemens Ltd. | D80: Mumbai | E80: Motor | F80: Suraj Musmade | G80: 9422906585 | H80: suraj.musmade@siemens.com | I80: 11010672/001 | J80: Contract | K80: No | L80: KXIND/W/MC/RV25-005 | M80: 45659 | N80: 73063 | O80: January | P80: February | Q80: 1 | R80: 9708949653 | S80: 29-01-2025 | T80: 73063 | U80: January | V80: 0
A81: 75 | C81: Siemens Ltd. | D81: Mumbai | E81: Motor | F81: Suraj Musmade | G81: 9422906585 | H81: suraj.musmade@siemens.com | I81: 11010675/001 | J81: Contract | K81: No | L81: KXIND/W/MC/RV25-005 | M81: 45659 | N81: 73063 | O81: January | P81: February | Q81: 1 | R81: 9708949653 | S81: 29-01-2025 | T81: 73063 | U81: January | V81: 0
A82: 76 | C82: Siemens Ltd. | D82: Mumbai | E82: Motor | F82: Suraj Musmade | G82: 9422906585 | H82: suraj.musmade@siemens.com | I82: 11004360/001 | J82: Contract | K82: No | L82: KXIND/W/MC/RV25-005 | M82: 45659 | N82: 73063 | O82: January | P82: February | Q82: 1 | R82: 9708949653 | S82: 29-01-2025 | T82: 73063 | U82: January | V82: 0
A83: 77 | B83: 45668 | C83: Siemens Ltd. | D83: Aurangabad | F83: Masngesh Masne | G83: 9096796959 | H83: mangesh.masne@siemens.com | I83: 10009903/001 | J83: SPP | K83: Yes | L83: KXIND/W/SPP/RV25-006 | M83: 45668 | N83: 256700 | O83: January | P83: March | Q83: 1 | R83: 9709012590 | S83: 27/2/2025 | T83: 246432 | U83: February | V83: 0
A84: 78 | B84: 23/1/2025 | C84: Rishabh Instruments LTD | D84: Nashik | F84: Sunil Patil | G84: 9623101254 | H84: sunil.patil@rishabh.co.in | I84: 01005521/001 | J84: Relocation | K84: No | L84: KXIND/W/RE/RV25-007 | M84: 23-01-2025 | N84: 0 | O84: January | P84: April | Q84: 0.3 | V84: 0 | W84: Project cancel
A85: 79 | B85: 23/1/2025 | C85: Rishabh Instruments LTD | D85: Nashik | F85: Sunil Patil | G85: 9623101254 | H85: sunil.patil@rishabh.co.in | I85: 98001536/001 | J85: Midlife Upgrade | K85: Yes | L85: KXIND/W/MLU/RV25-008 | M85: 23-01-2025 | N85: 1759910 | O85: January | P85: June | Q85: 1 | R85: 4250001498 | S85: 23/3/2025 | T85: 1636717 | U85: March | V85: 0 | Z85: Yes | AA85: Yes
A86: 80 | B86: 27/1/2025 | C86: Bosch Ltd | D86: Nashik | F86: Renuka Navander | G86: 9595134464 | H86: renuka.navandar@in.bosch.com | J86: spp | K86: Yes | L86: repeat order | M86: 27-01-2025 | N86: 22776 | O86: January | P86: February | Q86: 1 | R86: POE 49245879 - YQL | S86: 27-01-2025 | T86: 22776 | U86: January | V86: 0 | Y86: 13/2/2025
A87: 81 | B87: 28/1/2025 | C87: Bajaj Auto Ltd | D87: Aurangabad | F87: Chandrashekhar Pathak | G87: 7757057351 | H87: cspathak@bajajauto.co.in | I87: 14002435/001 | J87: Midlife Upgrade | K87: Yes | L87: KXIND/W/MLU/RV25-009 | M87: 28-01-2025 | N87: 610160 | O87: January | P87: March | Q87: 1 | R87: 5210057069 and 5210057405 | S87: 28/1/2025 | T87: 432566 | U87: January | V87: 0 | Z87: Yes | AA87: Yes
A88: 82 | B88: 28/1/2025 | C88: ASB International | D88: Mumbai | F88: Milind Kadam | G88: 9011049428 | H88: milind.kadam@nisseiasb.com | I88: 12005273/001 | J88: Midlife Upgrade | K88: Yes | L88: KXIND/W/MLU/RV25-010 | M88: 28-01-2025 | N88: 1185738 | O88: January | P88: April | Q88: 1 | R88: ZPML/3600009997 | S88: 16/4/2025 | T88: 650697 | U88: April | V88: 0 | Z88: Yes | AA88: Yes
A89: 83 | B89: 45700 | C89: Mahindra & Mahindra LTD | D89: Mumbai | F89: Durvesh Phopale | G89: 8879743946 | H89: Phopale.durvesh@mahindra.com | I89: 17001696/001 | J89: BD Spare | K89: No | L89: KXIND/W/SPP/RV25-011 | M89: 45700 | N89: 45900 | O89: February | P89: March | Q89: 1 | R89: ARP/3800306985 | S89: 18/2/2025 | T89: 45900 | U89: February | V89: 0 | Y89: 21/2/2025
A90: 84 | B90: 45700 | C90: Mahindra & Mahindra LTD | D90: Mumbai | F90: Durvesh Phopale | G90: 8879743946 | H90: Phopale.durvesh@mahindra.com | I90: 17001696/001 | J90: BD Charges | K90: No | L90: KXIND/W/SR/RV25-012 | M90: 45700 | N90: 0 | O90: February | P90: March | Q90: 0.4 | V90: 0 | W90: Cancel customer solved the problem
A91: 85 | B91: 45700 | C91: Mylan Laboratories LTD | D91: Nashik | F91: Kiran Mapari | G91: 251674799 | H91: kiran.mapari@viatris.com | I91: 18005565/002 | J91: BD Spare | K91: no | L91: repeat Order | M91: 45700 | N91: 100000 | O91: February | P91: February | Q91: 1 | R91: 4501289944 | S91: 45700 | T91: 100000 | U91: February | V91: 0 | Y91: 45700
A92: 86 | B92: 21/2/2025 | C92: Epiroc Mining India Ltd (Atlas) | D92: Nashik | F92: Nisha Solanki | G92: 7030919035 | H92: nisha.solanki@epiroc.com | I92: 11008208/001 | J92: Midlife Upgrade | K92: Yes | L92: KXIND/W/MLU/RV25-013 | M92: 21/2/2025 | N92: 5183082 | O92: February | P92: May | Q92: 1 | R92: 2500237815 | S92: 15/5/2025 | T92: 989363 | U92: May | V92: 0 | W92: Spare price for one year rate contract | Z92: Yes | AA92: Yes
A93: 87 | B93: 21/2/2025 | C93: ABB India Ltd | D93: Nashik | F93: Mayur Aswale | G93: 8788392320 | H93: mayur.aswale@in.abb.com | I93: 06006180/001 | J93: Midlife Upgrade | K93: Yes | L93: KXIND/W/MLU/RV25-014 | M93: 21/2/2025 | N93: 839270 | O93: February | P93: July | Q93: 1 | R93: 3091040975 | S93: 13/6/2025 | T93: 460161 | U93: June | V93: 0 | W93: under discussion | Z93: Yes | AA93: yes
A94: 88 | B94: 45717 | C94: KSB Pumps LTD | D94: Nashik | F94: Dinkar Tarale | G94: 9960460637 | H94: dinkar.tarale@ksb.com | I94: 11007580/001 | J94: Midlife Upgrade | K94: Yes | L94: KXIND/W/MLU/RV25-015 | M94: 45717 | N94: 1137252 | O94: March | P94: April | Q94: 1 | R94: 4507499727 | S94: 28/4/2025 | T94: 802287 | U94: April | V94: 0 | Z94: Yes | AA94: Yes
A95: 89 | B95: 45726 | C95: ABB India Ltd | D95: Nashik | F95: Chandrakant Rule | G95: 9860892180 | H95: chandrakant.rule@in.abb.com | I95: 07004576/001 | J95: SPP | K95: Yes | L95: KXIND/W/SPP/RV25-016 | M95: 45726 | N95: 0 | O95: March | P95: June | Q95: 0.4 | V95: 0 | W95: Custome Repair spare part
A96: 90 | B96: 15/3/2025 | C96: Bosch Ltd | D96: Nashik | F96: Harsha Daswani | G96: 9607001672 | H96: harsha.daswani@in.bosch.com | I96: 05007890/001 | J96: Midlife Upgrade | K96: Yes | L96: KXIND/W/MLU/RV25-017 | M96: 15/3/2025 | N96: 625800 | O96: March | P96: December | Q96: 0.3 | V96: 625800 | Z96: Yes
A97: 91 | B97: 18/3/2025 | C97: ABB India Ltd | D97: Nashik | F97: Mayur Aswale | G97: 8788392320 | H97: mayur.aswale@in.abb.com | I97: 06006180/001 | J97: Contract | K97: No | L97: KXIND/W/MC/RV25-018 | M97: 18/3/2025 | N97: 61500 | O97: March | P97: April | Q97: 1 | R97: 3791227950 | S97: 23/04/2025 | T97: 61500 | U97: April | V97: 0
A98: 92 | B98: 18/3/2025 | C98: BLUESTAR | D98: Mumbai | F98: Pravin Jaiswal | G98: 8669908679 | H98: praveenjaiswal@bluestarindia.com | I98: 18000191/001 | J98: Contract | K98: No | L98: KXIND/W/MC/RV25-0019 | M98: 18/3/2025 | N98: 83000 | O98: March | P98: April | Q98: 1 | R98: 5000132738 | S98: 22/4/2025 | T98: 83000 | U98: April | V98: 0
A99: 93 | B99: 19/3/2025 | C99: Rishabh Instruments LTD | D99: Nashik | F99: Sunil Patil | G99: 9623101254 | H99: sunil.patil@rishabh.co.in | I99: 01005521/001 | J99: Contract | K99: No | L99: KXIND/W/MC/RV25-0020 | M99: 19/3/2025 | N99: 75900 | O99: March | P99: June | Q99: 1 | R99: 4220019956 | S99: 25/5/2026 | T99: 72864 | U99: May | V99: 0
A100: 94 | C100: Rishabh Instruments LTD | D100: Nashik | F100: Sunil Patil | G100: 9623101254 | H100: sunil.patil@rishabh.co.in | I100: 98001536/001 | J100: Contract | K100: No | L100: KXIND/W/MC/RV25-0020 | M100: 19/3/2025 | N100: 75900 | O100: March | P100: June | Q100: 1 | R100: 4220019956 | S100: 25/5/2026 | T100: 72864 | U100: May | V100: 0
...

Sheet Minesh
AB1: Month wise data
A2: KARDEX INDIA - LIVE OFFER FUNEL - MINESH - WEST | AB2: Month | AC2: Offers Total | AD2: Order Received | AE2: Forecast | AF2: Forecast- Po Received
U3: Total Offered Value | V3: =SUM(N7:N402) -> 30588261 | AB3: January | AC3: =SUMIF($O$7:$O$402,"January",$N$7:$N$402) -> 6579745 | AD3: =SUMIF($U$7:$U$402,"January",$T$7:$T$402) -> 4361918 | AE3: =SUMIF($P$7:$P$428,"January",$N$7:$N$428) -> 4465110 | AF3: =AE3-AD3 -> 103192
A4: Total Offers | B4: =COUNTA(B7:B1424) -> 113 | U4: Order Received | V4: =SUM(T7:T402) -> 21310721 | AB4: February | AC4: =SUMIF($O$7:$O$402,"February",$N$7:$N$402) -> 290000 | AD4: =SUMIF($U$7:$U$402,"February",$T$7:$T$402) -> 1491040 | AE4: =SUMIF($P$7:$P$428,"February",$N$7:$N$428) -> 1534165 | AF4: =AE4-AD4 -> 43125
U5: Open Funnel | V5: =SUM(V7:V402) -> 4608300 | Y5: * Updated by Girija | AB5: March | AC5: =SUMIF($O$7:$O$402,"March",$N$7:$N$402) -> 3483840 | AD5: =SUMIF($U$7:$U$402,"March",$T$7:$T$402) -> 666040 | AE5: =SUMIF($P$7:$P$428,"March",$N$7:$N$428) -> 405650 | AF5: =AE5-AD5 -> -260390
A6: SL | B6: Reg Date | C6: Company | D6: Location | E6: Department | F6: Contact Person Name | G6: Contact Number | H6: E-Mail ID | I6: Machine Serial Number | J6: Product Type | K6: Lead | L6: Offer Reference Number | M6: Offer Reference Date | N6: Offer Value | O6: Offer Month | P6: PO Expected Month | Q6: Probabality in Percentage | R6: PO Number | S6: PO Date | T6: PO Value | U6: PO Received Month | V6: Open Funnel | W6: Remarks | X6: Status | Y6: Booking Date in SAP B1 | Z6: Offer Updated in CRM | AA6: Offer closed in CRM | AB6: April | AC6: =SUMIF($O$7:$O$402,"April",$N$7:$N$402) -> 3188580 | AD6: =SUMIF($U$7:$U$402,"April",$T$7:$T$402) -> 2496685 | AE6: =SUMIF($P$7:$P$428,"April",$N$7:$N$428) -> 2936340 | AF6: =AE6-AD6 -> 439655
A7: 1 | B7: 45901 | C7: Kabra Extrusiontechnik Ltd | D7: Daman | E7: Maintenance | F7: Krunal patel | G7: 7226982211 | H7: krunal.patel@kolsitegroup.com | I7: 10007235/001 | J7: Contract | K7: No | L7: KXIND/W/MV/MC/24085 | M7: 45575 | N7: 85560 | O7: January | P7: January | Q7: 1 | R7: 4900003319 | S7: 45588 | T7: 85560 | U7: January | V7: =Table62689345679[[#This Row],[Offer Value]]-Table62689345679[[#This Row],[PO Value]] -> 0 | Y7: 31/1/2025 | AB7: May | AC7: =SUMIF($O$7:$O$402,"May",$N$7:$N$402) -> 2088450 | AD7: =SUMIF($U$7:$U$402,"May",$T$7:$T$402) -> 2314237 | AE7: =SUMIF($P$7:$P$428,"May",$N$7:$N$428) -> 2524790 | AF7: =AE7-AD7 -> 210553
A8: 2 | B8: 45901 | C8: Firmenich Aerometics I Pvt.ltd. | D8: Daman | E8: QA | F8: Niteshkumar Patel | G8: 9033953449 | H8: Niteshkumar.PATEL@dsm-firmenich.com | I8: 18001930/001 | J8: Contract | K8: NO | L8: KXIND/W/MV/MC/24102 | M8: 45639 | N8: 58000 | O8: January | P8: January | Q8: 1 | R8: 3001011375 - | S8: 45642 | T8: 58000 | U8: January | V8: =Table62689345679[[#This Row],[Offer Value]]-Table62689345679[[#This Row],[PO Value]] -> 0 | W8: Already booked in Dec-25 remove from offer funnel | Y8: 31/12/2204 | AB8: June | AC8: =SUMIF($O$7:$O$402,"June",$N$7:$N$402) -> 423600 | AD8: =SUMIF($U$7:$U$402,"June",$T$7:$T$402) -> 1813295 | AE8: =SUMIF($P$7:$P$428,"June",$N$7:$N$428) -> 2174860 | AF8: =AE8-AD8 -> 361565
C9: Firmenich Aerometics I Pvt.ltd. | D9: Daman | E9: QA | F9: Niteshkumar Patel | G9: 9033953449 | H9: Niteshkumar.PATEL@dsm-firmenich.com | I9: 18001930/002 | J9: Contract | K9: NO | L9: KXIND/W/MV/MC/24102 | M9: 45639 | N9: 58000 | O9: January | P9: January | Q9: 1 | R9: 3001011375 - | S9: 45642 | T9: 58000 | U9: January | V9: =Table62689345679[[#This Row],[Offer Value]]-Table62689345679[[#This Row],[PO Value]] -> 0 | W9: Already booked in Dec-25 remove from offer funnel | Y9: 31/12/2204 | AB9: July | AC9: =SUMIF($O$7:$O$402,"July",$N$7:$N$402) -> 3804436 | AD9: =SUMIF($U$7:$U$402,"July",$T$7:$T$402) -> 200800 | AE9: =SUMIF($P$7:$P$428,"July",$N$7:$N$428) -> 129000 | AF9: =AE9-AD9 -> -71800
C10: Firmenich Aerometics I Pvt.ltd. | D10: Daman | E10: QA | F10: Niteshkumar Patel | G10: 9033953449 | H10: Niteshkumar.PATEL@dsm-firmenich.com | I10: 18001930/003 | J10: Contract | K10: NO | L10: KXIND/W/MV/MC/24102 | M10: 45639 | N10: 58000 | O10: January | P10: January | Q10: 1 | R10: 3001011375 - | S10: 45642 | T10: 58000 | U10: January | V10: =Table62689345679[[#This Row],[Offer Value]]-Table62689345679[[#This Row],[PO Value]] -> 0 | W10: Already booked in Dec-25 remove from offer funnel | Y10: 31/12/2204 | AB10: August | AC10: =SUMIF($O$7:$O$402,"August",$N$7:$N$402) -> 2520990 | AD10: =SUMIF($U$7:$U$402,"August",$T$7:$T$402) -> 1965162 | AE10: =SUMIF($P$7:$P$428,"August",$N$7:$N$428) -> 4429476 | AF10: =AE10-AD10 -> 2464314
A11: 3 | B11: 45901 | C11: Cello Household Products | D11: Daman | E11: Production | F11: Rakesh Shah | G11: 9377283473 | H11: rakesh.shah@celloworld.com | I11: 16004134/001 | J11: Contract | K11: No | L11: KXIND/W/MV/MC/24086 | M11: 45575 | N11: 85500 | O11: January | Q11: 0.5 | V11: =Table62689345679[[#This Row],[Offer Value]]-Table62689345679[[#This Row],[PO Value]] -> 85500 | AB11: September | AC11: =SUMIF($O$7:$O$402,"September",$N$7:$N$402) -> 1714900 | AD11: =SUMIF($U$7:$U$402,"September",$T$7:$T$402) -> 1369223 | AE11: =SUMIF($P$7:$P$428,"September",$N$7:$N$428) -> 2696450 | AF11: =AE11-AD11 -> 1327227
A12: 4 | B12: 45901 | C12: Jaiko Industries Ltd | D12: Ankleshwar | E12: Plant Head | F12: Vinod Mahajan | G12: 9426806524 | H12: jaikoindustries2011@gmail.com | I12: 10007105/001 | J12: Contract | K12: No | L12: KXIND/W/MV/MC/24087 | M12: 45575 | N12: 86000 | O12: January | P12: January | Q12: 1 | R12: P240771 | S12: 45362 | T12: 86000 | U12: January | V12: =Table62689345679[[#This Row],[Offer Value]]-Table62689345679[[#This Row],[PO Value]] -> 0 | AB12: October | AC12: =SUMIF($O$7:$O$402,"October",$N$7:$N$402) -> 3875820 | AD12: =SUMIF($U$7:$U$402,"October",$T$7:$T$402) -> 3303797 | AE12: =SUMIF($P$7:$P$428,"October",$N$7:$N$428) -> 2755540 | AF12: =AE12-AD12 -> -548257
A13: 5 | B13: 45901 | C13: JP Extrusiontech Ltd | D13: Ankleshwar | E13: Purchase | F13: Asish Biswas | G13: 9924214600 | H13: purchase@jpel.in | I13: 13000085/001 | J13: Contract | K13: No | L13: KXIND/W/MV/MC/24072 | M13: 45534 | N13: 86000 | O13: January | P13: January | Q13: 1 | R13: P2401770 | S13: 45362 | T13: 86000 | U13: January | V13: =Table62689345679[[#This Row],[Offer Value]]-Table62689345679[[#This Row],[PO Value]] -> 0 | Y13: 45810 | AB13: November | AC13: =SUMIF($O$7:$O$402,"November",$N$7:$N$402) -> 1175400 | AD13: =SUMIF($U$7:$U$402,"November",$T$7:$T$402) -> 507710 | AE13: =SUMIF($P$7:$P$428,"November",$N$7:$N$428) -> 1000130 | AF13: =AE13-AD13 -> 492420
A14: 6 | B14: 45901 | C14: Turbo Energy Pvt Ltd | D14: Vadodara | E14: Maintenance | F14: Mr. Kabilan | G14: 8072231531 | H14: TEV_Utility@turboenergy.co.in | I14: 18001203/001 | J14: Contract | K14: NO | L14: KXIND/W/MV/MC/24103 | M14: 45639 | N14: 86000 | O14: January | P14: January | Q14: 1 | R14: 6800045052 | S14: 45839 | T14: 86000 | U14: January | V14: =Table62689345679[[#This Row],[Offer Value]]-Table62689345679[[#This Row],[PO Value]] -> 0 | Y14: 17/2/2025 | AB14: December | AC14: =SUMIF($O$7:$O$402,"December",$N$7:$N$402) -> 1442500 | AD14: =SUMIF($U$7:$U$402,"December",$T$7:$T$402) -> 820814 | AE14: =SUMIF($P$7:$P$428,"December",$N$7:$N$428) -> 3204850 | AF14: =AE14-AD14 -> 2384036
A15: 7 | B15: 45901 | C15: Hero Moto Corp Ltd. | D15: Vadodara | E15: Maitenance | F15: Rutvik Joshi | G15: 9974002322 | H15: rutviksanjay.joshi@heromotocorp.com | I15: 15006703/001 | J15: Contract | K15: No | L15: KXIND/W/MV/MC/24075 | M15: 45534 | N15: 85000 | O15: January | P15: January | Q15: 1 | R15: 2710000006 | S15: 45574 | T15: 85000 | U15: January | V15: =Table62689345679[[#This Row],[Offer Value]]-Table62689345679[[#This Row],[PO Value]] -> 0
C16: Hero Moto Corp Ltd. | D16: Vadodara | E16: Maitenance | F16: Rutvik Joshi | G16: 9974002322 | H16: rutviksanjay.joshi@heromotocorp.com | I16: 15006703/002 | J16: Contract | K16: No | L16: KXIND/W/MV/MC/24075 | M16: 45534 | N16: 85000 | O16: January | P16: January | Q16: 1 | R16: 2710000006 | S16: 45574 | T16: 85000 | U16: January | V16: =Table62689345679[[#This Row],[Offer Value]]-Table62689345679[[#This Row],[PO Value]] -> 0
A17: 8 | B17: 45689 | C17: Rotomotive Powerdrives India Ltd | D17: Anand | E17: Production | F17: Hitesh Patel | G17: 9824637297 | H17: prod-gbx@rotomotive.com | I17: 11008006/001 | J17: Relocation | K17: No | L17: KXIND/W/MV/RE/25001 | M17: 45689 | N17: 350000 | O17: January | P17: February | Q17: 1 | R17: PO/24/05048 | S17: 28/01/2025 | T17: 322000 | U17: February | V17: 0
A18: 9 | B18: 45901 | C18: Elecon Engg Co Ltd | D18: Anand | E18: Maintenance | F18: Darshan Upadhyay | G18: 9723071561 | H18: daupadhyay@akaaish.com | I18: 03007902/001 | J18: SPP | K18: NO | L18: KXIND/W/MV/SPP/24100 | M18: 45639 | N18: 45200 | O18: January | P18: January | Q18: 1 | R18: 659391/0 | S18: 45652 | T18: 43392 | U18: January | V18: 0 | Y18: 30/1/2025
A19: 10 | B19: 45870 | C19: Elecon Engg Co Ltd | D19: Anand | E19: Purchase | F19: Gawrang Soni | G19: 8160147583 | H19: gjsoni@elecon.com | I19: 03007902/001 | J19: SPP | K19: Yes | L19: KXIND/W/MV/SPP/25002 | M19: 45870 | N19: 83000 | O19: January | P19: January | Q19: 1 | R19: 661955/0 | S19: 45870 | T19: 83000 | U19: January | V19: =Table62689345679[[#This Row],[Offer Value]]-Table62689345679[[#This Row],[PO Value]] -> 0 | Y19: 16/1/2025
A20: 11 | B20: 45901 | C20: Power Build Ltd | D20: Anand | E20: Maitenance | F20: Alpesh J.Thakkar | G20: 98795 07642 | H20: ajthakkar@akaaish.com | I20: 02002802/001 | J20: SPP | K20: Yes | L20: KXIND/W/MV/MLU/24090 | M20: 45588 | N20: 927200 | O20: January | P20: January | Q20: 1 | R20: 2411048818/0 | S20: 45611 | T20: 853024 | U20: January | V20: 0 | Y20: 16/1/2025 | Z20: yes | AA20: yes
A21: 12 | B21: 45901 | C21: KHS Machinery Pvt Ltd | D21: Ahmadabad | E21: Maintenance | F21: Biresh Banerjee | G21: 9898646272 | H21: Biresh.Banerjee@khs.com | I21: 06007041/001 | J21: Contract | K21: NO | L21: KXIND/W/MV/MC/24104 | M21: 45639 | N21: 52500 | O21: January | P21: January | Q21: 1 | R21: 91029375 - | S21: 45640 | T21: 52500 | U21: January | V21: =Table62689345679[[#This Row],[Offer Value]]-Table62689345679[[#This Row],[PO Value]] -> 0 | W21: Already booked in Dec-25 remove from offer funnel | Y21: 31/12/2024
C22: KHS Machinery Pvt Ltd | D22: Ahmadabad | E22: Maintenance | F22: Biresh Banerjee | G22: 9898646272 | H22: Biresh.Banerjee@khs.com | I22: 06007041/002 | J22: Contract | K22: NO | L22: KXIND/W/MV/MC/24104 | M22: 45639 | N22: 52500 | O22: January | P22: January | Q22: 1 | R22: 91029375 - | S22: 45640 | T22: 52500 | U22: January | V22: =Table62689345679[[#This Row],[Offer Value]]-Table62689345679[[#This Row],[PO Value]] -> 0 | W22: Already booked in Dec-25 remove from offer funnel | Y22: 31/12/2024
C23: KHS Machinery Pvt Ltd | D23: Ahmadabad | E23: Maintenance | F23: Biresh Banerjee | G23: 9898646272 | H23: Biresh.Banerjee@khs.com | I23: 06007041/003 | J23: Contract | K23: NO | L23: KXIND/W/MV/MC/24104 | M23: 45639 | N23: 52500 | O23: January | P23: January | Q23: 1 | R23: 91029375 - | S23: 45640 | T23: 52500 | U23: January | V23: =Table62689345679[[#This Row],[Offer Value]]-Table62689345679[[#This Row],[PO Value]] -> 0 | W23: Already booked in Dec-25 remove from offer funnel | Y23: 31/12/2024
C24: KHS Machinery Pvt Ltd | D24: Ahmadabad | E24: Maintenance | F24: Biresh Banerjee | G24: 9898646272 | H24: Biresh.Banerjee@khs.com | I24: 06007041/004 | J24: Contract | K24: NO | L24: KXIND/W/MV/MC/24104 | M24: 45639 | N24: 52500 | O24: January | P24: January | Q24: 1 | R24: 91029375 - | S24: 45640 | T24: 52500 | U24: January | V24: =Table62689345679[[#This Row],[Offer Value]]-Table62689345679[[#This Row],[PO Value]] -> 0 | W24: Already booked in Dec-25 remove from offer funnel | Y24: 31/12/2024
C25: KHS Machinery Pvt Ltd | D25: Ahmadabad | E25: Maintenance | F25: Biresh Banerjee | G25: 9898646272 | H25: Biresh.Banerjee@khs.com | I25: 06007041/005 | J25: Contract | K25: NO | L25: KXIND/W/MV/MC/24104 | M25: 45639 | N25: 52500 | O25: January | P25: January | Q25: 1 | R25: 91029375 - | S25: 45640 | T25: 52500 | U25: January | V25: =Table62689345679[[#This Row],[Offer Value]]-Table62689345679[[#This Row],[PO Value]] -> 0 | W25: Already booked in Dec-25 remove from offer funnel | Y25: 31/12/2024
A26: 13 | B26: 45901 | C26: Ferromatik Milacron India Ltd (Milacron India Pvt ltd) | D26: Ahmadabad | E26: Maintenance | F26: Kalpesh Panchal | G26: 9722013361 | H26: Kalpesh_Panchal@milacron.com | I26: 11002444/001 | J26: Contract | K26: No | L26: KXIND/W/MV/MC/24094 - R1 | M26: 45681 | N26: 53000 | O26: January | P26: January | Q26: 1 | R26: 30010283/O2/24152993 | S26: 45686 | T26: 53000 | U26: January | V26: =Table62689345679[[#This Row],[Offer Value]]-Table62689345679[[#This Row],[PO Value]] -> 0
C27: Ferromatik Milacron India Ltd (Milacron India Pvt ltd) | D27: Ahmadabad | E27: Maintenance | F27: Kalpesh Panchal | G27: 9722013361 | H27: Kalpesh_Panchal@milacron.com | I27: 11002457/001 | J27: Contract | K27: No | L27: KXIND/W/MV/MC/24094 - R1 | M27: 45681 | N27: 53000 | O27: January | P27: January | Q27: 1 | R27: 30010283/O2/24152993 | S27: 45686 | T27: 53000 | U27: January | V27: =Table62689345679[[#This Row],[Offer Value]]-Table62689345679[[#This Row],[PO Value]] -> 0
C28: Ferromatik Milacron India Ltd (Milacron India Pvt ltd) | D28: Ahmadabad | E28: Maintenance | F28: Kalpesh Panchal | G28: 9722013361 | H28: Kalpesh_Panchal@milacron.com | I28: 10003923/001 | J28: Contract | K28: No | L28: KXIND/W/MV/MC/24094 - R1 | M28: 45681 | N28: 53000 | O28: January | P28: January | Q28: 1 | R28: 30010283/O2/24152993 | S28: 45686 | T28: 53000 | U28: January | V28: =Table62689345679[[#This Row],[Offer Value]]-Table62689345679[[#This Row],[PO Value]] -> 0
A29: 14 | B29: 45901 | C29: Prashant Ferber Logistics Automation Pvt Ltd (Prashant Gamatex Pvt Ltd) | D29: Ahmadabad | E29: Purchase | F29: Ghanshyam Borse | G29: 7874699823 | H29: c-purchase@prashantgroup.com | I29: 12006388/001 | J29: Contract | K29: NO | L29: KXIND/W/MV/MC/24084 | M29: 45575 | N29: 52800 | O29: January | P29: January | Q29: 1 | R29: SERVICE/30 | S29: 45394 | T29: 52800 | U29: January | V29: =Table62689345679[[#This Row],[Offer Value]]-Table62689345679[[#This Row],[PO Value]] -> 0 | Y29: 45840
A30: 15 | B30: 45901 | C30: Truetzschler India Pvt Ltd | D30: Ahmadabad | E30: Maintenance | F30: Arun Kavta | G30: 7046372509 | H30: ankavta@truetzschler.in | I30: 18001462/001 | J30: Contract | K30: No | L30: KXIND/W/MV/MC/24098 | M30: 45623 | V30: =Table62689345679[[#This Row],[Offer Value]]-Table62689345679[[#This Row],[PO Value]] -> 0
A31: 16 | B31: 45901 | C31: Truetzschler India Pvt Ltd | D31: Ahmadabad | E31: Maintenance | F31: Arun Kavta | G31: 7046372509 | H31: ankavta@truetzschler.in | I31: 11001979/001 | J31: Relocation | K31: No | L31: KXIND/W/MV/RE/24099 – R1 | M31: 45640 | N31: 370000 | O31: January | P31: January | Q31: 1 | R31: P2406119 | S31: 45651 | T31: 370000 | U31: January | V31: =Table62689345679[[#This Row],[Offer Value]]-Table62689345679[[#This Row],[PO Value]] -> 0 | Y31: 30/1/2025
C32: Truetzschler India Pvt Ltd | D32: Ahmadabad | E32: Maintenance | F32: Arun Kavta | G32: 7046372509 | H32: ankavta@truetzschler.in | I32: 11001980/001 | J32: Relocation | K32: No | L32: KXIND/W/MV/RE/24099 – R1 | M32: 45640 | N32: 370000 | O32: January | P32: January | Q32: 1 | R32: P2406119 | S32: 45651 | T32: 370000 | U32: January | V32: =Table62689345679[[#This Row],[Offer Value]]-Table62689345679[[#This Row],[PO Value]] -> 0 | Y32: 30/1/2025
C33: Truetzschler India Pvt Ltd | D33: Ahmadabad | E33: Maintenance | F33: Arun Kavta | G33: 7046372509 | H33: ankavta@truetzschler.in | I33: 18001462/001 | J33: Relocation | K33: No | L33: KXIND/W/MV/RE/24099 – R1 | M33: 45640 | N33: 370000 | O33: January | P33: January | Q33: 1 | R33: P2406119 | S33: 45651 | T33: 370000 | U33: January | V33: =Table62689345679[[#This Row],[Offer Value]]-Table62689345679[[#This Row],[PO Value]] -> 0 | Y33: 30/1/2025
A34: 17 | B34: 45901 | C34: Innovatec India Pvt ltd | D34: Ahmadabad | E34: Production | F34: Prasanna Manogaran | G34: 8939560604 | H34: prasanna.manogaran@fermator.com | I34: 21008408/001 | J34: Contract | K34: Yes | L34: KXIND/W/MV/MC/24083 | M34: 45556 | N34: 90000 | O34: January | P34: June | Q34: 1 | R34: 2025/67 | S34: 14/04/2025 | T34: 90000 | U34: May | V34: =Table62689345679[[#This Row],[Offer Value]]-Table62689345679[[#This Row],[PO Value]] -> 0
A35: 18 | B35: 45901 | C35: Kirloskar brothers LTD | D35: sanand | E35: Maitenance | F35: Hiren Patel | G35: 7624008077 | H35: Hirenkumar.Patel@kbl.co.in | I35: 17001433/003 | J35: Contract | K35: Yes | L35: KXIND/W/MV/MC/24073 | M35: 45534 | N35: 71250 | O35: January | P35: January | Q35: 1 | R35: 1600029226 - | S35: 45580 | T35: 71250 | U35: January | V35: =Table62689345679[[#This Row],[Offer Value]]-Table62689345679[[#This Row],[PO Value]] -> 0 | Y35: 23/1/2025
A36: 19 | B36: 45901 | C36: Nayara Energy Ltd. | D36: Dwarka | E36: Manager | F36: Arvind Jadeja | G36: 9825207929 | H36: Arvindsinh.jadeja@nayaraenergy.com | I36: 18009095/001 | J36: Contract | K36: No | L36: KXIND/W/MV/MC/24054 | M36: 45357 | N36: 98000 | O36: January | P36: January | Q36: 1 | R36: 5300005783 | S36: 45467 | T36: 98000 | U36: January | V36: =Table62689345679[[#This Row],[Offer Value]]-Table62689345679[[#This Row],[PO Value]] -> 0 | W36: we have received PO for 3 years contract (2025 to 2027 @ INR 98000 / machine / year
C37: Nayara Energy Ltd. | D37: Dwarka | E37: Manager | F37: Arvind Jadeja | G37: 9825207929 | H37: Arvindsinh.jadeja@nayaraenergy.com | I37: 18009095/002 | J37: Contract | K37: No | L37: KXIND/W/MV/MC/24054 | M37: 45357 | N37: 98000 | O37: January | P37: January | Q37: 1 | R37: 5300005783 | S37: 45467 | T37: 98000 | U37: January | V37: =Table62689345679[[#This Row],[Offer Value]]-Table62689345679[[#This Row],[PO Value]] -> 0 | W37: we have received PO for 3 years contract (2025 to 2027 @ INR 98000 / machine / year
C38: Nayara Energy Ltd. | D38: Dwarka | E38: Manager | F38: Arvind Jadeja | G38: 9825207929 | H38: Arvindsinh.jadeja@nayaraenergy.com | I38: 18009095/003 | J38: Contract | K38: No | L38: KXIND/W/MV/MC/24054 | M38: 45357 | N38: 98000 | O38: January | P38: January | Q38: 1 | R38: 5300005783 | S38: 45467 | T38: 98000 | U38: January | V38: =Table62689345679[[#This Row],[Offer Value]]-Table62689345679[[#This Row],[PO Value]] -> 0 | W38: we have received PO for 3 years contract (2025 to 2027 @ INR 98000 / machine / year
A39: 20 | B39: 45901 | C39: Grundfos Pumps India Pvt Ltd | D39: Ahmadabad | E39: Maintenance | F39: Govind Rajput | G39: 8469867330 | H39: rajput@grundfos.com | I39: 16006392/001 | J39: Contract | K39: No | L39: KXIND/W/MV/MC/24106 | M39: 45641 | N39: 77200 | O39: January | P39: January | Q39: 1 | R39: 4516924874 | S39: 45717 | T39: 77200 | U39: January | V39: =Table62689345679[[#This Row],[Offer Value]]-Table62689345679[[#This Row],[PO Value]] -> 0 | W39: we have received PO for 2 years contract @ INR 77200 / machine / year
C40: Grundfos Pumps India Pvt Ltd | D40: Ahmadabad | E40: Maintenance | F40: Govind Rajput | G40: 8469867330 | H40: rajput@grundfos.com | I40: 16006392/002 | J40: Contract | K40: No | L40: KXIND/W/MV/MC/24106 | M40: 45641 | N40: 77200 | O40: January | P40: January | Q40: 1 | R40: 4516924874 | S40: 45717 | T40: 77200 | U40: January | V40: =Table62689345679[[#This Row],[Offer Value]]-Table62689345679[[#This Row],[PO Value]] -> 0 | W40: we have received PO for 2 years contract @ INR 77200 / machine / year
C41: Grundfos Pumps India Pvt Ltd | D41: Ahmadabad | E41: Maintenance | F41: Govind Rajput | G41: 8469867330 | H41: rajput@grundfos.com | I41: 102006293 | J41: Contract | K41: No | L41: KXIND/W/MV/MC/24106 | M41: 45641 | N41: 65100 | O41: January | P41: January | Q41: 1 | R41: 4516924874 | S41: 45717 | T41: 65100 | U41: January | V41: =Table62689345679[[#This Row],[Offer Value]]-Table62689345679[[#This Row],[PO Value]] -> 0 | W41: we have received PO for 2 years contract @ INR 65100 / machine / year
A42: 21 | B42: 45901 | C42: Mylan Laboratories LTD | D42: pithampur | E42: Maintenance | F42: Rajev Jain | G42: 9575802320 | H42: Rajev.Jain@viatris.com | I42: 18005564/001 | J42: Contract | K42: No | L42: KXIND/W/MV/MC/24105 | M42: 45640 | N42: 118335 | O42: January | P42: February | Q42: 1 | R42: 5700171274 | S42: 17/02/2025 | T42: 118335 | U42: February | V42: =Table62689345679[[#This Row],[Offer Value]]-Table62689345679[[#This Row],[PO Value]] -> 0 | W42: we have received PO for 2 years contract (2025 & 2026) @ INR 118335 / machine / year
C43: Mylan Laboratories LTD | D43: pithampur | E43: Maintenance | F43: Rajev Jain | G43: 9575802320 | H43: Rajev.Jain@viatris.com | I43: 18005564/002 | J43: Contract | K43: No | L43: KXIND/W/MV/MC/24105 | M43: 45640 | N43: 118335 | O43: January | P43: February | Q43: 1 | R43: 5700171274 | S43: 17/02/2025 | T43: 118335 | U43: February | V43: =Table62689345679[[#This Row],[Offer Value]]-Table62689345679[[#This Row],[PO Value]] -> 0 | W43: we have received PO for 2 years contract (2025 & 2026) @ INR 118335 / machine / year
C44: Mylan Laboratories LTD | D44: pithampur | E44: Maintenance | F44: Rajev Jain | G44: 9575802320 | H44: Rajev.Jain@viatris.com | I44: 20004153/001 | J44: Contract | K44: No | L44: KXIND/W/MV/MC/24105 | M44: 45640 | N44: 118335 | O44: January | P44: February | Q44: 1 | R44: 5700171274 | S44: 17/02/2025 | T44: 118335 | U44: February | V44: =Table62689345679[[#This Row],[Offer Value]]-Table62689345679[[#This Row],[PO Value]] -> 0 | W44: we have received PO for 2 years contract (2025 & 2026) @ INR 118335 / machine / year
C45: Mylan Laboratories LTD | D45: pithampur | E45: Maintenance | F45: Rajev Jain | G45: 9575802320 | H45: Rajev.Jain@viatris.com | I45: 20004153/002 | J45: Contract | K45: No | L45: KXIND/W/MV/MC/24105 | M45: 45640 | N45: 118335 | O45: January | P45: February | Q45: 1 | R45: 5700171274 | S45: 17/02/2025 | T45: 118335 | U45: February | V45: =Table62689345679[[#This Row],[Offer Value]]-Table62689345679[[#This Row],[PO Value]] -> 0 | W45: we have received PO for 2 years contract (2025 & 2026) @ INR 118335 / machine / year
C46: Mylan Laboratories LTD | D46: pithampur | E46: Maintenance | F46: Rajev Jain | G46: 9575802320 | H46: Rajev.Jain@viatris.com | I46: 21003856/001 | J46: Contract | K46: No | L46: KXIND/W/MV/MC/24105 | M46: 45640 | N46: 118335 | O46: January | P46: February | Q46: 1 | R46: 5700171274 | S46: 17/02/2025 | T46: 118335 | U46: February | V46: =Table62689345679[[#This Row],[Offer Value]]-Table62689345679[[#This Row],[PO Value]] -> 0 | W46: we have received PO for 2 years contract (2025 & 2026) @ INR 118335 / machine / year
A47: 22 | B47: 45901 | C47: Force Motors Ltd | D47: pithampur | E47: Maintenance | F47: Manoj Verma | G47: 9575300235 | H47: mverma@forcemotors.com | I47: 15005798/001 | J47: Contract | K47: Yes | L47: KXIND/W/MV/MC/24093 | M47: 45615 | N47: 62500 | O47: January | P47: January | Q47: 1 | R47: 6460007868 | S47: 45652 | T47: 60000 | U47: January | V47: 0
A48: 23 | B48: 45901 | C48: Hitachi Energy India Ltd | D48: Vadodara | E48: Maintenance | F48: Parth Bhatwadekar | G48: 9909972542 | H48: parth.bhatwadekar@hitachienergy.com | I48: 12005859/001 | J48: Midlife Upgrade | K48: Yes | L48: KXIND/W/MV/MLU/24080 | M48: 45551 | N48: 694970 | O48: January | P48: May | Q48: 1 | R48: 7000147895 | S48: 45662 | T48: 660221 | U48: May | V48: 0 | Z48: yes | AA48: yes
A49: 24 | B49: 45670 | C49: Hindustan Aeronautics LTD | D49: Bengaluru | E49: Purchase | F49: Arivalagan S | H49: imm_commercial.engines@hal-india.co.in | I49: 21000483/004 | J49: Contract | K49: Yes | L49: KRIND/S/MC/ASK2300039 R2 | M49: 45459 | N49: 142000 | O49: January | P49: January | Q49: 1 | R49: 16882528 | S49: 45670 | T49: 142000 | U49: January | V49: =Table62689345679[[#This Row],[Offer Value]]-Table62689345679[[#This Row],[PO Value]] -> 0
A50: 25 | B50: 45674 | C50: Burckhardt Compression | D50: Vadodara | E50: Purchase | F50: Hardik Jadav | G50: 9409775475 | H50: Hardik.jadav@burckhardtcompression.com | I50: 18005150 / 001 | J50: SPP | K50: No | L50: KXIND/W/MV/SPP/24091 | M50: 45589 | N50: 242600 | O50: January | P50: January | Q50: 1 | R50: 10169675 | S50: 45673 | T50: 223192 | U50: January | V50: 0 | Y50: 23/1/2025
A51: 26 | B51: 45680 | C51: PRASAD RAPID INDIA PRIVATE LIMITED | D51: Ahmadabad | E51: Purchase | F51: Darshak Sathvara | G51: 9099031719 | H51: purchase03-pmpl@prasadgroup.com | I51: 12006484/001 | J51: BD Charges | K51: No | L51: KXIND/W/MV/OTH/25003 | M51: 45680 | N51: 106000 | O51: January | P51: January | Q51: 1 | R51: CAPITAL/3 | S51: 45685 | T51: 100700 | U51: January | V51: 0
A52: 27 | B52: 45688 | C52: PRASAD RAPID INDIA PRIVATE LIMITED | D52: Ahmadabad | E52: Purchase | F52: Darshak Sathvara | G52: 9099031719 | H52: purchase03-pmpl@prasadgroup.com | I52: 12006484/001 | J52: SPP | K52: Yes | L52: KXIND/W/MV/SPP/25004 | M52: 45688 | N52: 302490 | O52: January | P52: February | Q52: 1 | R52: CAPITAL/4 | S52: 45749 | T52: 287365 | U52: February | V52: 0 | Y52: 45993
A53: 28 | B53: 45932 | C53: Secure Meters Limited | D53: Udaipur | E53: Stores | F53: Madan Mohan Singh | G53: 9414738104 | H53: Madan.Singh@Securemeters.Com | I53: 16000992/001 | J53: Contract | K53: No | L53: KXIND/W/MV/MC/25005 - R1 | M53: 17/04/2025 | N53: 83200 | O53: April | P53: April | Q53: 1 | R53: 2102500018 | S53: 45692 | T53: 83200 | U53: April | V53: =Table62689345679[[#This Row],[Offer Value]]-Table62689345679[[#This Row],[PO Value]] -> 0
